Workbook

Sheet Output >>

Sheet 1. Income Statement
Q5: FY | AD5: FY | AO5: YTD | AP5: TTM
B6: ($'000s) | E6: 44957 | F6: =EOMONTH(E6,1) -> 44985 | G6: =EOMONTH(F6,1) -> 45016 | H6: =EOMONTH(G6,1) -> 45046 | I6: =EOMONTH(H6,1) -> 45077 | J6: =EOMONTH(I6,1) -> 45107 | K6: =EOMONTH(J6,1) -> 45138 | L6: =EOMONTH(K6,1) -> 45169 | M6: =EOMONTH(L6,1) -> 45199 | ... P6: =EOMONTH(O6,1) -> 45291 | Q6: =YEAR(P6) -> 2023 | R6: =EOMONTH(P6,1) -> 45322 | S6: =EOMONTH(R6,1) -> 45351 | T6: =EOMONTH(S6,1) -> 45382 | U6: =EOMONTH(T6,1) -> 45412 | V6: =EOMONTH(U6,1) -> 45443 | W6: =EOMONTH(V6,1) -> 45473 | X6: =EOMONTH(W6,1) -> 45504 | Y6: =EOMONTH(X6,1) -> 45535 | Z6: =EOMONTH(Y6,1) -> 45565 | ... AC6: =EOMONTH(AB6,1) -> 45657 | AD6: =YEAR(AC6) -> 2024 | AE6: =EOMONTH(AC6,1) -> 45688 | AF6: =EOMONTH(AE6,1) -> 45716 | AG6: =EOMONTH(AF6,1) -> 45747 | AH6: =EOMONTH(AG6,1) -> 45777 | AI6: =EOMONTH(AH6,1) -> 45808 | AJ6: =EOMONTH(AI6,1) -> 45838 | AK6: =EOMONTH(AJ6,1) -> 45869 | AL6: =EOMONTH(AK6,1) -> 45900 | AM6: =EOMONTH(AL6,1) -> 45930 | AN6: =EOMONTH(AM6,1) -> 45961 | AO6: =+AN6 -> 45961 | AP6: =+AO6 -> 45961 | AR6: SUMIF Match
B8: Revenue
B9: =+AR9 -> Fire Sprinkler Installation | E9: =SUMIF('Income Statement Source'!$C:$C,'1. Income Statement'!$AR9,'Income Statement Source'!G:G)/1000 -> 94.66262 | F9: =SUMIF('Income Statement Source'!$C:$C,'1. Income Statement'!$AR9,'Income Statement Source'!H:H)/1000 -> 97.62104 | G9: =SUMIF('Income Statement Source'!$C:$C,'1. Income Statement'!$AR9,'Income Statement Source'!I:I)/1000 -> 109.05163 | H9: =SUMIF('Income Statement Source'!$C:$C,'1. Income Statement'!$AR9,'Income Statement Source'!J:J)/1000 -> 116.69817 | I9: =SUMIF('Income Statement Source'!$C:$C,'1. Income Statement'!$AR9,'Income Statement Source'!K:K)/1000 -> 129.38949 | J9: =SUMIF('Income Statement Source'!$C:$C,'1. Income Statement'!$AR9,'Income Statement Source'!L:L)/1000 -> 139.20879 | K9: =SUMIF('Income Statement Source'!$C:$C,'1. Income Statement'!$AR9,'Income Statement Source'!M:M)/1000 -> 128.77655 | L9: =SUMIF('Income Statement Source'!$C:$C,'1. Income Statement'!$AR9,'Income Statement Source'!N:N)/1000 -> 121.31438 | M9: =SUMIF('Income Statement Source'!$C:$C,'1. Income Statement'!$AR9,'Income Statement Source'!O:O)/1000 -> 132.06497 | N9: =SUMIF('Income Statement Source'!$C:$C,'1. Income Statement'!$AR9,'Income Statement Source'!P:P)/1000 -> 115.39684 | O9: =SUMIF('Income Statement Source'!$C:$C,'1. Income Statement'!$AR9,'Income Statement Source'!Q:Q)/1000 -> 92.35307 | P9: =SUMIF('Income Statement Source'!$C:$C,'1. Income Statement'!$AR9,'Income Statement Source'!R:R)/1000 -> 99.50006 | Q9: =SUM(E9:P9) -> 1376.0376 | R9: =SUMIF('Income Statement Source'!$C:$C,'1. Income Statement'!$AR9,'Income Statement Source'!T:T)/1000 -> 121.5151 | S9: =SUMIF('Income Statement Source'!$C:$C,'1. Income Statement'!$AR9,'Income Statement Source'!U:U)/1000 -> 125.70488 | T9: =SUMIF('Income Statement Source'!$C:$C,'1. Income Statement'!$AR9,'Income Statement Source'!V:V)/1000 -> 139.28441 | U9: =SUMIF('Income Statement Source'!$C:$C,'1. Income Statement'!$AR9,'Income Statement Source'!W:W)/1000 -> 169.39376 | V9: =SUMIF('Income Statement Source'!$C:$C,'1. Income Statement'!$AR9,'Income Statement Source'!X:X)/1000 -> 179.57191 | W9: =SUMIF('Income Statement Source'!$C:$C,'1. Income Statement'!$AR9,'Income Statement Source'!Y:Y)/1000 -> 205.64962 | X9: =SUMIF('Income Statement Source'!$C:$C,'1. Income Statement'!$AR9,'Income Statement Source'!Z:Z)/1000 -> 206.52219 | Y9: =SUMIF('Income Statement Source'!$C:$C,'1. Income Statement'!$AR9,'Income Statement Source'!AA:AA)/1000 -> 204.1675 | Z9: =SUMIF('Income Statement Source'!$C:$C,'1. Income Statement'!$AR9,'Income Statement Source'!AB:AB)/1000 -> 172.58198 | AA9: =SUMIF('Income Statement Source'!$C:$C,'1. Income Statement'!$AR9,'Income Statement Source'!AC:AC)/1000 -> 149.03408 | AB9: =SUMIF('Income Statement Source'!$C:$C,'1. Income Statement'!$AR9,'Income Statement Source'!AD:AD)/1000 -> 150.49911 | AC9: =SUMIF('Income Statement Source'!$C:$C,'1. Income Statement'!$AR9,'Income Statement Source'!AE:AE)/1000 -> 122.23012 | AD9: =SUM(R9:AC9) -> 1946.1547 | AE9: =SUMIF('Income Statement Source'!$C:$C,'1. Income Statement'!$AR9,'Income Statement Source'!AG:AG)/1000 -> 127.52364 | AF9: =SUMIF('Income Statement Source'!$C:$C,'1. Income Statement'!$AR9,'Income Statement Source'!AH:AH)/1000 -> 128.71096 | AG9: =SUMIF('Income Statement Source'!$C:$C,'1. Income Statement'!$AR9,'Income Statement Source'!AI:AI)/1000 -> 154.37443 | AH9: =SUMIF('Income Statement Source'!$C:$C,'1. Income Statement'!$AR9,'Income Statement Source'!AJ:AJ)/1000 -> 180.38214 | AI9: =SUMIF('Income Statement Source'!$C:$C,'1. Income Statement'!$AR9,'Income Statement Source'!AK:AK)/1000 -> 173.05318 | AJ9: =SUMIF('Income Statement Source'!$C:$C,'1. Income Statement'!$AR9,'Income Statement Source'!AL:AL)/1000 -> 206.02639 | AK9: =SUMIF('Income Statement Source'!$C:$C,'1. Income Statement'!$AR9,'Income Statement Source'!AM:AM)/1000 -> 204.11108 | AL9: =SUMIF('Income Statement Source'!$C:$C,'1. Income Statement'!$AR9,'Income Statement Source'!AN:AN)/1000 -> 179.90498 | AM9: =SUMIF('Income Statement Source'!$C:$C,'1. Income Statement'!$AR9,'Income Statement Source'!AO:AO)/1000 -> 193.30511 | AN9: =SUMIF('Income Statement Source'!$C:$C,'1. Income Statement'!$AR9,'Income Statement Source'!AP:AP)/1000 -> 176.64857 | AO9: =SUM(AE9:AN9) -> 1724.0405 | AP9: =SUM(AO9,AB9:AC9) -> 1996.7697 | AR9: Fire Sprinkler Installation
E10: =IFERROR(E9/E$19,0) -> 0.4982872 | F10: =IFERROR(F9/F$19,0) -> 0.42951932 | G10: =IFERROR(G9/G$19,0) -> 0.35450626 | H10: =IFERROR(H9/H$19,0) -> 0.45119255 | I10: =IFERROR(I9/I$19,0) -> 0.47608696 | J10: =IFERROR(J9/J$19,0) -> 0.37802272 | K10: =IFERROR(K9/K$19,0) -> 0.4257124 | L10: =IFERROR(L9/L$19,0) -> 0.4376064 | ... AP10: =IFERROR(AP9/AP$19,0) -> 0.47079517
B11: =+AR11 -> Fire Alarm Installation | E11: =SUMIF('Income Statement Source'!$C:$C,'1. Income Statement'!$AR11,'Income Statement Source'!G:G)/1000 -> 77.60896 | F11: =SUMIF('Income Statement Source'!$C:$C,'1. Income Statement'!$AR11,'Income Statement Source'!H:H)/1000 -> 86.5478 | G11: =SUMIF('Income Statement Source'!$C:$C,'1. Income Statement'!$AR11,'Income Statement Source'!I:I)/1000 -> 84.03452 | H11: =SUMIF('Income Statement Source'!$C:$C,'1. Income Statement'!$AR11,'Income Statement Source'!J:J)/1000 -> 100.14304 | I11: =SUMIF('Income Statement Source'!$C:$C,'1. Income Statement'!$AR11,'Income Statement Source'!K:K)/1000 -> 101.76326 | J11: =SUMIF('Income Statement Source'!$C:$C,'1. Income Statement'!$AR11,'Income Statement Source'!L:L)/1000 -> 116.44295 | K11: =SUMIF('Income Statement Source'!$C:$C,'1. Income Statement'!$AR11,'Income Statement Source'!M:M)/1000 -> 129.76729 | L11: =SUMIF('Income Statement Source'!$C:$C,'1. Income Statement'!$AR11,'Income Statement Source'!N:N)/1000 -> 114.08084 | M11: =SUMIF('Income Statement Source'!$C:$C,'1. Income Statement'!$AR11,'Income Statement Source'!O:O)/1000 -> 107.71489 | N11: =SUMIF('Income Statement Source'!$C:$C,'1. Income Statement'!$AR11,'Income Statement Source'!P:P)/1000 -> 108.33409 | O11: =SUMIF('Income Statement Source'!$C:$C,'1. Income Statement'!$AR11,'Income Statement Source'!Q:Q)/1000 -> 89.03694 | P11: =SUMIF('Income Statement Source'!$C:$C,'1. Income Statement'!$AR11,'Income Statement Source'!R:R)/1000 -> 77.21956 | Q11: =SUM(E11:P11) -> 1192.6941 | R11: =SUMIF('Income Statement Source'!$C:$C,'1. Income Statement'!$AR11,'Income Statement Source'!T:T)/1000 -> 85.34755 | S11: =SUMIF('Income Statement Source'!$C:$C,'1. Income Statement'!$AR11,'Income Statement Source'!U:U)/1000 -> 86.64764 | T11: =SUMIF('Income Statement Source'!$C:$C,'1. Income Statement'!$AR11,'Income Statement Source'!V:V)/1000 -> 94.09094 | U11: =SUMIF('Income Statement Source'!$C:$C,'1. Income Statement'!$AR11,'Income Statement Source'!W:W)/1000 -> 105.72795 | V11: =SUMIF('Income Statement Source'!$C:$C,'1. Income Statement'!$AR11,'Income Statement Source'!X:X)/1000 -> 117.38177 | W11: =SUMIF('Income Statement Source'!$C:$C,'1. Income Statement'!$AR11,'Income Statement Source'!Y:Y)/1000 -> 119.70302 | X11: =SUMIF('Income Statement Source'!$C:$C,'1. Income Statement'!$AR11,'Income Statement Source'!Z:Z)/1000 -> 117.26527 | Y11: =SUMIF('Income Statement Source'!$C:$C,'1. Income Statement'!$AR11,'Income Statement Source'!AA:AA)/1000 -> 130.83706 | Z11: =SUMIF('Income Statement Source'!$C:$C,'1. Income Statement'!$AR11,'Income Statement Source'!AB:AB)/1000 -> 108.45174 | AA11: =SUMIF('Income Statement Source'!$C:$C,'1. Income Statement'!$AR11,'Income Statement Source'!AC:AC)/1000 -> 113.57406 | AB11: =SUMIF('Income Statement Source'!$C:$C,'1. Income Statement'!$AR11,'Income Statement Source'!AD:AD)/1000 -> 98.33674 | AC11: =SUMIF('Income Statement Source'!$C:$C,'1. Income Statement'!$AR11,'Income Statement Source'!AE:AE)/1000 -> 93.0428 | AD11: =SUM(R11:AC11) -> 1270.4065 | AE11: =SUMIF('Income Statement Source'!$C:$C,'1. Income Statement'!$AR11,'Income Statement Source'!AG:AG)/1000 -> 88.38627 | AF11: =SUMIF('Income Statement Source'!$C:$C,'1. Income Statement'!$AR11,'Income Statement Source'!AH:AH)/1000 -> 97.32335 | AG11: =SUMIF('Income Statement Source'!$C:$C,'1. Income Statement'!$AR11,'Income Statement Source'!AI:AI)/1000 -> 95.14147 | AH11: =SUMIF('Income Statement Source'!$C:$C,'1. Income Statement'!$AR11,'Income Statement Source'!AJ:AJ)/1000 -> 113.54869 | AI11: =SUMIF('Income Statement Source'!$C:$C,'1. Income Statement'!$AR11,'Income Statement Source'!AK:AK)/1000 -> 116.15574 | AJ11: =SUMIF('Income Statement Source'!$C:$C,'1. Income Statement'!$AR11,'Income Statement Source'!AL:AL)/1000 -> 132.59605 | AK11: =SUMIF('Income Statement Source'!$C:$C,'1. Income Statement'!$AR11,'Income Statement Source'!AM:AM)/1000 -> 126.67882 | AL11: =SUMIF('Income Statement Source'!$C:$C,'1. Income Statement'!$AR11,'Income Statement Source'!AN:AN)/1000 -> 120.13104 | AM11: =SUMIF('Income Statement Source'!$C:$C,'1. Income Statement'!$AR11,'Income Statement Source'!AO:AO)/1000 -> 116.06038 | AN11: =SUMIF('Income Statement Source'!$C:$C,'1. Income Statement'!$AR11,'Income Statement Source'!AP:AP)/1000 -> 104.1304 | AO11: =SUM(AE11:AN11) -> 1110.1522 | AP11: =SUM(AO11,AB11:AC11) -> 1301.5317 | AR11: Fire Alarm Installation
E12: =IFERROR(E11/E$19,0) -> 0.40851977 | F12: =IFERROR(F11/F$19,0) -> 0.38079857 | G12: =IFERROR(G11/G$19,0) -> 0.27318036 | H12: =IFERROR(H11/H$19,0) -> 0.38718511 | I12: =IFERROR(I11/I$19,0) -> 0.3744366 | J12: =IFERROR(J11/J$19,0) -> 0.31620188 | K12: =IFERROR(K11/K$19,0) -> 0.42898761 | L12: =IFERROR(L11/L$19,0) -> 0.41151351 | ... AP12: =IFERROR(AP11/AP$19,0) -> 0.30687308
B13: =+AR13 -> Inspection & Testing Services | E13: =SUMIF('Income Statement Source'!$C:$C,'1. Income Statement'!$AR13,'Income Statement Source'!G:G)/1000 -> 42.70444 | F13: =SUMIF('Income Statement Source'!$C:$C,'1. Income Statement'!$AR13,'Income Statement Source'!H:H)/1000 -> 43.1109 | G13: =SUMIF('Income Statement Source'!$C:$C,'1. Income Statement'!$AR13,'Income Statement Source'!I:I)/1000 -> 43.65919 | H13: =SUMIF('Income Statement Source'!$C:$C,'1. Income Statement'!$AR13,'Income Statement Source'!J:J)/1000 -> 41.80262 | I13: =SUMIF('Income Statement Source'!$C:$C,'1. Income Statement'!$AR13,'Income Statement Source'!K:K)/1000 -> 40.62426 | J13: =SUMIF('Income Statement Source'!$C:$C,'1. Income Statement'!$AR13,'Income Statement Source'!L:L)/1000 -> 44.83388 | K13: =SUMIF('Income Statement Source'!$C:$C,'1. Income Statement'!$AR13,'Income Statement Source'!M:M)/1000 -> 43.95275 | L13: =SUMIF('Income Statement Source'!$C:$C,'1. Income Statement'!$AR13,'Income Statement Source'!N:N)/1000 -> 41.82737 | M13: =SUMIF('Income Statement Source'!$C:$C,'1. Income Statement'!$AR13,'Income Statement Source'!O:O)/1000 -> 43.05176 | N13: =SUMIF('Income Statement Source'!$C:$C,'1. Income Statement'!$AR13,'Income Statement Source'!P:P)/1000 -> 43.42413 | O13: =SUMIF('Income Statement Source'!$C:$C,'1. Income Statement'!$AR13,'Income Statement Source'!Q:Q)/1000 -> 43.90217 | P13: =SUMIF('Income Statement Source'!$C:$C,'1. Income Statement'!$AR13,'Income Statement Source'!R:R)/1000 -> 43.46634 | Q13: =SUM(E13:P13) -> 516.35981 | R13: =SUMIF('Income Statement Source'!$C:$C,'1. Income Statement'!$AR13,'Income Statement Source'!T:T)/1000 -> 44.16799 | S13: =SUMIF('Income Statement Source'!$C:$C,'1. Income Statement'!$AR13,'Income Statement Source'!U:U)/1000 -> 45.85822 | T13: =SUMIF('Income Statement Source'!$C:$C,'1. Income Statement'!$AR13,'Income Statement Source'!V:V)/1000 -> 47.05096 | U13: =SUMIF('Income Statement Source'!$C:$C,'1. Income Statement'!$AR13,'Income Statement Source'!W:W)/1000 -> 44.57798 | V13: =SUMIF('Income Statement Source'!$C:$C,'1. Income Statement'!$AR13,'Income Statement Source'!X:X)/1000 -> 43.08885 | W13: =SUMIF('Income Statement Source'!$C:$C,'1. Income Statement'!$AR13,'Income Statement Source'!Y:Y)/1000 -> 43.93139 | X13: =SUMIF('Income Statement Source'!$C:$C,'1. Income Statement'!$AR13,'Income Statement Source'!Z:Z)/1000 -> 47.31837 | Y13: =SUMIF('Income Statement Source'!$C:$C,'1. Income Statement'!$AR13,'Income Statement Source'!AA:AA)/1000 -> 46.08266 | Z13: =SUMIF('Income Statement Source'!$C:$C,'1. Income Statement'!$AR13,'Income Statement Source'!AB:AB)/1000 -> 43.8666 | AA13: =SUMIF('Income Statement Source'!$C:$C,'1. Income Statement'!$AR13,'Income Statement Source'!AC:AC)/1000 -> 42.68755 | AB13: =SUMIF('Income Statement Source'!$C:$C,'1. Income Statement'!$AR13,'Income Statement Source'!AD:AD)/1000 -> 43.86092 | AC13: =SUMIF('Income Statement Source'!$C:$C,'1. Income Statement'!$AR13,'Income Statement Source'!AE:AE)/1000 -> 46.83949 | AD13: =SUM(R13:AC13) -> 539.33098 | AE13: =SUMIF('Income Statement Source'!$C:$C,'1. Income Statement'!$AR13,'Income Statement Source'!AG:AG)/1000 -> 49.42844 | AF13: =SUMIF('Income Statement Source'!$C:$C,'1. Income Statement'!$AR13,'Income Statement Source'!AH:AH)/1000 -> 47.0902 | AG13: =SUMIF('Income Statement Source'!$C:$C,'1. Income Statement'!$AR13,'Income Statement Source'!AI:AI)/1000 -> 46.45931 | AH13: =SUMIF('Income Statement Source'!$C:$C,'1. Income Statement'!$AR13,'Income Statement Source'!AJ:AJ)/1000 -> 46.91218 | AI13: =SUMIF('Income Statement Source'!$C:$C,'1. Income Statement'!$AR13,'Income Statement Source'!AK:AK)/1000 -> 48.69308 | AJ13: =SUMIF('Income Statement Source'!$C:$C,'1. Income Statement'!$AR13,'Income Statement Source'!AL:AL)/1000 -> 47.85082 | AK13: =SUMIF('Income Statement Source'!$C:$C,'1. Income Statement'!$AR13,'Income Statement Source'!AM:AM)/1000 -> 45.19238 | AL13: =SUMIF('Income Statement Source'!$C:$C,'1. Income Statement'!$AR13,'Income Statement Source'!AN:AN)/1000 -> 47.09875 | AM13: =SUMIF('Income Statement Source'!$C:$C,'1. Income Statement'!$AR13,'Income Statement Source'!AO:AO)/1000 -> 47.70437 | AN13: =SUMIF('Income Statement Source'!$C:$C,'1. Income Statement'!$AR13,'Income Statement Source'!AP:AP)/1000 -> 48.08421 | AO13: =SUM(AE13:AN13) -> 474.51374 | AP13: =SUM(AO13,AB13:AC13) -> 565.21415 | AR13: Inspection & Testing Services
E14: =IFERROR(E13/E$19,0) -> 0.22478858 | F14: =IFERROR(F13/F$19,0) -> 0.18968211 | G14: =IFERROR(G13/G$19,0) -> 0.14192778 | H14: =IFERROR(H13/H$19,0) -> 0.16162234 | I14: =IFERROR(I13/I$19,0) -> 0.14947644 | J14: =IFERROR(J13/J$19,0) -> 0.1217468 | K14: =IFERROR(K13/K$19,0) -> 0.14529999 | L14: =IFERROR(L13/L$19,0) -> 0.15088009 | ... AP14: =IFERROR(AP13/AP$19,0) -> 0.13326529
B15: =+AR15 -> Maintenance Contracts | E15: =SUMIF('Income Statement Source'!$C:$C,'1. Income Statement'!$AR15,'Income Statement Source'!G:G)/1000 -> 0 | F15: =SUMIF('Income Statement Source'!$C:$C,'1. Income Statement'!$AR15,'Income Statement Source'!H:H)/1000 -> 0 | G15: =SUMIF('Income Statement Source'!$C:$C,'1. Income Statement'!$AR15,'Income Statement Source'!I:I)/1000 -> 70.87019 | H15: =SUMIF('Income Statement Source'!$C:$C,'1. Income Statement'!$AR15,'Income Statement Source'!J:J)/1000 -> 0 | I15: =SUMIF('Income Statement Source'!$C:$C,'1. Income Statement'!$AR15,'Income Statement Source'!K:K)/1000 -> 0 | J15: =SUMIF('Income Statement Source'!$C:$C,'1. Income Statement'!$AR15,'Income Statement Source'!L:L)/1000 -> 67.76947 | K15: =SUMIF('Income Statement Source'!$C:$C,'1. Income Statement'!$AR15,'Income Statement Source'!M:M)/1000 -> 0 | L15: =SUMIF('Income Statement Source'!$C:$C,'1. Income Statement'!$AR15,'Income Statement Source'!N:N)/1000 -> 0 | M15: =SUMIF('Income Statement Source'!$C:$C,'1. Income Statement'!$AR15,'Income Statement Source'!O:O)/1000 -> 71.44845 | N15: =SUMIF('Income Statement Source'!$C:$C,'1. Income Statement'!$AR15,'Income Statement Source'!P:P)/1000 -> 0 | O15: =SUMIF('Income Statement Source'!$C:$C,'1. Income Statement'!$AR15,'Income Statement Source'!Q:Q)/1000 -> 0 | P15: =SUMIF('Income Statement Source'!$C:$C,'1. Income Statement'!$AR15,'Income Statement Source'!R:R)/1000 -> 70.38265 | Q15: =SUM(E15:P15) -> 280.47076 | R15: =SUMIF('Income Statement Source'!$C:$C,'1. Income Statement'!$AR15,'Income Statement Source'!T:T)/1000 -> 0 | S15: =SUMIF('Income Statement Source'!$C:$C,'1. Income Statement'!$AR15,'Income Statement Source'!U:U)/1000 -> 0 | T15: =SUMIF('Income Statement Source'!$C:$C,'1. Income Statement'!$AR15,'Income Statement Source'!V:V)/1000 -> 72.44887 | U15: =SUMIF('Income Statement Source'!$C:$C,'1. Income Statement'!$AR15,'Income Statement Source'!W:W)/1000 -> 0 | V15: =SUMIF('Income Statement Source'!$C:$C,'1. Income Statement'!$AR15,'Income Statement Source'!X:X)/1000 -> 0 | W15: =SUMIF('Income Statement Source'!$C:$C,'1. Income Statement'!$AR15,'Income Statement Source'!Y:Y)/1000 -> 68.36416 | X15: =SUMIF('Income Statement Source'!$C:$C,'1. Income Statement'!$AR15,'Income Statement Source'!Z:Z)/1000 -> 0 | Y15: =SUMIF('Income Statement Source'!$C:$C,'1. Income Statement'!$AR15,'Income Statement Source'!AA:AA)/1000 -> 0 | Z15: =SUMIF('Income Statement Source'!$C:$C,'1. Income Statement'!$AR15,'Income Statement Source'!AB:AB)/1000 -> 73.20211 | AA15: =SUMIF('Income Statement Source'!$C:$C,'1. Income Statement'!$AR15,'Income Statement Source'!AC:AC)/1000 -> 0 | AB15: =SUMIF('Income Statement Source'!$C:$C,'1. Income Statement'!$AR15,'Income Statement Source'!AD:AD)/1000 -> 0 | AC15: =SUMIF('Income Statement Source'!$C:$C,'1. Income Statement'!$AR15,'Income Statement Source'!AE:AE)/1000 -> 75.40684 | AD15: =SUM(R15:AC15) -> 289.42198 | AE15: =SUMIF('Income Statement Source'!$C:$C,'1. Income Statement'!$AR15,'Income Statement Source'!AG:AG)/1000 -> 0 | AF15: =SUMIF('Income Statement Source'!$C:$C,'1. Income Statement'!$AR15,'Income Statement Source'!AH:AH)/1000 -> 0 | AG15: =SUMIF('Income Statement Source'!$C:$C,'1. Income Statement'!$AR15,'Income Statement Source'!AI:AI)/1000 -> 76.3279 | AH15: =SUMIF('Income Statement Source'!$C:$C,'1. Income Statement'!$AR15,'Income Statement Source'!AJ:AJ)/1000 -> 0 | AI15: =SUMIF('Income Statement Source'!$C:$C,'1. Income Statement'!$AR15,'Income Statement Source'!AK:AK)/1000 -> 0 | AJ15: =SUMIF('Income Statement Source'!$C:$C,'1. Income Statement'!$AR15,'Income Statement Source'!AL:AL)/1000 -> 78.2589 | AK15: =SUMIF('Income Statement Source'!$C:$C,'1. Income Statement'!$AR15,'Income Statement Source'!AM:AM)/1000 -> 0 | AL15: =SUMIF('Income Statement Source'!$C:$C,'1. Income Statement'!$AR15,'Income Statement Source'!AN:AN)/1000 -> 0 | AM15: =SUMIF('Income Statement Source'!$C:$C,'1. Income Statement'!$AR15,'Income Statement Source'!AO:AO)/1000 -> 72.9321 | AN15: =SUMIF('Income Statement Source'!$C:$C,'1. Income Statement'!$AR15,'Income Statement Source'!AP:AP)/1000 -> 0 | AO15: =SUM(AE15:AN15) -> 227.5189 | AP15: =SUM(AO15,AB15:AC15) -> 302.92574 | AR15: Maintenance Contracts
E16: =IFERROR(E15/E$19,0) -> 0 | F16: =IFERROR(F15/F$19,0) -> 0 | G16: =IFERROR(G15/G$19,0) -> 0.23038561 | H16: =IFERROR(H15/H$19,0) -> 0 | I16: =IFERROR(I15/I$19,0) -> 0 | J16: =IFERROR(J15/J$19,0) -> 0.1840286 | K16: =IFERROR(K15/K$19,0) -> 0 | L16: =IFERROR(L15/L$19,0) -> 0 | ... AP16: =IFERROR(AP15/AP$19,0) -> 0.071423347
B17: =+AR17 -> WIP Adjustment | E17: =SUMIF('Income Statement Source'!$C:$C,'1. Income Statement'!$AR17,'Income Statement Source'!G:G)/1000 -> -25 | F17: =SUMIF('Income Statement Source'!$C:$C,'1. Income Statement'!$AR17,'Income Statement Source'!H:H)/1000 -> 0 | G17: =SUMIF('Income Statement Source'!$C:$C,'1. Income Statement'!$AR17,'Income Statement Source'!I:I)/1000 -> 0 | H17: =SUMIF('Income Statement Source'!$C:$C,'1. Income Statement'!$AR17,'Income Statement Source'!J:J)/1000 -> 0 | I17: =SUMIF('Income Statement Source'!$C:$C,'1. Income Statement'!$AR17,'Income Statement Source'!K:K)/1000 -> 0 | J17: =SUMIF('Income Statement Source'!$C:$C,'1. Income Statement'!$AR17,'Income Statement Source'!L:L)/1000 -> 0 | K17: =SUMIF('Income Statement Source'!$C:$C,'1. Income Statement'!$AR17,'Income Statement Source'!M:M)/1000 -> 0 | L17: =SUMIF('Income Statement Source'!$C:$C,'1. Income Statement'!$AR17,'Income Statement Source'!N:N)/1000 -> 0 | M17: =SUMIF('Income Statement Source'!$C:$C,'1. Income Statement'!$AR17,'Income Statement Source'!O:O)/1000 -> 0 | N17: =SUMIF('Income Statement Source'!$C:$C,'1. Income Statement'!$AR17,'Income Statement Source'!P:P)/1000 -> 0 | O17: =SUMIF('Income Statement Source'!$C:$C,'1. Income Statement'!$AR17,'Income Statement Source'!Q:Q)/1000 -> 0 | P17: =SUMIF('Income Statement Source'!$C:$C,'1. Income Statement'!$AR17,'Income Statement Source'!R:R)/1000 -> 48.52345 | Q17: =SUM(E17:P17) -> 23.52345 | R17: =SUMIF('Income Statement Source'!$C:$C,'1. Income Statement'!$AR17,'Income Statement Source'!T:T)/1000 -> -48.52345 | S17: =SUMIF('Income Statement Source'!$C:$C,'1. Income Statement'!$AR17,'Income Statement Source'!U:U)/1000 -> 0 | T17: =SUMIF('Income Statement Source'!$C:$C,'1. Income Statement'!$AR17,'Income Statement Source'!V:V)/1000 -> 0 | U17: =SUMIF('Income Statement Source'!$C:$C,'1. Income Statement'!$AR17,'Income Statement Source'!W:W)/1000 -> 0 | V17: =SUMIF('Income Statement Source'!$C:$C,'1. Income Statement'!$AR17,'Income Statement Source'!X:X)/1000 -> 0 | W17: =SUMIF('Income Statement Source'!$C:$C,'1. Income Statement'!$AR17,'Income Statement Source'!Y:Y)/1000 -> 0 | X17: =SUMIF('Income Statement Source'!$C:$C,'1. Income Statement'!$AR17,'Income Statement Source'!Z:Z)/1000 -> 0 | Y17: =SUMIF('Income Statement Source'!$C:$C,'1. Income Statement'!$AR17,'Income Statement Source'!AA:AA)/1000 -> 0 | Z17: =SUMIF('Income Statement Source'!$C:$C,'1. Income Statement'!$AR17,'Income Statement Source'!AB:AB)/1000 -> 0 | AA17: =SUMIF('Income Statement Source'!$C:$C,'1. Income Statement'!$AR17,'Income Statement Source'!AC:AC)/1000 -> 0 | AB17: =SUMIF('Income Statement Source'!$C:$C,'1. Income Statement'!$AR17,'Income Statement Source'!AD:AD)/1000 -> 0 | AC17: =SUMIF('Income Statement Source'!$C:$C,'1. Income Statement'!$AR17,'Income Statement Source'!AE:AE)/1000 -> 52.89123 | AD17: =SUM(R17:AC17) -> 4.36778 | AE17: =SUMIF('Income Statement Source'!$C:$C,'1. Income Statement'!$AR17,'Income Statement Source'!AG:AG)/1000 -> -52.89123 | AF17: =SUMIF('Income Statement Source'!$C:$C,'1. Income Statement'!$AR17,'Income Statement Source'!AH:AH)/1000 -> 9.4342 | AG17: =SUMIF('Income Statement Source'!$C:$C,'1. Income Statement'!$AR17,'Income Statement Source'!AI:AI)/1000 -> 9.34611 | AH17: =SUMIF('Income Statement Source'!$C:$C,'1. Income Statement'!$AR17,'Income Statement Source'!AJ:AJ)/1000 -> 8.09037 | AI17: =SUMIF('Income Statement Source'!$C:$C,'1. Income Statement'!$AR17,'Income Statement Source'!AK:AK)/1000 -> 7.8028 | AJ17: =SUMIF('Income Statement Source'!$C:$C,'1. Income Statement'!$AR17,'Income Statement Source'!AL:AL)/1000 -> 7.65396 | AK17: =SUMIF('Income Statement Source'!$C:$C,'1. Income Statement'!$AR17,'Income Statement Source'!AM:AM)/1000 -> 9.07126 | AL17: =SUMIF('Income Statement Source'!$C:$C,'1. Income Statement'!$AR17,'Income Statement Source'!AN:AN)/1000 -> 6.80614 | AM17: =SUMIF('Income Statement Source'!$C:$C,'1. Income Statement'!$AR17,'Income Statement Source'!AO:AO)/1000 -> 7.23004 | AN17: =SUMIF('Income Statement Source'!$C:$C,'1. Income Statement'!$AR17,'Income Statement Source'!AP:AP)/1000 -> 9.39436 | AO17: =SUM(AE17:AN17) -> 21.93801 | AP17: =SUM(AO17,AB17:AC17) -> 74.82924 | AR17: WIP Adjustment
E18: =IFERROR(E17/E$19,0) -> -0.13159556 | F18: =IFERROR(F17/F$19,0) -> 0 | G18: =IFERROR(G17/G$19,0) -> 0 | H18: =IFERROR(H17/H$19,0) -> 0 | I18: =IFERROR(I17/I$19,0) -> 0 | J18: =IFERROR(J17/J$19,0) -> 0 | K18: =IFERROR(K17/K$19,0) -> 0 | L18: =IFERROR(L17/L$19,0) -> 0 | ... AP18: =IFERROR(AP17/AP$19,0) -> 0.017643119
B19: =+B8 -> Revenue | E19: =SUM(E9,E11,E13,E15,E17) -> 189.97602 | F19: =SUM(F9,F11,F13,F15,F17) -> 227.27974 | G19: =SUM(G9,G11,G13,G15,G17) -> 307.61553 | H19: =SUM(H9,H11,H13,H15,H17) -> 258.64383 | I19: =SUM(I9,I11,I13,I15,I17) -> 271.77701 | J19: =SUM(J9,J11,J13,J15,J17) -> 368.25509 | K19: =SUM(K9,K11,K13,K15,K17) -> 302.49659 | L19: =SUM(L9,L11,L13,L15,L17) -> 277.22259 | ... AP19: =SUM(AP9,AP11,AP13,AP15,AP17) -> 4241.2706
B22: Cost of Goods Sold
B23: Materials & Equipment
B24: =+AR24 -> Sprinkler Materials & Fittings | E24: =SUMIF('Income Statement Source'!$C:$C,'1. Income Statement'!$AR24,'Income Statement Source'!G:G)/1000 -> 18.7739 | F24: =SUMIF('Income Statement Source'!$C:$C,'1. Income Statement'!$AR24,'Income Statement Source'!H:H)/1000 -> 22.36071 | G24: =SUMIF('Income Statement Source'!$C:$C,'1. Income Statement'!$AR24,'Income Statement Source'!I:I)/1000 -> 30.52923 | H24: =SUMIF('Income Statement Source'!$C:$C,'1. Income Statement'!$AR24,'Income Statement Source'!J:J)/1000 -> 26.31319 | I24: =SUMIF('Income Statement Source'!$C:$C,'1. Income Statement'!$AR24,'Income Statement Source'!K:K)/1000 -> 25.1539 | J24: =SUMIF('Income Statement Source'!$C:$C,'1. Income Statement'!$AR24,'Income Statement Source'!L:L)/1000 -> 35.27347 | K24: =SUMIF('Income Statement Source'!$C:$C,'1. Income Statement'!$AR24,'Income Statement Source'!M:M)/1000 -> 32.34572 | L24: =SUMIF('Income Statement Source'!$C:$C,'1. Income Statement'!$AR24,'Income Statement Source'!N:N)/1000 -> 27.19652 | M24: =SUMIF('Income Statement Source'!$C:$C,'1. Income Statement'!$AR24,'Income Statement Source'!O:O)/1000 -> 34.61393 | N24: =SUMIF('Income Statement Source'!$C:$C,'1. Income Statement'!$AR24,'Income Statement Source'!P:P)/1000 -> 26.91335 | O24: =SUMIF('Income Statement Source'!$C:$C,'1. Income Statement'!$AR24,'Income Statement Source'!Q:Q)/1000 -> 22.13631 | P24: =SUMIF('Income Statement Source'!$C:$C,'1. Income Statement'!$AR24,'Income Statement Source'!R:R)/1000 -> 34.79761 | Q24: =SUM(E24:P24) -> 336.40784 | R24: =SUMIF('Income Statement Source'!$C:$C,'1. Income Statement'!$AR24,'Income Statement Source'!T:T)/1000 -> 28.66928 | S24: =SUMIF('Income Statement Source'!$C:$C,'1. Income Statement'!$AR24,'Income Statement Source'!U:U)/1000 -> 36.19647 | T24: =SUMIF('Income Statement Source'!$C:$C,'1. Income Statement'!$AR24,'Income Statement Source'!V:V)/1000 -> 51.79314 | U24: =SUMIF('Income Statement Source'!$C:$C,'1. Income Statement'!$AR24,'Income Statement Source'!W:W)/1000 -> 42.45691 | V24: =SUMIF('Income Statement Source'!$C:$C,'1. Income Statement'!$AR24,'Income Statement Source'!X:X)/1000 -> 49.58224 | W24: =SUMIF('Income Statement Source'!$C:$C,'1. Income Statement'!$AR24,'Income Statement Source'!Y:Y)/1000 -> 54.22888 | X24: =SUMIF('Income Statement Source'!$C:$C,'1. Income Statement'!$AR24,'Income Statement Source'!Z:Z)/1000 -> 47.7458 | Y24: =SUMIF('Income Statement Source'!$C:$C,'1. Income Statement'!$AR24,'Income Statement Source'!AA:AA)/1000 -> 56.03896 | Z24: =SUMIF('Income Statement Source'!$C:$C,'1. Income Statement'!$AR24,'Income Statement Source'!AB:AB)/1000 -> 52.2476 | AA24: =SUMIF('Income Statement Source'!$C:$C,'1. Income Statement'!$AR24,'Income Statement Source'!AC:AC)/1000 -> 44.13816 | AB24: =SUMIF('Income Statement Source'!$C:$C,'1. Income Statement'!$AR24,'Income Statement Source'!AD:AD)/1000 -> 37.54888 | AC24: =SUMIF('Income Statement Source'!$C:$C,'1. Income Statement'!$AR24,'Income Statement Source'!AE:AE)/1000 -> 53.87737 | AD24: =SUM(R24:AC24) -> 554.52369 | AE24: =SUMIF('Income Statement Source'!$C:$C,'1. Income Statement'!$AR24,'Income Statement Source'!AG:AG)/1000 -> 22.32297 | AF24: =SUMIF('Income Statement Source'!$C:$C,'1. Income Statement'!$AR24,'Income Statement Source'!AH:AH)/1000 -> 26.3794 | AG24: =SUMIF('Income Statement Source'!$C:$C,'1. Income Statement'!$AR24,'Income Statement Source'!AI:AI)/1000 -> 39.4709 | AH24: =SUMIF('Income Statement Source'!$C:$C,'1. Income Statement'!$AR24,'Income Statement Source'!AJ:AJ)/1000 -> 33.33789 | AI24: =SUMIF('Income Statement Source'!$C:$C,'1. Income Statement'!$AR24,'Income Statement Source'!AK:AK)/1000 -> 32.72787 | AJ24: =SUMIF('Income Statement Source'!$C:$C,'1. Income Statement'!$AR24,'Income Statement Source'!AL:AL)/1000 -> 43.80515 | AK24: =SUMIF('Income Statement Source'!$C:$C,'1. Income Statement'!$AR24,'Income Statement Source'!AM:AM)/1000 -> 38.10798 | AL24: =SUMIF('Income Statement Source'!$C:$C,'1. Income Statement'!$AR24,'Income Statement Source'!AN:AN)/1000 -> 37.87525 | AM24: =SUMIF('Income Statement Source'!$C:$C,'1. Income Statement'!$AR24,'Income Statement Source'!AO:AO)/1000 -> 46.60732 | AN24: =SUMIF('Income Statement Source'!$C:$C,'1. Income Statement'!$AR24,'Income Statement Source'!AP:AP)/1000 -> 35.48698 | AO24: =SUM(AE24:AN24) -> 356.12171 | AP24: =SUM(AO24,AB24:AC24) -> 447.54796 | AR24: Sprinkler Materials & Fittings
B25: =+AR25 -> Alarm Equipment & Devices | E25: =SUMIF('Income Statement Source'!$C:$C,'1. Income Statement'!$AR25,'Income Statement Source'!G:G)/1000 -> 14.5666 | F25: =SUMIF('Income Statement Source'!$C:$C,'1. Income Statement'!$AR25,'Income Statement Source'!H:H)/1000 -> 19.50343 | G25: =SUMIF('Income Statement Source'!$C:$C,'1. Income Statement'!$AR25,'Income Statement Source'!I:I)/1000 -> 26.00369 | H25: =SUMIF('Income Statement Source'!$C:$C,'1. Income Statement'!$AR25,'Income Statement Source'!J:J)/1000 -> 20.26115 | I25: =SUMIF('Income Statement Source'!$C:$C,'1. Income Statement'!$AR25,'Income Statement Source'!K:K)/1000 -> 22.37212 | J25: =SUMIF('Income Statement Source'!$C:$C,'1. Income Statement'!$AR25,'Income Statement Source'!L:L)/1000 -> 28.26905 | K25: =SUMIF('Income Statement Source'!$C:$C,'1. Income Statement'!$AR25,'Income Statement Source'!M:M)/1000 -> 24.85563 | L25: =SUMIF('Income Statement Source'!$C:$C,'1. Income Statement'!$AR25,'Income Statement Source'!N:N)/1000 -> 20.78975 | M25: =SUMIF('Income Statement Source'!$C:$C,'1. Income Statement'!$AR25,'Income Statement Source'!O:O)/1000 -> 29.16329 | N25: =SUMIF('Income Statement Source'!$C:$C,'1. Income Statement'!$AR25,'Income Statement Source'!P:P)/1000 -> 21.53118 | O25: =SUMIF('Income Statement Source'!$C:$C,'1. Income Statement'!$AR25,'Income Statement Source'!Q:Q)/1000 -> 17.53121 | P25: =SUMIF('Income Statement Source'!$C:$C,'1. Income Statement'!$AR25,'Income Statement Source'!R:R)/1000 -> 24.99498 | Q25: =SUM(E25:P25) -> 269.84208 | R25: =SUMIF('Income Statement Source'!$C:$C,'1. Income Statement'!$AR25,'Income Statement Source'!T:T)/1000 -> 14.94188 | S25: =SUMIF('Income Statement Source'!$C:$C,'1. Income Statement'!$AR25,'Income Statement Source'!U:U)/1000 -> 20.16927 | T25: =SUMIF('Income Statement Source'!$C:$C,'1. Income Statement'!$AR25,'Income Statement Source'!V:V)/1000 -> 26.32557 | U25: =SUMIF('Income Statement Source'!$C:$C,'1. Income Statement'!$AR25,'Income Statement Source'!W:W)/1000 -> 25.80505 | V25: =SUMIF('Income Statement Source'!$C:$C,'1. Income Statement'!$AR25,'Income Statement Source'!X:X)/1000 -> 27.24572 | W25: =SUMIF('Income Statement Source'!$C:$C,'1. Income Statement'!$AR25,'Income Statement Source'!Y:Y)/1000 -> 32.45994 | X25: =SUMIF('Income Statement Source'!$C:$C,'1. Income Statement'!$AR25,'Income Statement Source'!Z:Z)/1000 -> 27.85306 | Y25: =SUMIF('Income Statement Source'!$C:$C,'1. Income Statement'!$AR25,'Income Statement Source'!AA:AA)/1000 -> 28.9749 | Z25: =SUMIF('Income Statement Source'!$C:$C,'1. Income Statement'!$AR25,'Income Statement Source'!AB:AB)/1000 -> 30.56051 | AA25: =SUMIF('Income Statement Source'!$C:$C,'1. Income Statement'!$AR25,'Income Statement Source'!AC:AC)/1000 -> 25.49331 | AB25: =SUMIF('Income Statement Source'!$C:$C,'1. Income Statement'!$AR25,'Income Statement Source'!AD:AD)/1000 -> 21.9899 | AC25: =SUMIF('Income Statement Source'!$C:$C,'1. Income Statement'!$AR25,'Income Statement Source'!AE:AE)/1000 -> 31.29619 | AD25: =SUM(R25:AC25) -> 313.1153 | AE25: =SUMIF('Income Statement Source'!$C:$C,'1. Income Statement'!$AR25,'Income Statement Source'!AG:AG)/1000 -> 15.63756 | AF25: =SUMIF('Income Statement Source'!$C:$C,'1. Income Statement'!$AR25,'Income Statement Source'!AH:AH)/1000 -> 23.6607 | AG25: =SUMIF('Income Statement Source'!$C:$C,'1. Income Statement'!$AR25,'Income Statement Source'!AI:AI)/1000 -> 31.61507 | AH25: =SUMIF('Income Statement Source'!$C:$C,'1. Income Statement'!$AR25,'Income Statement Source'!AJ:AJ)/1000 -> 28.20431 | AI25: =SUMIF('Income Statement Source'!$C:$C,'1. Income Statement'!$AR25,'Income Statement Source'!AK:AK)/1000 -> 27.13521 | AJ25: =SUMIF('Income Statement Source'!$C:$C,'1. Income Statement'!$AR25,'Income Statement Source'!AL:AL)/1000 -> 39.05671 | AK25: =SUMIF('Income Statement Source'!$C:$C,'1. Income Statement'!$AR25,'Income Statement Source'!AM:AM)/1000 -> 30.74309 | AL25: =SUMIF('Income Statement Source'!$C:$C,'1. Income Statement'!$AR25,'Income Statement Source'!AN:AN)/1000 -> 28.31626 | AM25: =SUMIF('Income Statement Source'!$C:$C,'1. Income Statement'!$AR25,'Income Statement Source'!AO:AO)/1000 -> 37.5884 | AN25: =SUMIF('Income Statement Source'!$C:$C,'1. Income Statement'!$AR25,'Income Statement Source'!AP:AP)/1000 -> 25.3577 | AO25: =SUM(AE25:AN25) -> 287.31501 | AP25: =SUM(AO25,AB25:AC25) -> 340.6011 | AR25: Alarm Equipment & Devices
B26: =+AR26 -> Pipe & Valves | E26: =SUMIF('Income Statement Source'!$C:$C,'1. Income Statement'!$AR26,'Income Statement Source'!G:G)/1000 -> 7.96719 | F26: =SUMIF('Income Statement Source'!$C:$C,'1. Income Statement'!$AR26,'Income Statement Source'!H:H)/1000 -> 8.80689 | G26: =SUMIF('Income Statement Source'!$C:$C,'1. Income Statement'!$AR26,'Income Statement Source'!I:I)/1000 -> 12.74384 | H26: =SUMIF('Income Statement Source'!$C:$C,'1. Income Statement'!$AR26,'Income Statement Source'!J:J)/1000 -> 9.67119 | I26: =SUMIF('Income Statement Source'!$C:$C,'1. Income Statement'!$AR26,'Income Statement Source'!K:K)/1000 -> 11.5685 | J26: =SUMIF('Income Statement Source'!$C:$C,'1. Income Statement'!$AR26,'Income Statement Source'!L:L)/1000 -> 15.43408 | K26: =SUMIF('Income Statement Source'!$C:$C,'1. Income Statement'!$AR26,'Income Statement Source'!M:M)/1000 -> 12.15675 | L26: =SUMIF('Income Statement Source'!$C:$C,'1. Income Statement'!$AR26,'Income Statement Source'!N:N)/1000 -> 10.3325 | M26: =SUMIF('Income Statement Source'!$C:$C,'1. Income Statement'!$AR26,'Income Statement Source'!O:O)/1000 -> 14.53934 | N26: =SUMIF('Income Statement Source'!$C:$C,'1. Income Statement'!$AR26,'Income Statement Source'!P:P)/1000 -> 11.06018 | O26: =SUMIF('Income Statement Source'!$C:$C,'1. Income Statement'!$AR26,'Income Statement Source'!Q:Q)/1000 -> 9.26131 | P26: =SUMIF('Income Statement Source'!$C:$C,'1. Income Statement'!$AR26,'Income Statement Source'!R:R)/1000 -> 14.45518 | Q26: =SUM(E26:P26) -> 137.99695 | R26: =SUMIF('Income Statement Source'!$C:$C,'1. Income Statement'!$AR26,'Income Statement Source'!T:T)/1000 -> 10.53007 | S26: =SUMIF('Income Statement Source'!$C:$C,'1. Income Statement'!$AR26,'Income Statement Source'!U:U)/1000 -> 14.37085 | T26: =SUMIF('Income Statement Source'!$C:$C,'1. Income Statement'!$AR26,'Income Statement Source'!V:V)/1000 -> 19.52075 | U26: =SUMIF('Income Statement Source'!$C:$C,'1. Income Statement'!$AR26,'Income Statement Source'!W:W)/1000 -> 18.57891 | V26: =SUMIF('Income Statement Source'!$C:$C,'1. Income Statement'!$AR26,'Income Statement Source'!X:X)/1000 -> 19.3347 | W26: =SUMIF('Income Statement Source'!$C:$C,'1. Income Statement'!$AR26,'Income Statement Source'!Y:Y)/1000 -> 24.45855 | X26: =SUMIF('Income Statement Source'!$C:$C,'1. Income Statement'!$AR26,'Income Statement Source'!Z:Z)/1000 -> 18.69852 | Y26: =SUMIF('Income Statement Source'!$C:$C,'1. Income Statement'!$AR26,'Income Statement Source'!AA:AA)/1000 -> 19.93018 | Z26: =SUMIF('Income Statement Source'!$C:$C,'1. Income Statement'!$AR26,'Income Statement Source'!AB:AB)/1000 -> 23.22331 | AA26: =SUMIF('Income Statement Source'!$C:$C,'1. Income Statement'!$AR26,'Income Statement Source'!AC:AC)/1000 -> 16.76829 | AB26: =SUMIF('Income Statement Source'!$C:$C,'1. Income Statement'!$AR26,'Income Statement Source'!AD:AD)/1000 -> 14.90274 | AC26: =SUMIF('Income Statement Source'!$C:$C,'1. Income Statement'!$AR26,'Income Statement Source'!AE:AE)/1000 -> 22.12784 | AD26: =SUM(R26:AC26) -> 222.44471 | AE26: =SUMIF('Income Statement Source'!$C:$C,'1. Income Statement'!$AR26,'Income Statement Source'!AG:AG)/1000 -> 8.4189 | AF26: =SUMIF('Income Statement Source'!$C:$C,'1. Income Statement'!$AR26,'Income Statement Source'!AH:AH)/1000 -> 12.34643 | AG26: =SUMIF('Income Statement Source'!$C:$C,'1. Income Statement'!$AR26,'Income Statement Source'!AI:AI)/1000 -> 13.75594 | AH26: =SUMIF('Income Statement Source'!$C:$C,'1. Income Statement'!$AR26,'Income Statement Source'!AJ:AJ)/1000 -> 15.26791 | AI26: =SUMIF('Income Statement Source'!$C:$C,'1. Income Statement'!$AR26,'Income Statement Source'!AK:AK)/1000 -> 14.83659 | AJ26: =SUMIF('Income Statement Source'!$C:$C,'1. Income Statement'!$AR26,'Income Statement Source'!AL:AL)/1000 -> 17.90564 | AK26: =SUMIF('Income Statement Source'!$C:$C,'1. Income Statement'!$AR26,'Income Statement Source'!AM:AM)/1000 -> 16.2984 | AL26: =SUMIF('Income Statement Source'!$C:$C,'1. Income Statement'!$AR26,'Income Statement Source'!AN:AN)/1000 -> 13.11337 | AM26: =SUMIF('Income Statement Source'!$C:$C,'1. Income Statement'!$AR26,'Income Statement Source'!AO:AO)/1000 -> 18.2645 | AN26: =SUMIF('Income Statement Source'!$C:$C,'1. Income Statement'!$AR26,'Income Statement Source'!AP:AP)/1000 -> 13.09253 | AO26: =SUM(AE26:AN26) -> 143.30021 | AP26: =SUM(AO26,AB26:AC26) -> 180.33079 | AR26: Pipe & Valves
B27: =+AR27 -> Wire & Cable | E27: =SUMIF('Income Statement Source'!$C:$C,'1. Income Statement'!$AR27,'Income Statement Source'!G:G)/1000 -> 3.60962 | F27: =SUMIF('Income Statement Source'!$C:$C,'1. Income Statement'!$AR27,'Income Statement Source'!H:H)/1000 -> 4.37161 | G27: =SUMIF('Income Statement Source'!$C:$C,'1. Income Statement'!$AR27,'Income Statement Source'!I:I)/1000 -> 6.68513 | H27: =SUMIF('Income Statement Source'!$C:$C,'1. Income Statement'!$AR27,'Income Statement Source'!J:J)/1000 -> 5.49789 | I27: =SUMIF('Income Statement Source'!$C:$C,'1. Income Statement'!$AR27,'Income Statement Source'!K:K)/1000 -> 5.89769 | J27: =SUMIF('Income Statement Source'!$C:$C,'1. Income Statement'!$AR27,'Income Statement Source'!L:L)/1000 -> 6.93855 | K27: =SUMIF('Income Statement Source'!$C:$C,'1. Income Statement'!$AR27,'Income Statement Source'!M:M)/1000 -> 5.78917 | L27: =SUMIF('Income Statement Source'!$C:$C,'1. Income Statement'!$AR27,'Income Statement Source'!N:N)/1000 -> 5.87802 | M27: =SUMIF('Income Statement Source'!$C:$C,'1. Income Statement'!$AR27,'Income Statement Source'!O:O)/1000 -> 7.06928 | N27: =SUMIF('Income Statement Source'!$C:$C,'1. Income Statement'!$AR27,'Income Statement Source'!P:P)/1000 -> 5.65943 | O27: =SUMIF('Income Statement Source'!$C:$C,'1. Income Statement'!$AR27,'Income Statement Source'!Q:Q)/1000 -> 4.38967 | P27: =SUMIF('Income Statement Source'!$C:$C,'1. Income Statement'!$AR27,'Income Statement Source'!R:R)/1000 -> 6.47235 | Q27: =SUM(E27:P27) -> 68.25841 | R27: =SUMIF('Income Statement Source'!$C:$C,'1. Income Statement'!$AR27,'Income Statement Source'!T:T)/1000 -> 3.90052 | S27: =SUMIF('Income Statement Source'!$C:$C,'1. Income Statement'!$AR27,'Income Statement Source'!U:U)/1000 -> 5.5374 | T27: =SUMIF('Income Statement Source'!$C:$C,'1. Income Statement'!$AR27,'Income Statement Source'!V:V)/1000 -> 7.31537 | U27: =SUMIF('Income Statement Source'!$C:$C,'1. Income Statement'!$AR27,'Income Statement Source'!W:W)/1000 -> 6.31953 | V27: =SUMIF('Income Statement Source'!$C:$C,'1. Income Statement'!$AR27,'Income Statement Source'!X:X)/1000 -> 6.87549 | W27: =SUMIF('Income Statement Source'!$C:$C,'1. Income Statement'!$AR27,'Income Statement Source'!Y:Y)/1000 -> 8.47002 | X27: =SUMIF('Income Statement Source'!$C:$C,'1. Income Statement'!$AR27,'Income Statement Source'!Z:Z)/1000 -> 7.04846 | Y27: =SUMIF('Income Statement Source'!$C:$C,'1. Income Statement'!$AR27,'Income Statement Source'!AA:AA)/1000 -> 7.08275 | Z27: =SUMIF('Income Statement Source'!$C:$C,'1. Income Statement'!$AR27,'Income Statement Source'!AB:AB)/1000 -> 8.29786 | AA27: =SUMIF('Income Statement Source'!$C:$C,'1. Income Statement'!$AR27,'Income Statement Source'!AC:AC)/1000 -> 5.70457 | AB27: =SUMIF('Income Statement Source'!$C:$C,'1. Income Statement'!$AR27,'Income Statement Source'!AD:AD)/1000 -> 5.95883 | AC27: =SUMIF('Income Statement Source'!$C:$C,'1. Income Statement'!$AR27,'Income Statement Source'!AE:AE)/1000 -> 7.20565 | AD27: =SUM(R27:AC27) -> 79.71645 | AE27: =SUMIF('Income Statement Source'!$C:$C,'1. Income Statement'!$AR27,'Income Statement Source'!AG:AG)/1000 -> 3.98623 | AF27: =SUMIF('Income Statement Source'!$C:$C,'1. Income Statement'!$AR27,'Income Statement Source'!AH:AH)/1000 -> 5.20447 | AG27: =SUMIF('Income Statement Source'!$C:$C,'1. Income Statement'!$AR27,'Income Statement Source'!AI:AI)/1000 -> 7.59876 | AH27: =SUMIF('Income Statement Source'!$C:$C,'1. Income Statement'!$AR27,'Income Statement Source'!AJ:AJ)/1000 -> 6.63018 | AI27: =SUMIF('Income Statement Source'!$C:$C,'1. Income Statement'!$AR27,'Income Statement Source'!AK:AK)/1000 -> 6.68559 | AJ27: =SUMIF('Income Statement Source'!$C:$C,'1. Income Statement'!$AR27,'Income Statement Source'!AL:AL)/1000 -> 8.75379 | AK27: =SUMIF('Income Statement Source'!$C:$C,'1. Income Statement'!$AR27,'Income Statement Source'!AM:AM)/1000 -> 7.45253 | AL27: =SUMIF('Income Statement Source'!$C:$C,'1. Income Statement'!$AR27,'Income Statement Source'!AN:AN)/1000 -> 7.23256 | AM27: =SUMIF('Income Statement Source'!$C:$C,'1. Income Statement'!$AR27,'Income Statement Source'!AO:AO)/1000 -> 9.11839 | AN27: =SUMIF('Income Statement Source'!$C:$C,'1. Income Statement'!$AR27,'Income Statement Source'!AP:AP)/1000 -> 6.35552 | AO27: =SUM(AE27:AN27) -> 69.01802 | AP27: =SUM(AO27,AB27:AC27) -> 82.1825 | AR27: Wire & Cable
B28: =+AR28 -> Equipment Rental | E28: =SUMIF('Income Statement Source'!$C:$C,'1. Income Statement'!$AR28,'Income Statement Source'!G:G)/1000 -> 2.51848 | F28: =SUMIF('Income Statement Source'!$C:$C,'1. Income Statement'!$AR28,'Income Statement Source'!H:H)/1000 -> 3.58479 | G28: =SUMIF('Income Statement Source'!$C:$C,'1. Income Statement'!$AR28,'Income Statement Source'!I:I)/1000 -> 4.55144 | H28: =SUMIF('Income Statement Source'!$C:$C,'1. Income Statement'!$AR28,'Income Statement Source'!J:J)/1000 -> 3.66865 | I28: =SUMIF('Income Statement Source'!$C:$C,'1. Income Statement'!$AR28,'Income Statement Source'!K:K)/1000 -> 4.02613 | J28: =SUMIF('Income Statement Source'!$C:$C,'1. Income Statement'!$AR28,'Income Statement Source'!L:L)/1000 -> 5.81517 | K28: =SUMIF('Income Statement Source'!$C:$C,'1. Income Statement'!$AR28,'Income Statement Source'!M:M)/1000 -> 4.33839 | L28: =SUMIF('Income Statement Source'!$C:$C,'1. Income Statement'!$AR28,'Income Statement Source'!N:N)/1000 -> 4.1258 | M28: =SUMIF('Income Statement Source'!$C:$C,'1. Income Statement'!$AR28,'Income Statement Source'!O:O)/1000 -> 4.86586 | N28: =SUMIF('Income Statement Source'!$C:$C,'1. Income Statement'!$AR28,'Income Statement Source'!P:P)/1000 -> 3.6313 | O28: =SUMIF('Income Statement Source'!$C:$C,'1. Income Statement'!$AR28,'Income Statement Source'!Q:Q)/1000 -> 3.57506 | P28: =SUMIF('Income Statement Source'!$C:$C,'1. Income Statement'!$AR28,'Income Statement Source'!R:R)/1000 -> 4.78671 | Q28: =SUM(E28:P28) -> 49.48778 | R28: =SUMIF('Income Statement Source'!$C:$C,'1. Income Statement'!$AR28,'Income Statement Source'!T:T)/1000 -> 3.68157 | S28: =SUMIF('Income Statement Source'!$C:$C,'1. Income Statement'!$AR28,'Income Statement Source'!U:U)/1000 -> 4.70851 | T28: =SUMIF('Income Statement Source'!$C:$C,'1. Income Statement'!$AR28,'Income Statement Source'!V:V)/1000 -> 7.02594 | U28: =SUMIF('Income Statement Source'!$C:$C,'1. Income Statement'!$AR28,'Income Statement Source'!W:W)/1000 -> 5.91875 | V28: =SUMIF('Income Statement Source'!$C:$C,'1. Income Statement'!$AR28,'Income Statement Source'!X:X)/1000 -> 7.04082 | W28: =SUMIF('Income Statement Source'!$C:$C,'1. Income Statement'!$AR28,'Income Statement Source'!Y:Y)/1000 -> 8.51923 | X28: =SUMIF('Income Statement Source'!$C:$C,'1. Income Statement'!$AR28,'Income Statement Source'!Z:Z)/1000 -> 7.54677 | Y28: =SUMIF('Income Statement Source'!$C:$C,'1. Income Statement'!$AR28,'Income Statement Source'!AA:AA)/1000 -> 7.58808 | Z28: =SUMIF('Income Statement Source'!$C:$C,'1. Income Statement'!$AR28,'Income Statement Source'!AB:AB)/1000 -> 8.75482 | AA28: =SUMIF('Income Statement Source'!$C:$C,'1. Income Statement'!$AR28,'Income Statement Source'!AC:AC)/1000 -> 5.44283 | AB28: =SUMIF('Income Statement Source'!$C:$C,'1. Income Statement'!$AR28,'Income Statement Source'!AD:AD)/1000 -> 5.27398 | AC28: =SUMIF('Income Statement Source'!$C:$C,'1. Income Statement'!$AR28,'Income Statement Source'!AE:AE)/1000 -> 7.39418 | AD28: =SUM(R28:AC28) -> 78.89548 | AE28: =SUMIF('Income Statement Source'!$C:$C,'1. Income Statement'!$AR28,'Income Statement Source'!AG:AG)/1000 -> 3.34906 | AF28: =SUMIF('Income Statement Source'!$C:$C,'1. Income Statement'!$AR28,'Income Statement Source'!AH:AH)/1000 -> 4.58164 | AG28: =SUMIF('Income Statement Source'!$C:$C,'1. Income Statement'!$AR28,'Income Statement Source'!AI:AI)/1000 -> 5.92902 | AH28: =SUMIF('Income Statement Source'!$C:$C,'1. Income Statement'!$AR28,'Income Statement Source'!AJ:AJ)/1000 -> 4.93635 | AI28: =SUMIF('Income Statement Source'!$C:$C,'1. Income Statement'!$AR28,'Income Statement Source'!AK:AK)/1000 -> 5.56752 | AJ28: =SUMIF('Income Statement Source'!$C:$C,'1. Income Statement'!$AR28,'Income Statement Source'!AL:AL)/1000 -> 7.05902 | AK28: =SUMIF('Income Statement Source'!$C:$C,'1. Income Statement'!$AR28,'Income Statement Source'!AM:AM)/1000 -> 5.65396 | AL28: =SUMIF('Income Statement Source'!$C:$C,'1. Income Statement'!$AR28,'Income Statement Source'!AN:AN)/1000 -> 5.95739 | AM28: =SUMIF('Income Statement Source'!$C:$C,'1. Income Statement'!$AR28,'Income Statement Source'!AO:AO)/1000 -> 5.79226 | AN28: =SUMIF('Income Statement Source'!$C:$C,'1. Income Statement'!$AR28,'Income Statement Source'!AP:AP)/1000 -> 5.53821 | AO28: =SUM(AE28:AN28) -> 54.36443 | AP28: =SUM(AO28,AB28:AC28) -> 67.03259 | AR28: Equipment Rental
B29: =+AR29 -> Job Supplies & Consumables | E29: =SUMIF('Income Statement Source'!$C:$C,'1. Income Statement'!$AR29,'Income Statement Source'!G:G)/1000 -> 1.57881 | F29: =SUMIF('Income Statement Source'!$C:$C,'1. Income Statement'!$AR29,'Income Statement Source'!H:H)/1000 -> 1.75111 | G29: =SUMIF('Income Statement Source'!$C:$C,'1. Income Statement'!$AR29,'Income Statement Source'!I:I)/1000 -> 2.39149 | H29: =SUMIF('Income Statement Source'!$C:$C,'1. Income Statement'!$AR29,'Income Statement Source'!J:J)/1000 -> 2.07259 | I29: =SUMIF('Income Statement Source'!$C:$C,'1. Income Statement'!$AR29,'Income Statement Source'!K:K)/1000 -> 2.12019 | J29: =SUMIF('Income Statement Source'!$C:$C,'1. Income Statement'!$AR29,'Income Statement Source'!L:L)/1000 -> 2.9964 | K29: =SUMIF('Income Statement Source'!$C:$C,'1. Income Statement'!$AR29,'Income Statement Source'!M:M)/1000 -> 2.24103 | L29: =SUMIF('Income Statement Source'!$C:$C,'1. Income Statement'!$AR29,'Income Statement Source'!N:N)/1000 -> 2.03537 | M29: =SUMIF('Income Statement Source'!$C:$C,'1. Income Statement'!$AR29,'Income Statement Source'!O:O)/1000 -> 2.94044 | N29: =SUMIF('Income Statement Source'!$C:$C,'1. Income Statement'!$AR29,'Income Statement Source'!P:P)/1000 -> 2.08361 | O29: =SUMIF('Income Statement Source'!$C:$C,'1. Income Statement'!$AR29,'Income Statement Source'!Q:Q)/1000 -> 1.78521 | P29: =SUMIF('Income Statement Source'!$C:$C,'1. Income Statement'!$AR29,'Income Statement Source'!R:R)/1000 -> 2.88374 | Q29: =SUM(E29:P29) -> 26.87999 | R29: =SUMIF('Income Statement Source'!$C:$C,'1. Income Statement'!$AR29,'Income Statement Source'!T:T)/1000 -> 1.55321 | S29: =SUMIF('Income Statement Source'!$C:$C,'1. Income Statement'!$AR29,'Income Statement Source'!U:U)/1000 -> 1.96974 | T29: =SUMIF('Income Statement Source'!$C:$C,'1. Income Statement'!$AR29,'Income Statement Source'!V:V)/1000 -> 3.02294 | U29: =SUMIF('Income Statement Source'!$C:$C,'1. Income Statement'!$AR29,'Income Statement Source'!W:W)/1000 -> 2.52509 | V29: =SUMIF('Income Statement Source'!$C:$C,'1. Income Statement'!$AR29,'Income Statement Source'!X:X)/1000 -> 2.7116 | W29: =SUMIF('Income Statement Source'!$C:$C,'1. Income Statement'!$AR29,'Income Statement Source'!Y:Y)/1000 -> 3.5038 | X29: =SUMIF('Income Statement Source'!$C:$C,'1. Income Statement'!$AR29,'Income Statement Source'!Z:Z)/1000 -> 3.19273 | Y29: =SUMIF('Income Statement Source'!$C:$C,'1. Income Statement'!$AR29,'Income Statement Source'!AA:AA)/1000 -> 3.00584 | Z29: =SUMIF('Income Statement Source'!$C:$C,'1. Income Statement'!$AR29,'Income Statement Source'!AB:AB)/1000 -> 2.92531 | AA29: =SUMIF('Income Statement Source'!$C:$C,'1. Income Statement'!$AR29,'Income Statement Source'!AC:AC)/1000 -> 2.50119 | AB29: =SUMIF('Income Statement Source'!$C:$C,'1. Income Statement'!$AR29,'Income Statement Source'!AD:AD)/1000 -> 2.46293 | AC29: =SUMIF('Income Statement Source'!$C:$C,'1. Income Statement'!$AR29,'Income Statement Source'!AE:AE)/1000 -> 3.17195 | AD29: =SUM(R29:AC29) -> 32.54633 | AE29: =SUMIF('Income Statement Source'!$C:$C,'1. Income Statement'!$AR29,'Income Statement Source'!AG:AG)/1000 -> 1.65568 | AF29: =SUMIF('Income Statement Source'!$C:$C,'1. Income Statement'!$AR29,'Income Statement Source'!AH:AH)/1000 -> 2.43077 | AG29: =SUMIF('Income Statement Source'!$C:$C,'1. Income Statement'!$AR29,'Income Statement Source'!AI:AI)/1000 -> 3.3537 | AH29: =SUMIF('Income Statement Source'!$C:$C,'1. Income Statement'!$AR29,'Income Statement Source'!AJ:AJ)/1000 -> 3.0686 | AI29: =SUMIF('Income Statement Source'!$C:$C,'1. Income Statement'!$AR29,'Income Statement Source'!AK:AK)/1000 -> 2.59056 | AJ29: =SUMIF('Income Statement Source'!$C:$C,'1. Income Statement'!$AR29,'Income Statement Source'!AL:AL)/1000 -> 3.63916 | AK29: =SUMIF('Income Statement Source'!$C:$C,'1. Income Statement'!$AR29,'Income Statement Source'!AM:AM)/1000 -> 3.08563 | AL29: =SUMIF('Income Statement Source'!$C:$C,'1. Income Statement'!$AR29,'Income Statement Source'!AN:AN)/1000 -> 2.85981 | AM29: =SUMIF('Income Statement Source'!$C:$C,'1. Income Statement'!$AR29,'Income Statement Source'!AO:AO)/1000 -> 3.80183 | AN29: =SUMIF('Income Statement Source'!$C:$C,'1. Income Statement'!$AR29,'Income Statement Source'!AP:AP)/1000 -> 2.88548 | AO29: =SUM(AE29:AN29) -> 29.37122 | AP29: =SUM(AO29,AB29:AC29) -> 35.0061 | AR29: Job Supplies & Consumables
B30: =+B23 -> Materials & Equipment | E30: =SUM(E24:E29) -> 49.0146 | F30: =SUM(F24:F29) -> 60.37854 | G30: =SUM(G24:G29) -> 82.90482 | H30: =SUM(H24:H29) -> 67.48466 | I30: =SUM(I24:I29) -> 71.13853 | J30: =SUM(J24:J29) -> 94.72672 | K30: =SUM(K24:K29) -> 81.72669 | L30: =SUM(L24:L29) -> 70.35796 | ... AP30: =SUM(AP24:AP29) -> 1152.701
E31: =IFERROR(E30/E$19,0) -> 0.25800414 | F31: =IFERROR(F30/F$19,0) -> 0.26565738 | G31: =IFERROR(G30/G$19,0) -> 0.26950791 | H31: =IFERROR(H30/H$19,0) -> 0.26091734 | I31: =IFERROR(I30/I$19,0) -> 0.2617533 | J31: =IFERROR(J30/J$19,0) -> 0.25723126 | K31: =IFERROR(K30/K$19,0) -> 0.27017392 | L31: =IFERROR(L30/L$19,0) -> 0.25379591 | ... AP31: =IFERROR(AP30/AP$19,0) -> 0.27178201
B32: Subcontract
B33: =+AR33 -> Sprinkler Subcontractor Labor | E33: =SUMIF('Income Statement Source'!$C:$C,'1. Income Statement'!$AR33,'Income Statement Source'!G:G)/1000 -> 68.64558 | F33: =SUMIF('Income Statement Source'!$C:$C,'1. Income Statement'!$AR33,'Income Statement Source'!H:H)/1000 -> 87.77917 | G33: =SUMIF('Income Statement Source'!$C:$C,'1. Income Statement'!$AR33,'Income Statement Source'!I:I)/1000 -> 9.70356 | H33: =SUMIF('Income Statement Source'!$C:$C,'1. Income Statement'!$AR33,'Income Statement Source'!J:J)/1000 -> 53.70016 | I33: =SUMIF('Income Statement Source'!$C:$C,'1. Income Statement'!$AR33,'Income Statement Source'!K:K)/1000 -> 60.77124 | J33: =SUMIF('Income Statement Source'!$C:$C,'1. Income Statement'!$AR33,'Income Statement Source'!L:L)/1000 -> 148.81247 | K33: =SUMIF('Income Statement Source'!$C:$C,'1. Income Statement'!$AR33,'Income Statement Source'!M:M)/1000 -> 9.92969 | L33: =SUMIF('Income Statement Source'!$C:$C,'1. Income Statement'!$AR33,'Income Statement Source'!N:N)/1000 -> 61.47874 | M33: =SUMIF('Income Statement Source'!$C:$C,'1. Income Statement'!$AR33,'Income Statement Source'!O:O)/1000 -> 153.63807 | N33: =SUMIF('Income Statement Source'!$C:$C,'1. Income Statement'!$AR33,'Income Statement Source'!P:P)/1000 -> 8.65425 | O33: =SUMIF('Income Statement Source'!$C:$C,'1. Income Statement'!$AR33,'Income Statement Source'!Q:Q)/1000 -> 51.5449 | P33: =SUMIF('Income Statement Source'!$C:$C,'1. Income Statement'!$AR33,'Income Statement Source'!R:R)/1000 -> 70.20015 | Q33: =SUM(E33:P33) -> 784.85798 | R33: =SUMIF('Income Statement Source'!$C:$C,'1. Income Statement'!$AR33,'Income Statement Source'!T:T)/1000 -> 63.8535 | S33: =SUMIF('Income Statement Source'!$C:$C,'1. Income Statement'!$AR33,'Income Statement Source'!U:U)/1000 -> 79.89286 | T33: =SUMIF('Income Statement Source'!$C:$C,'1. Income Statement'!$AR33,'Income Statement Source'!V:V)/1000 -> 191.93299 | U33: =SUMIF('Income Statement Source'!$C:$C,'1. Income Statement'!$AR33,'Income Statement Source'!W:W)/1000 -> 14.94238 | V33: =SUMIF('Income Statement Source'!$C:$C,'1. Income Statement'!$AR33,'Income Statement Source'!X:X)/1000 -> 102.26975 | W33: =SUMIF('Income Statement Source'!$C:$C,'1. Income Statement'!$AR33,'Income Statement Source'!Y:Y)/1000 -> 130.93173 | X33: =SUMIF('Income Statement Source'!$C:$C,'1. Income Statement'!$AR33,'Income Statement Source'!Z:Z)/1000 -> 207.77417 | Y33: =SUMIF('Income Statement Source'!$C:$C,'1. Income Statement'!$AR33,'Income Statement Source'!AA:AA)/1000 -> 17.11902 | Z33: =SUMIF('Income Statement Source'!$C:$C,'1. Income Statement'!$AR33,'Income Statement Source'!AB:AB)/1000 -> 118.43041 | AA33: =SUMIF('Income Statement Source'!$C:$C,'1. Income Statement'!$AR33,'Income Statement Source'!AC:AC)/1000 -> 87.04569 | AB33: =SUMIF('Income Statement Source'!$C:$C,'1. Income Statement'!$AR33,'Income Statement Source'!AD:AD)/1000 -> 159.36507 | AC33: =SUMIF('Income Statement Source'!$C:$C,'1. Income Statement'!$AR33,'Income Statement Source'!AE:AE)/1000 -> 17.59675 | AD33: =SUM(R33:AC33) -> 1191.1543 | AE33: =SUMIF('Income Statement Source'!$C:$C,'1. Income Statement'!$AR33,'Income Statement Source'!AG:AG)/1000 -> 49.12704 | AF33: =SUMIF('Income Statement Source'!$C:$C,'1. Income Statement'!$AR33,'Income Statement Source'!AH:AH)/1000 -> 65.7948 | AG33: =SUMIF('Income Statement Source'!$C:$C,'1. Income Statement'!$AR33,'Income Statement Source'!AI:AI)/1000 -> 89.6791 | AH33: =SUMIF('Income Statement Source'!$C:$C,'1. Income Statement'!$AR33,'Income Statement Source'!AJ:AJ)/1000 -> 150.91857 | AI33: =SUMIF('Income Statement Source'!$C:$C,'1. Income Statement'!$AR33,'Income Statement Source'!AK:AK)/1000 -> 11.57816 | AJ33: =SUMIF('Income Statement Source'!$C:$C,'1. Income Statement'!$AR33,'Income Statement Source'!AL:AL)/1000 -> 101.82188 | AK33: =SUMIF('Income Statement Source'!$C:$C,'1. Income Statement'!$AR33,'Income Statement Source'!AM:AM)/1000 -> 80.43095 | AL33: =SUMIF('Income Statement Source'!$C:$C,'1. Income Statement'!$AR33,'Income Statement Source'!AN:AN)/1000 -> 145.96461 | AM33: =SUMIF('Income Statement Source'!$C:$C,'1. Income Statement'!$AR33,'Income Statement Source'!AO:AO)/1000 -> 14.04965 | AN33: =SUMIF('Income Statement Source'!$C:$C,'1. Income Statement'!$AR33,'Income Statement Source'!AP:AP)/1000 -> 73.11584 | AO33: =SUM(AE33:AN33) -> 782.4806 | AP33: =SUM(AO33,AB33:AC33) -> 959.44242 | AR33: Sprinkler Subcontractor Labor
B34: =+AR34 -> Subcontractor - Other | E34: =SUMIF('Income Statement Source'!$C:$C,'1. Income Statement'!$AR34,'Income Statement Source'!G:G)/1000 -> 0.94556 | F34: =SUMIF('Income Statement Source'!$C:$C,'1. Income Statement'!$AR34,'Income Statement Source'!H:H)/1000 -> 1.11384 | G34: =SUMIF('Income Statement Source'!$C:$C,'1. Income Statement'!$AR34,'Income Statement Source'!I:I)/1000 -> 1.66517 | H34: =SUMIF('Income Statement Source'!$C:$C,'1. Income Statement'!$AR34,'Income Statement Source'!J:J)/1000 -> 1.46351 | I34: =SUMIF('Income Statement Source'!$C:$C,'1. Income Statement'!$AR34,'Income Statement Source'!K:K)/1000 -> 1.37033 | J34: =SUMIF('Income Statement Source'!$C:$C,'1. Income Statement'!$AR34,'Income Statement Source'!L:L)/1000 -> 2.11407 | K34: =SUMIF('Income Statement Source'!$C:$C,'1. Income Statement'!$AR34,'Income Statement Source'!M:M)/1000 -> 1.47321 | L34: =SUMIF('Income Statement Source'!$C:$C,'1. Income Statement'!$AR34,'Income Statement Source'!N:N)/1000 -> 1.37159 | M34: =SUMIF('Income Statement Source'!$C:$C,'1. Income Statement'!$AR34,'Income Statement Source'!O:O)/1000 -> 1.96726 | N34: =SUMIF('Income Statement Source'!$C:$C,'1. Income Statement'!$AR34,'Income Statement Source'!P:P)/1000 -> 1.371 | O34: =SUMIF('Income Statement Source'!$C:$C,'1. Income Statement'!$AR34,'Income Statement Source'!Q:Q)/1000 -> 1.11384 | P34: =SUMIF('Income Statement Source'!$C:$C,'1. Income Statement'!$AR34,'Income Statement Source'!R:R)/1000 -> 1.88701 | Q34: =SUM(E34:P34) -> 17.85639 | R34: =SUMIF('Income Statement Source'!$C:$C,'1. Income Statement'!$AR34,'Income Statement Source'!T:T)/1000 -> 0.95703 | S34: =SUMIF('Income Statement Source'!$C:$C,'1. Income Statement'!$AR34,'Income Statement Source'!U:U)/1000 -> 1.21684 | T34: =SUMIF('Income Statement Source'!$C:$C,'1. Income Statement'!$AR34,'Income Statement Source'!V:V)/1000 -> 1.76442 | U34: =SUMIF('Income Statement Source'!$C:$C,'1. Income Statement'!$AR34,'Income Statement Source'!W:W)/1000 -> 1.41398 | V34: =SUMIF('Income Statement Source'!$C:$C,'1. Income Statement'!$AR34,'Income Statement Source'!X:X)/1000 -> 1.64743 | W34: =SUMIF('Income Statement Source'!$C:$C,'1. Income Statement'!$AR34,'Income Statement Source'!Y:Y)/1000 -> 2.25899 | X34: =SUMIF('Income Statement Source'!$C:$C,'1. Income Statement'!$AR34,'Income Statement Source'!Z:Z)/1000 -> 1.74329 | Y34: =SUMIF('Income Statement Source'!$C:$C,'1. Income Statement'!$AR34,'Income Statement Source'!AA:AA)/1000 -> 1.64783 | Z34: =SUMIF('Income Statement Source'!$C:$C,'1. Income Statement'!$AR34,'Income Statement Source'!AB:AB)/1000 -> 1.97218 | AA34: =SUMIF('Income Statement Source'!$C:$C,'1. Income Statement'!$AR34,'Income Statement Source'!AC:AC)/1000 -> 1.3564 | AB34: =SUMIF('Income Statement Source'!$C:$C,'1. Income Statement'!$AR34,'Income Statement Source'!AD:AD)/1000 -> 1.3244 | AC34: =SUMIF('Income Statement Source'!$C:$C,'1. Income Statement'!$AR34,'Income Statement Source'!AE:AE)/1000 -> 1.78222 | AD34: =SUM(R34:AC34) -> 19.08501 | AE34: =SUMIF('Income Statement Source'!$C:$C,'1. Income Statement'!$AR34,'Income Statement Source'!AG:AG)/1000 -> 1.1557 | AF34: =SUMIF('Income Statement Source'!$C:$C,'1. Income Statement'!$AR34,'Income Statement Source'!AH:AH)/1000 -> 1.43743 | AG34: =SUMIF('Income Statement Source'!$C:$C,'1. Income Statement'!$AR34,'Income Statement Source'!AI:AI)/1000 -> 1.77278 | AH34: =SUMIF('Income Statement Source'!$C:$C,'1. Income Statement'!$AR34,'Income Statement Source'!AJ:AJ)/1000 -> 1.59566 | AI34: =SUMIF('Income Statement Source'!$C:$C,'1. Income Statement'!$AR34,'Income Statement Source'!AK:AK)/1000 -> 1.83216 | AJ34: =SUMIF('Income Statement Source'!$C:$C,'1. Income Statement'!$AR34,'Income Statement Source'!AL:AL)/1000 -> 2.18877 | AK34: =SUMIF('Income Statement Source'!$C:$C,'1. Income Statement'!$AR34,'Income Statement Source'!AM:AM)/1000 -> 1.98728 | AL34: =SUMIF('Income Statement Source'!$C:$C,'1. Income Statement'!$AR34,'Income Statement Source'!AN:AN)/1000 -> 1.70188 | AM34: =SUMIF('Income Statement Source'!$C:$C,'1. Income Statement'!$AR34,'Income Statement Source'!AO:AO)/1000 -> 2.0443 | AN34: =SUMIF('Income Statement Source'!$C:$C,'1. Income Statement'!$AR34,'Income Statement Source'!AP:AP)/1000 -> 1.46181 | AO34: =SUM(AE34:AN34) -> 17.17777 | AP34: =SUM(AO34,AB34:AC34) -> 20.28439 | AR34: Subcontractor - Other
B35: =+B32 -> Subcontract | E35: =SUM(E33:E34) -> 69.59114 | F35: =SUM(F33:F34) -> 88.89301 | G35: =SUM(G33:G34) -> 11.36873 | H35: =SUM(H33:H34) -> 55.16367 | I35: =SUM(I33:I34) -> 62.14157 | J35: =SUM(J33:J34) -> 150.92654 | K35: =SUM(K33:K34) -> 11.4029 | L35: =SUM(L33:L34) -> 62.85033 | ... AP35: =SUM(AP33:AP34) -> 979.72681
E36: =IFERROR(E35/E$19,0) -> 0.36631539 | F36: =IFERROR(F35/F$19,0) -> 0.39111718 | G36: =IFERROR(G35/G$19,0) -> 0.036957594 | H36: =IFERROR(H35/H$19,0) -> 0.21328044 | I36: =IFERROR(I35/I$19,0) -> 0.2286491 | J36: =IFERROR(J35/J$19,0) -> 0.40984237 | K36: =IFERROR(K35/K$19,0) -> 0.037695962 | L36: =IFERROR(L35/L$19,0) -> 0.22671432 | ... AP36: =IFERROR(AP35/AP$19,0) -> 0.23099842
B37: =+AR37 -> Alarm Installation Labor - Direct | E37: =SUMIF('Income Statement Source'!$C:$C,'1. Income Statement'!$AR37,'Income Statement Source'!G:G)/1000 -> 21.05397 | F37: =SUMIF('Income Statement Source'!$C:$C,'1. Income Statement'!$AR37,'Income Statement Source'!H:H)/1000 -> 27.31484 | G37: =SUMIF('Income Statement Source'!$C:$C,'1. Income Statement'!$AR37,'Income Statement Source'!I:I)/1000 -> 37.69449 | H37: =SUMIF('Income Statement Source'!$C:$C,'1. Income Statement'!$AR37,'Income Statement Source'!J:J)/1000 -> 31.0596 | I37: =SUMIF('Income Statement Source'!$C:$C,'1. Income Statement'!$AR37,'Income Statement Source'!K:K)/1000 -> 48.39315 | J37: =SUMIF('Income Statement Source'!$C:$C,'1. Income Statement'!$AR37,'Income Statement Source'!L:L)/1000 -> 45.93623 | K37: =SUMIF('Income Statement Source'!$C:$C,'1. Income Statement'!$AR37,'Income Statement Source'!M:M)/1000 -> 37.84084 | L37: =SUMIF('Income Statement Source'!$C:$C,'1. Income Statement'!$AR37,'Income Statement Source'!N:N)/1000 -> 34.82304 | M37: =SUMIF('Income Statement Source'!$C:$C,'1. Income Statement'!$AR37,'Income Statement Source'!O:O)/1000 -> 42.67172 | N37: =SUMIF('Income Statement Source'!$C:$C,'1. Income Statement'!$AR37,'Income Statement Source'!P:P)/1000 -> 47.04143 | O37: =SUMIF('Income Statement Source'!$C:$C,'1. Income Statement'!$AR37,'Income Statement Source'!Q:Q)/1000 -> 26.52543 | P37: =SUMIF('Income Statement Source'!$C:$C,'1. Income Statement'!$AR37,'Income Statement Source'!R:R)/1000 -> 38.84399 | Q37: =SUM(E37:P37) -> 439.19873 | R37: =SUMIF('Income Statement Source'!$C:$C,'1. Income Statement'!$AR37,'Income Statement Source'!T:T)/1000 -> 25.37761 | S37: =SUMIF('Income Statement Source'!$C:$C,'1. Income Statement'!$AR37,'Income Statement Source'!U:U)/1000 -> 29.56788 | T37: =SUMIF('Income Statement Source'!$C:$C,'1. Income Statement'!$AR37,'Income Statement Source'!V:V)/1000 -> 40.66381 | U37: =SUMIF('Income Statement Source'!$C:$C,'1. Income Statement'!$AR37,'Income Statement Source'!W:W)/1000 -> 39.72079 | V37: =SUMIF('Income Statement Source'!$C:$C,'1. Income Statement'!$AR37,'Income Statement Source'!X:X)/1000 -> 63.53001 | W37: =SUMIF('Income Statement Source'!$C:$C,'1. Income Statement'!$AR37,'Income Statement Source'!Y:Y)/1000 -> 54.45015 | X37: =SUMIF('Income Statement Source'!$C:$C,'1. Income Statement'!$AR37,'Income Statement Source'!Z:Z)/1000 -> 44.87415 | Y37: =SUMIF('Income Statement Source'!$C:$C,'1. Income Statement'!$AR37,'Income Statement Source'!AA:AA)/1000 -> 46.3026 | Z37: =SUMIF('Income Statement Source'!$C:$C,'1. Income Statement'!$AR37,'Income Statement Source'!AB:AB)/1000 -> 48.77865 | AA37: =SUMIF('Income Statement Source'!$C:$C,'1. Income Statement'!$AR37,'Income Statement Source'!AC:AC)/1000 -> 53.27082 | AB37: =SUMIF('Income Statement Source'!$C:$C,'1. Income Statement'!$AR37,'Income Statement Source'!AD:AD)/1000 -> 34.4557 | AC37: =SUMIF('Income Statement Source'!$C:$C,'1. Income Statement'!$AR37,'Income Statement Source'!AE:AE)/1000 -> 47.26429 | AD37: =SUM(R37:AC37) -> 528.25646 | AE37: =SUMIF('Income Statement Source'!$C:$C,'1. Income Statement'!$AR37,'Income Statement Source'!AG:AG)/1000 -> 24.63062 | AF37: =SUMIF('Income Statement Source'!$C:$C,'1. Income Statement'!$AR37,'Income Statement Source'!AH:AH)/1000 -> 33.17054 | AG37: =SUMIF('Income Statement Source'!$C:$C,'1. Income Statement'!$AR37,'Income Statement Source'!AI:AI)/1000 -> 44.05896 | AH37: =SUMIF('Income Statement Source'!$C:$C,'1. Income Statement'!$AR37,'Income Statement Source'!AJ:AJ)/1000 -> 43.44829 | AI37: =SUMIF('Income Statement Source'!$C:$C,'1. Income Statement'!$AR37,'Income Statement Source'!AK:AK)/1000 -> 61.5291 | AJ37: =SUMIF('Income Statement Source'!$C:$C,'1. Income Statement'!$AR37,'Income Statement Source'!AL:AL)/1000 -> 59.25728 | AK37: =SUMIF('Income Statement Source'!$C:$C,'1. Income Statement'!$AR37,'Income Statement Source'!AM:AM)/1000 -> 45.53578 | AL37: =SUMIF('Income Statement Source'!$C:$C,'1. Income Statement'!$AR37,'Income Statement Source'!AN:AN)/1000 -> 42.80865 | AM37: =SUMIF('Income Statement Source'!$C:$C,'1. Income Statement'!$AR37,'Income Statement Source'!AO:AO)/1000 -> 52.65681 | AN37: =SUMIF('Income Statement Source'!$C:$C,'1. Income Statement'!$AR37,'Income Statement Source'!AP:AP)/1000 -> 59.97557 | AO37: =SUM(AE37:AN37) -> 467.0716 | AP37: =SUM(AO37,AB37:AC37) -> 548.79159 | AR37: Alarm Installation Labor - Direct
E38: =IFERROR(E37/E$19,0) -> 0.11082436 | F38: =IFERROR(F37/F$19,0) -> 0.12018159 | G38: =IFERROR(G37/G$19,0) -> 0.12253767 | H38: =IFERROR(H37/H$19,0) -> 0.12008638 | I38: =IFERROR(I37/I$19,0) -> 0.17806197 | J38: =IFERROR(J37/J$19,0) -> 0.12474024 | K38: =IFERROR(K37/K$19,0) -> 0.1250951 | L38: =IFERROR(L37/L$19,0) -> 0.12561401 | ... AP38: =IFERROR(AP37/AP$19,0) -> 0.1293932
B39: =+AR39 -> Vehicle Fuel - Job Related | E39: =SUMIF('Income Statement Source'!$C:$C,'1. Income Statement'!$AR39,'Income Statement Source'!G:G)/1000 -> 1.73266 | F39: =SUMIF('Income Statement Source'!$C:$C,'1. Income Statement'!$AR39,'Income Statement Source'!H:H)/1000 -> 2.29818 | G39: =SUMIF('Income Statement Source'!$C:$C,'1. Income Statement'!$AR39,'Income Statement Source'!I:I)/1000 -> 3.23709 | H39: =SUMIF('Income Statement Source'!$C:$C,'1. Income Statement'!$AR39,'Income Statement Source'!J:J)/1000 -> 2.4494 | I39: =SUMIF('Income Statement Source'!$C:$C,'1. Income Statement'!$AR39,'Income Statement Source'!K:K)/1000 -> 2.81773 | J39: =SUMIF('Income Statement Source'!$C:$C,'1. Income Statement'!$AR39,'Income Statement Source'!L:L)/1000 -> 3.887 | K39: =SUMIF('Income Statement Source'!$C:$C,'1. Income Statement'!$AR39,'Income Statement Source'!M:M)/1000 -> 3.10919 | L39: =SUMIF('Income Statement Source'!$C:$C,'1. Income Statement'!$AR39,'Income Statement Source'!N:N)/1000 -> 2.65609 | M39: =SUMIF('Income Statement Source'!$C:$C,'1. Income Statement'!$AR39,'Income Statement Source'!O:O)/1000 -> 3.31784 | N39: =SUMIF('Income Statement Source'!$C:$C,'1. Income Statement'!$AR39,'Income Statement Source'!P:P)/1000 -> 2.72199 | O39: =SUMIF('Income Statement Source'!$C:$C,'1. Income Statement'!$AR39,'Income Statement Source'!Q:Q)/1000 -> 2.35163 | P39: =SUMIF('Income Statement Source'!$C:$C,'1. Income Statement'!$AR39,'Income Statement Source'!R:R)/1000 -> 3.50639 | Q39: =SUM(E39:P39) -> 34.08519 | R39: =SUMIF('Income Statement Source'!$C:$C,'1. Income Statement'!$AR39,'Income Statement Source'!T:T)/1000 -> 1.98555 | S39: =SUMIF('Income Statement Source'!$C:$C,'1. Income Statement'!$AR39,'Income Statement Source'!U:U)/1000 -> 2.53385 | T39: =SUMIF('Income Statement Source'!$C:$C,'1. Income Statement'!$AR39,'Income Statement Source'!V:V)/1000 -> 3.57079 | U39: =SUMIF('Income Statement Source'!$C:$C,'1. Income Statement'!$AR39,'Income Statement Source'!W:W)/1000 -> 3.21087 | V39: =SUMIF('Income Statement Source'!$C:$C,'1. Income Statement'!$AR39,'Income Statement Source'!X:X)/1000 -> 3.18892 | W39: =SUMIF('Income Statement Source'!$C:$C,'1. Income Statement'!$AR39,'Income Statement Source'!Y:Y)/1000 -> 4.50473 | X39: =SUMIF('Income Statement Source'!$C:$C,'1. Income Statement'!$AR39,'Income Statement Source'!Z:Z)/1000 -> 3.56465 | Y39: =SUMIF('Income Statement Source'!$C:$C,'1. Income Statement'!$AR39,'Income Statement Source'!AA:AA)/1000 -> 4.07591 | Z39: =SUMIF('Income Statement Source'!$C:$C,'1. Income Statement'!$AR39,'Income Statement Source'!AB:AB)/1000 -> 4.26936 | AA39: =SUMIF('Income Statement Source'!$C:$C,'1. Income Statement'!$AR39,'Income Statement Source'!AC:AC)/1000 -> 3.27221 | AB39: =SUMIF('Income Statement Source'!$C:$C,'1. Income Statement'!$AR39,'Income Statement Source'!AD:AD)/1000 -> 2.72109 | AC39: =SUMIF('Income Statement Source'!$C:$C,'1. Income Statement'!$AR39,'Income Statement Source'!AE:AE)/1000 -> 4.05196 | AD39: =SUM(R39:AC39) -> 40.94989 | AE39: =SUMIF('Income Statement Source'!$C:$C,'1. Income Statement'!$AR39,'Income Statement Source'!AG:AG)/1000 -> 2.26477 | AF39: =SUMIF('Income Statement Source'!$C:$C,'1. Income Statement'!$AR39,'Income Statement Source'!AH:AH)/1000 -> 2.65792 | AG39: =SUMIF('Income Statement Source'!$C:$C,'1. Income Statement'!$AR39,'Income Statement Source'!AI:AI)/1000 -> 3.71261 | AH39: =SUMIF('Income Statement Source'!$C:$C,'1. Income Statement'!$AR39,'Income Statement Source'!AJ:AJ)/1000 -> 3.47667 | AI39: =SUMIF('Income Statement Source'!$C:$C,'1. Income Statement'!$AR39,'Income Statement Source'!AK:AK)/1000 -> 3.67626 | AJ39: =SUMIF('Income Statement Source'!$C:$C,'1. Income Statement'!$AR39,'Income Statement Source'!AL:AL)/1000 -> 4.93782 | AK39: =SUMIF('Income Statement Source'!$C:$C,'1. Income Statement'!$AR39,'Income Statement Source'!AM:AM)/1000 -> 3.64508 | AL39: =SUMIF('Income Statement Source'!$C:$C,'1. Income Statement'!$AR39,'Income Statement Source'!AN:AN)/1000 -> 3.63743 | AM39: =SUMIF('Income Statement Source'!$C:$C,'1. Income Statement'!$AR39,'Income Statement Source'!AO:AO)/1000 -> 4.15114 | AN39: =SUMIF('Income Statement Source'!$C:$C,'1. Income Statement'!$AR39,'Income Statement Source'!AP:AP)/1000 -> 3.4891 | AO39: =SUM(AE39:AN39) -> 35.6488 | AP39: =SUM(AO39,AB39:AC39) -> 42.42185 | AR39: Vehicle Fuel - Job Related
E40: =IFERROR(E39/E$19,0) -> 0.0091204143 | F40: =IFERROR(F39/F$19,0) -> 0.01011168 | G40: =IFERROR(G39/G$19,0) -> 0.010523168 | H40: =IFERROR(H39/H$19,0) -> 0.009470166 | I40: =IFERROR(I39/I$19,0) -> 0.010367801 | J40: =IFERROR(J39/J$19,0) -> 0.010555183 | K40: =IFERROR(K39/K$19,0) -> 0.01027843 | L40: =IFERROR(L39/L$19,0) -> 0.0095810735 | ... AP40: =IFERROR(AP39/AP$19,0) -> 0.010002156
B41: =+B22 -> Cost of Goods Sold | E41: =SUM(E35,E30,E37,E39) -> 141.39237 | F41: =SUM(F35,F30,F37,F39) -> 178.88457 | G41: =SUM(G35,G30,G37,G39) -> 135.20513 | H41: =SUM(H35,H30,H37,H39) -> 156.15733 | I41: =SUM(I35,I30,I37,I39) -> 184.49098 | J41: =SUM(J35,J30,J37,J39) -> 295.47649 | K41: =SUM(K35,K30,K37,K39) -> 134.07962 | L41: =SUM(L35,L30,L37,L39) -> 170.68742 | ... AP41: =SUM(AP35,AP30,AP37,AP39) -> 2723.6413
E42: =IFERROR(E41/E$19,0) -> 0.7442643 | F42: =IFERROR(F41/F$19,0) -> 0.78706782 | G42: =IFERROR(G41/G$19,0) -> 0.43952635 | H42: =IFERROR(H41/H$19,0) -> 0.60375432 | I42: =IFERROR(I41/I$19,0) -> 0.67883218 | J42: =IFERROR(J41/J$19,0) -> 0.80236906 | K42: =IFERROR(K41/K$19,0) -> 0.44324341 | L42: =IFERROR(L41/L$19,0) -> 0.61570531 | ... AP42: =IFERROR(AP41/AP$19,0) -> 0.64217579
B44: Gross Profit | E44: =+E19-E41 -> 48.58365 | F44: =+F19-F41 -> 48.39517 | G44: =+G19-G41 -> 172.4104 | H44: =+H19-H41 -> 102.4865 | I44: =+I19-I41 -> 87.28603 | J44: =+J19-J41 -> 72.7786 | K44: =+K19-K41 -> 168.41697 | L44: =+L19-L41 -> 106.53517 | ... AP44: =+AP19-AP41 -> 1517.6293
E45: =IFERROR(E44/E$19,0) -> 0.2557357 | F45: =IFERROR(F44/F$19,0) -> 0.21293218 | G45: =IFERROR(G44/G$19,0) -> 0.56047365 | H45: =IFERROR(H44/H$19,0) -> 0.39624568 | I45: =IFERROR(I44/I$19,0) -> 0.32116782 | J45: =IFERROR(J44/J$19,0) -> 0.19763094 | K45: =IFERROR(K44/K$19,0) -> 0.55675659 | L45: =IFERROR(L44/L$19,0) -> 0.38429469 | ... AP45: =IFERROR(AP44/AP$19,0) -> 0.35782421
B47: Operating Expense
B48: Personnel
B49: =+AR49 -> Officer Salaries | E49: =SUMIF('Income Statement Source'!$C:$C,'1. Income Statement'!$AR49,'Income Statement Source'!G:G)/1000 -> 14.56636 | F49: =SUMIF('Income Statement Source'!$C:$C,'1. Income Statement'!$AR49,'Income Statement Source'!H:H)/1000 -> 14.84104 | G49: =SUMIF('Income Statement Source'!$C:$C,'1. Income Statement'!$AR49,'Income Statement Source'!I:I)/1000 -> 14.63945 | H49: =SUMIF('Income Statement Source'!$C:$C,'1. Income Statement'!$AR49,'Income Statement Source'!J:J)/1000 -> 14.88982 | I49: =SUMIF('Income Statement Source'!$C:$C,'1. Income Statement'!$AR49,'Income Statement Source'!K:K)/1000 -> 22.2405 | J49: =SUMIF('Income Statement Source'!$C:$C,'1. Income Statement'!$AR49,'Income Statement Source'!L:L)/1000 -> 14.52337 | K49: =SUMIF('Income Statement Source'!$C:$C,'1. Income Statement'!$AR49,'Income Statement Source'!M:M)/1000 -> 14.64797 | L49: =SUMIF('Income Statement Source'!$C:$C,'1. Income Statement'!$AR49,'Income Statement Source'!N:N)/1000 -> 15.03973 | M49: =SUMIF('Income Statement Source'!$C:$C,'1. Income Statement'!$AR49,'Income Statement Source'!O:O)/1000 -> 14.89935 | N49: =SUMIF('Income Statement Source'!$C:$C,'1. Income Statement'!$AR49,'Income Statement Source'!P:P)/1000 -> 21.52403 | O49: =SUMIF('Income Statement Source'!$C:$C,'1. Income Statement'!$AR49,'Income Statement Source'!Q:Q)/1000 -> 14.90499 | P49: =SUMIF('Income Statement Source'!$C:$C,'1. Income Statement'!$AR49,'Income Statement Source'!R:R)/1000 -> 15.06362 | Q49: =SUM(E49:P49) -> 191.78023 | R49: =SUMIF('Income Statement Source'!$C:$C,'1. Income Statement'!$AR49,'Income Statement Source'!T:T)/1000 -> 14.66461 | S49: =SUMIF('Income Statement Source'!$C:$C,'1. Income Statement'!$AR49,'Income Statement Source'!U:U)/1000 -> 14.34938 | T49: =SUMIF('Income Statement Source'!$C:$C,'1. Income Statement'!$AR49,'Income Statement Source'!V:V)/1000 -> 14.42284 | U49: =SUMIF('Income Statement Source'!$C:$C,'1. Income Statement'!$AR49,'Income Statement Source'!W:W)/1000 -> 14.97625 | V49: =SUMIF('Income Statement Source'!$C:$C,'1. Income Statement'!$AR49,'Income Statement Source'!X:X)/1000 -> 22.59717 | W49: =SUMIF('Income Statement Source'!$C:$C,'1. Income Statement'!$AR49,'Income Statement Source'!Y:Y)/1000 -> 14.67444 | X49: =SUMIF('Income Statement Source'!$C:$C,'1. Income Statement'!$AR49,'Income Statement Source'!Z:Z)/1000 -> 15.05092 | Y49: =SUMIF('Income Statement Source'!$C:$C,'1. Income Statement'!$AR49,'Income Statement Source'!AA:AA)/1000 -> 14.39802 | Z49: =SUMIF('Income Statement Source'!$C:$C,'1. Income Statement'!$AR49,'Income Statement Source'!AB:AB)/1000 -> 14.37866 | AA49: =SUMIF('Income Statement Source'!$C:$C,'1. Income Statement'!$AR49,'Income Statement Source'!AC:AC)/1000 -> 21.94521 | AB49: =SUMIF('Income Statement Source'!$C:$C,'1. Income Statement'!$AR49,'Income Statement Source'!AD:AD)/1000 -> 14.38593 | AC49: =SUMIF('Income Statement Source'!$C:$C,'1. Income Statement'!$AR49,'Income Statement Source'!AE:AE)/1000 -> 14.51441 | AD49: =SUM(R49:AC49) -> 190.35784 | AE49: =SUMIF('Income Statement Source'!$C:$C,'1. Income Statement'!$AR49,'Income Statement Source'!AG:AG)/1000 -> 14.74103 | AF49: =SUMIF('Income Statement Source'!$C:$C,'1. Income Statement'!$AR49,'Income Statement Source'!AH:AH)/1000 -> 14.78242 | AG49: =SUMIF('Income Statement Source'!$C:$C,'1. Income Statement'!$AR49,'Income Statement Source'!AI:AI)/1000 -> 14.46684 | AH49: =SUMIF('Income Statement Source'!$C:$C,'1. Income Statement'!$AR49,'Income Statement Source'!AJ:AJ)/1000 -> 14.59678 | AI49: =SUMIF('Income Statement Source'!$C:$C,'1. Income Statement'!$AR49,'Income Statement Source'!AK:AK)/1000 -> 22.59972 | AJ49: =SUMIF('Income Statement Source'!$C:$C,'1. Income Statement'!$AR49,'Income Statement Source'!AL:AL)/1000 -> 14.36219 | AK49: =SUMIF('Income Statement Source'!$C:$C,'1. Income Statement'!$AR49,'Income Statement Source'!AM:AM)/1000 -> 14.34703 | AL49: =SUMIF('Income Statement Source'!$C:$C,'1. Income Statement'!$AR49,'Income Statement Source'!AN:AN)/1000 -> 14.4056 | AM49: =SUMIF('Income Statement Source'!$C:$C,'1. Income Statement'!$AR49,'Income Statement Source'!AO:AO)/1000 -> 14.37448 | AN49: =SUMIF('Income Statement Source'!$C:$C,'1. Income Statement'!$AR49,'Income Statement Source'!AP:AP)/1000 -> 21.84806 | AO49: =SUM(AE49:AN49) -> 160.52415 | AP49: =SUM(AO49,AB49:AC49) -> 189.42449 | AR49: Officer Salaries
B50: =+AR50 -> Office Salaries | E50: =SUMIF('Income Statement Source'!$C:$C,'1. Income Statement'!$AR50,'Income Statement Source'!G:G)/1000 -> 10.49007 | F50: =SUMIF('Income Statement Source'!$C:$C,'1. Income Statement'!$AR50,'Income Statement Source'!H:H)/1000 -> 10.39947 | G50: =SUMIF('Income Statement Source'!$C:$C,'1. Income Statement'!$AR50,'Income Statement Source'!I:I)/1000 -> 10.37827 | H50: =SUMIF('Income Statement Source'!$C:$C,'1. Income Statement'!$AR50,'Income Statement Source'!J:J)/1000 -> 10.65348 | I50: =SUMIF('Income Statement Source'!$C:$C,'1. Income Statement'!$AR50,'Income Statement Source'!K:K)/1000 -> 15.47846 | J50: =SUMIF('Income Statement Source'!$C:$C,'1. Income Statement'!$AR50,'Income Statement Source'!L:L)/1000 -> 10.26196 | K50: =SUMIF('Income Statement Source'!$C:$C,'1. Income Statement'!$AR50,'Income Statement Source'!M:M)/1000 -> 10.44299 | L50: =SUMIF('Income Statement Source'!$C:$C,'1. Income Statement'!$AR50,'Income Statement Source'!N:N)/1000 -> 10.30673 | M50: =SUMIF('Income Statement Source'!$C:$C,'1. Income Statement'!$AR50,'Income Statement Source'!O:O)/1000 -> 10.3778 | N50: =SUMIF('Income Statement Source'!$C:$C,'1. Income Statement'!$AR50,'Income Statement Source'!P:P)/1000 -> 15.50783 | O50: =SUMIF('Income Statement Source'!$C:$C,'1. Income Statement'!$AR50,'Income Statement Source'!Q:Q)/1000 -> 10.39142 | P50: =SUMIF('Income Statement Source'!$C:$C,'1. Income Statement'!$AR50,'Income Statement Source'!R:R)/1000 -> 10.66697 | Q50: =SUM(E50:P50) -> 135.35545 | R50: =SUMIF('Income Statement Source'!$C:$C,'1. Income Statement'!$AR50,'Income Statement Source'!T:T)/1000 -> 10.58362 | S50: =SUMIF('Income Statement Source'!$C:$C,'1. Income Statement'!$AR50,'Income Statement Source'!U:U)/1000 -> 10.3588 | T50: =SUMIF('Income Statement Source'!$C:$C,'1. Income Statement'!$AR50,'Income Statement Source'!V:V)/1000 -> 10.70188 | U50: =SUMIF('Income Statement Source'!$C:$C,'1. Income Statement'!$AR50,'Income Statement Source'!W:W)/1000 -> 10.62355 | V50: =SUMIF('Income Statement Source'!$C:$C,'1. Income Statement'!$AR50,'Income Statement Source'!X:X)/1000 -> 16.06961 | W50: =SUMIF('Income Statement Source'!$C:$C,'1. Income Statement'!$AR50,'Income Statement Source'!Y:Y)/1000 -> 10.35528 | X50: =SUMIF('Income Statement Source'!$C:$C,'1. Income Statement'!$AR50,'Income Statement Source'!Z:Z)/1000 -> 10.25305 | Y50: =SUMIF('Income Statement Source'!$C:$C,'1. Income Statement'!$AR50,'Income Statement Source'!AA:AA)/1000 -> 10.58769 | Z50: =SUMIF('Income Statement Source'!$C:$C,'1. Income Statement'!$AR50,'Income Statement Source'!AB:AB)/1000 -> 10.35999 | AA50: =SUMIF('Income Statement Source'!$C:$C,'1. Income Statement'!$AR50,'Income Statement Source'!AC:AC)/1000 -> 15.90609 | AB50: =SUMIF('Income Statement Source'!$C:$C,'1. Income Statement'!$AR50,'Income Statement Source'!AD:AD)/1000 -> 10.40049 | AC50: =SUMIF('Income Statement Source'!$C:$C,'1. Income Statement'!$AR50,'Income Statement Source'!AE:AE)/1000 -> 10.29393 | AD50: =SUM(R50:AC50) -> 136.49398 | AE50: =SUMIF('Income Statement Source'!$C:$C,'1. Income Statement'!$AR50,'Income Statement Source'!AG:AG)/1000 -> 10.2689 | AF50: =SUMIF('Income Statement Source'!$C:$C,'1. Income Statement'!$AR50,'Income Statement Source'!AH:AH)/1000 -> 10.34273 | AG50: =SUMIF('Income Statement Source'!$C:$C,'1. Income Statement'!$AR50,'Income Statement Source'!AI:AI)/1000 -> 10.55627 | AH50: =SUMIF('Income Statement Source'!$C:$C,'1. Income Statement'!$AR50,'Income Statement Source'!AJ:AJ)/1000 -> 10.67794 | AI50: =SUMIF('Income Statement Source'!$C:$C,'1. Income Statement'!$AR50,'Income Statement Source'!AK:AK)/1000 -> 15.37694 | AJ50: =SUMIF('Income Statement Source'!$C:$C,'1. Income Statement'!$AR50,'Income Statement Source'!AL:AL)/1000 -> 10.37989 | AK50: =SUMIF('Income Statement Source'!$C:$C,'1. Income Statement'!$AR50,'Income Statement Source'!AM:AM)/1000 -> 10.47105 | AL50: =SUMIF('Income Statement Source'!$C:$C,'1. Income Statement'!$AR50,'Income Statement Source'!AN:AN)/1000 -> 10.52717 | AM50: =SUMIF('Income Statement Source'!$C:$C,'1. Income Statement'!$AR50,'Income Statement Source'!AO:AO)/1000 -> 10.23864 | AN50: =SUMIF('Income Statement Source'!$C:$C,'1. Income Statement'!$AR50,'Income Statement Source'!AP:AP)/1000 -> 15.93043 | AO50: =SUM(AE50:AN50) -> 114.76996 | AP50: =SUM(AO50,AB50:AC50) -> 135.46438 | AR50: Office Salaries
B51: =+AR51 -> Project Manager Salaries | E51: =SUMIF('Income Statement Source'!$C:$C,'1. Income Statement'!$AR51,'Income Statement Source'!G:G)/1000 -> 8.33787 | F51: =SUMIF('Income Statement Source'!$C:$C,'1. Income Statement'!$AR51,'Income Statement Source'!H:H)/1000 -> 8.38257 | G51: =SUMIF('Income Statement Source'!$C:$C,'1. Income Statement'!$AR51,'Income Statement Source'!I:I)/1000 -> 8.26443 | H51: =SUMIF('Income Statement Source'!$C:$C,'1. Income Statement'!$AR51,'Income Statement Source'!J:J)/1000 -> 8.30337 | I51: =SUMIF('Income Statement Source'!$C:$C,'1. Income Statement'!$AR51,'Income Statement Source'!K:K)/1000 -> 12.61894 | J51: =SUMIF('Income Statement Source'!$C:$C,'1. Income Statement'!$AR51,'Income Statement Source'!L:L)/1000 -> 8.39842 | K51: =SUMIF('Income Statement Source'!$C:$C,'1. Income Statement'!$AR51,'Income Statement Source'!M:M)/1000 -> 8.23286 | L51: =SUMIF('Income Statement Source'!$C:$C,'1. Income Statement'!$AR51,'Income Statement Source'!N:N)/1000 -> 8.30108 | M51: =SUMIF('Income Statement Source'!$C:$C,'1. Income Statement'!$AR51,'Income Statement Source'!O:O)/1000 -> 8.31525 | N51: =SUMIF('Income Statement Source'!$C:$C,'1. Income Statement'!$AR51,'Income Statement Source'!P:P)/1000 -> 12.69235 | O51: =SUMIF('Income Statement Source'!$C:$C,'1. Income Statement'!$AR51,'Income Statement Source'!Q:Q)/1000 -> 8.44831 | P51: =SUMIF('Income Statement Source'!$C:$C,'1. Income Statement'!$AR51,'Income Statement Source'!R:R)/1000 -> 8.43529 | Q51: =SUM(E51:P51) -> 108.73074 | R51: =SUMIF('Income Statement Source'!$C:$C,'1. Income Statement'!$AR51,'Income Statement Source'!T:T)/1000 -> 8.20142 | S51: =SUMIF('Income Statement Source'!$C:$C,'1. Income Statement'!$AR51,'Income Statement Source'!U:U)/1000 -> 8.36999 | T51: =SUMIF('Income Statement Source'!$C:$C,'1. Income Statement'!$AR51,'Income Statement Source'!V:V)/1000 -> 8.45961 | U51: =SUMIF('Income Statement Source'!$C:$C,'1. Income Statement'!$AR51,'Income Statement Source'!W:W)/1000 -> 8.20371 | V51: =SUMIF('Income Statement Source'!$C:$C,'1. Income Statement'!$AR51,'Income Statement Source'!X:X)/1000 -> 12.88581 | W51: =SUMIF('Income Statement Source'!$C:$C,'1. Income Statement'!$AR51,'Income Statement Source'!Y:Y)/1000 -> 8.4593 | X51: =SUMIF('Income Statement Source'!$C:$C,'1. Income Statement'!$AR51,'Income Statement Source'!Z:Z)/1000 -> 8.46394 | Y51: =SUMIF('Income Statement Source'!$C:$C,'1. Income Statement'!$AR51,'Income Statement Source'!AA:AA)/1000 -> 8.55762 | Z51: =SUMIF('Income Statement Source'!$C:$C,'1. Income Statement'!$AR51,'Income Statement Source'!AB:AB)/1000 -> 8.22101 | AA51: =SUMIF('Income Statement Source'!$C:$C,'1. Income Statement'!$AR51,'Income Statement Source'!AC:AC)/1000 -> 12.44303 | AB51: =SUMIF('Income Statement Source'!$C:$C,'1. Income Statement'!$AR51,'Income Statement Source'!AD:AD)/1000 -> 8.57542 | AC51: =SUMIF('Income Statement Source'!$C:$C,'1. Income Statement'!$AR51,'Income Statement Source'!AE:AE)/1000 -> 8.22899 | AD51: =SUM(R51:AC51) -> 109.06985 | AE51: =SUMIF('Income Statement Source'!$C:$C,'1. Income Statement'!$AR51,'Income Statement Source'!AG:AG)/1000 -> 8.46873 | AF51: =SUMIF('Income Statement Source'!$C:$C,'1. Income Statement'!$AR51,'Income Statement Source'!AH:AH)/1000 -> 8.5903 | AG51: =SUMIF('Income Statement Source'!$C:$C,'1. Income Statement'!$AR51,'Income Statement Source'!AI:AI)/1000 -> 8.60684 | AH51: =SUMIF('Income Statement Source'!$C:$C,'1. Income Statement'!$AR51,'Income Statement Source'!AJ:AJ)/1000 -> 8.23477 | AI51: =SUMIF('Income Statement Source'!$C:$C,'1. Income Statement'!$AR51,'Income Statement Source'!AK:AK)/1000 -> 12.28917 | AJ51: =SUMIF('Income Statement Source'!$C:$C,'1. Income Statement'!$AR51,'Income Statement Source'!AL:AL)/1000 -> 8.31347 | AK51: =SUMIF('Income Statement Source'!$C:$C,'1. Income Statement'!$AR51,'Income Statement Source'!AM:AM)/1000 -> 8.28903 | AL51: =SUMIF('Income Statement Source'!$C:$C,'1. Income Statement'!$AR51,'Income Statement Source'!AN:AN)/1000 -> 8.57816 | AM51: =SUMIF('Income Statement Source'!$C:$C,'1. Income Statement'!$AR51,'Income Statement Source'!AO:AO)/1000 -> 8.22654 | AN51: =SUMIF('Income Statement Source'!$C:$C,'1. Income Statement'!$AR51,'Income Statement Source'!AP:AP)/1000 -> 12.88493 | AO51: =SUM(AE51:AN51) -> 92.48194 | AP51: =SUM(AO51,AB51:AC51) -> 109.28635 | AR51: Project Manager Salaries
B52: =+AR52 -> Field Supervisor Salaries | E52: =SUMIF('Income Statement Source'!$C:$C,'1. Income Statement'!$AR52,'Income Statement Source'!G:G)/1000 -> 8.36238 | F52: =SUMIF('Income Statement Source'!$C:$C,'1. Income Statement'!$AR52,'Income Statement Source'!H:H)/1000 -> 8.60701 | G52: =SUMIF('Income Statement Source'!$C:$C,'1. Income Statement'!$AR52,'Income Statement Source'!I:I)/1000 -> 8.24278 | H52: =SUMIF('Income Statement Source'!$C:$C,'1. Income Statement'!$AR52,'Income Statement Source'!J:J)/1000 -> 8.31783 | I52: =SUMIF('Income Statement Source'!$C:$C,'1. Income Statement'!$AR52,'Income Statement Source'!K:K)/1000 -> 12.74375 | J52: =SUMIF('Income Statement Source'!$C:$C,'1. Income Statement'!$AR52,'Income Statement Source'!L:L)/1000 -> 8.29573 | K52: =SUMIF('Income Statement Source'!$C:$C,'1. Income Statement'!$AR52,'Income Statement Source'!M:M)/1000 -> 8.44237 | L52: =SUMIF('Income Statement Source'!$C:$C,'1. Income Statement'!$AR52,'Income Statement Source'!N:N)/1000 -> 8.53799 | M52: =SUMIF('Income Statement Source'!$C:$C,'1. Income Statement'!$AR52,'Income Statement Source'!O:O)/1000 -> 8.58169 | N52: =SUMIF('Income Statement Source'!$C:$C,'1. Income Statement'!$AR52,'Income Statement Source'!P:P)/1000 -> 12.61825 | O52: =SUMIF('Income Statement Source'!$C:$C,'1. Income Statement'!$AR52,'Income Statement Source'!Q:Q)/1000 -> 8.26998 | P52: =SUMIF('Income Statement Source'!$C:$C,'1. Income Statement'!$AR52,'Income Statement Source'!R:R)/1000 -> 8.21351 | Q52: =SUM(E52:P52) -> 109.23327 | R52: =SUMIF('Income Statement Source'!$C:$C,'1. Income Statement'!$AR52,'Income Statement Source'!T:T)/1000 -> 8.41381 | S52: =SUMIF('Income Statement Source'!$C:$C,'1. Income Statement'!$AR52,'Income Statement Source'!U:U)/1000 -> 8.19229 | T52: =SUMIF('Income Statement Source'!$C:$C,'1. Income Statement'!$AR52,'Income Statement Source'!V:V)/1000 -> 8.58411 | U52: =SUMIF('Income Statement Source'!$C:$C,'1. Income Statement'!$AR52,'Income Statement Source'!W:W)/1000 -> 8.49176 | V52: =SUMIF('Income Statement Source'!$C:$C,'1. Income Statement'!$AR52,'Income Statement Source'!X:X)/1000 -> 12.28891 | W52: =SUMIF('Income Statement Source'!$C:$C,'1. Income Statement'!$AR52,'Income Statement Source'!Y:Y)/1000 -> 8.49527 | X52: =SUMIF('Income Statement Source'!$C:$C,'1. Income Statement'!$AR52,'Income Statement Source'!Z:Z)/1000 -> 8.2793 | Y52: =SUMIF('Income Statement Source'!$C:$C,'1. Income Statement'!$AR52,'Income Statement Source'!AA:AA)/1000 -> 8.40122 | Z52: =SUMIF('Income Statement Source'!$C:$C,'1. Income Statement'!$AR52,'Income Statement Source'!AB:AB)/1000 -> 8.43129 | AA52: =SUMIF('Income Statement Source'!$C:$C,'1. Income Statement'!$AR52,'Income Statement Source'!AC:AC)/1000 -> 12.36018 | AB52: =SUMIF('Income Statement Source'!$C:$C,'1. Income Statement'!$AR52,'Income Statement Source'!AD:AD)/1000 -> 8.31884 | AC52: =SUMIF('Income Statement Source'!$C:$C,'1. Income Statement'!$AR52,'Income Statement Source'!AE:AE)/1000 -> 8.32564 | AD52: =SUM(R52:AC52) -> 108.58262 | AE52: =SUMIF('Income Statement Source'!$C:$C,'1. Income Statement'!$AR52,'Income Statement Source'!AG:AG)/1000 -> 8.48614 | AF52: =SUMIF('Income Statement Source'!$C:$C,'1. Income Statement'!$AR52,'Income Statement Source'!AH:AH)/1000 -> 8.35638 | AG52: =SUMIF('Income Statement Source'!$C:$C,'1. Income Statement'!$AR52,'Income Statement Source'!AI:AI)/1000 -> 8.31232 | AH52: =SUMIF('Income Statement Source'!$C:$C,'1. Income Statement'!$AR52,'Income Statement Source'!AJ:AJ)/1000 -> 8.25396 | AI52: =SUMIF('Income Statement Source'!$C:$C,'1. Income Statement'!$AR52,'Income Statement Source'!AK:AK)/1000 -> 12.64359 | AJ52: =SUMIF('Income Statement Source'!$C:$C,'1. Income Statement'!$AR52,'Income Statement Source'!AL:AL)/1000 -> 8.4127 | AK52: =SUMIF('Income Statement Source'!$C:$C,'1. Income Statement'!$AR52,'Income Statement Source'!AM:AM)/1000 -> 8.27009 | AL52: =SUMIF('Income Statement Source'!$C:$C,'1. Income Statement'!$AR52,'Income Statement Source'!AN:AN)/1000 -> 8.34144 | AM52: =SUMIF('Income Statement Source'!$C:$C,'1. Income Statement'!$AR52,'Income Statement Source'!AO:AO)/1000 -> 8.42789 | AN52: =SUMIF('Income Statement Source'!$C:$C,'1. Income Statement'!$AR52,'Income Statement Source'!AP:AP)/1000 -> 12.84699 | AO52: =SUM(AE52:AN52) -> 92.3515 | AP52: =SUM(AO52,AB52:AC52) -> 108.99598 | AR52: Field Supervisor Salaries
B53: =+AR53 -> Bonus Expense | E53: =SUMIF('Income Statement Source'!$C:$C,'1. Income Statement'!$AR53,'Income Statement Source'!G:G)/1000 -> 0 | F53: =SUMIF('Income Statement Source'!$C:$C,'1. Income Statement'!$AR53,'Income Statement Source'!H:H)/1000 -> 0 | G53: =SUMIF('Income Statement Source'!$C:$C,'1. Income Statement'!$AR53,'Income Statement Source'!I:I)/1000 -> 0 | H53: =SUMIF('Income Statement Source'!$C:$C,'1. Income Statement'!$AR53,'Income Statement Source'!J:J)/1000 -> 0 | I53: =SUMIF('Income Statement Source'!$C:$C,'1. Income Statement'!$AR53,'Income Statement Source'!K:K)/1000 -> 0 | J53: =SUMIF('Income Statement Source'!$C:$C,'1. Income Statement'!$AR53,'Income Statement Source'!L:L)/1000 -> 0 | K53: =SUMIF('Income Statement Source'!$C:$C,'1. Income Statement'!$AR53,'Income Statement Source'!M:M)/1000 -> 0 | L53: =SUMIF('Income Statement Source'!$C:$C,'1. Income Statement'!$AR53,'Income Statement Source'!N:N)/1000 -> 0 | M53: =SUMIF('Income Statement Source'!$C:$C,'1. Income Statement'!$AR53,'Income Statement Source'!O:O)/1000 -> 0 | N53: =SUMIF('Income Statement Source'!$C:$C,'1. Income Statement'!$AR53,'Income Statement Source'!P:P)/1000 -> 0 | O53: =SUMIF('Income Statement Source'!$C:$C,'1. Income Statement'!$AR53,'Income Statement Source'!Q:Q)/1000 -> 0 | P53: =SUMIF('Income Statement Source'!$C:$C,'1. Income Statement'!$AR53,'Income Statement Source'!R:R)/1000 -> 34.36487 | Q53: =SUM(E53:P53) -> 34.36487 | R53: =SUMIF('Income Statement Source'!$C:$C,'1. Income Statement'!$AR53,'Income Statement Source'!T:T)/1000 -> 0 | S53: =SUMIF('Income Statement Source'!$C:$C,'1. Income Statement'!$AR53,'Income Statement Source'!U:U)/1000 -> 0 | T53: =SUMIF('Income Statement Source'!$C:$C,'1. Income Statement'!$AR53,'Income Statement Source'!V:V)/1000 -> 0 | U53: =SUMIF('Income Statement Source'!$C:$C,'1. Income Statement'!$AR53,'Income Statement Source'!W:W)/1000 -> 0 | V53: =SUMIF('Income Statement Source'!$C:$C,'1. Income Statement'!$AR53,'Income Statement Source'!X:X)/1000 -> 0 | W53: =SUMIF('Income Statement Source'!$C:$C,'1. Income Statement'!$AR53,'Income Statement Source'!Y:Y)/1000 -> 0 | X53: =SUMIF('Income Statement Source'!$C:$C,'1. Income Statement'!$AR53,'Income Statement Source'!Z:Z)/1000 -> 0 | Y53: =SUMIF('Income Statement Source'!$C:$C,'1. Income Statement'!$AR53,'Income Statement Source'!AA:AA)/1000 -> 0 | Z53: =SUMIF('Income Statement Source'!$C:$C,'1. Income Statement'!$AR53,'Income Statement Source'!AB:AB)/1000 -> 0 | AA53: =SUMIF('Income Statement Source'!$C:$C,'1. Income Statement'!$AR53,'Income Statement Source'!AC:AC)/1000 -> 0 | AB53: =SUMIF('Income Statement Source'!$C:$C,'1. Income Statement'!$AR53,'Income Statement Source'!AD:AD)/1000 -> 0 | AC53: =SUMIF('Income Statement Source'!$C:$C,'1. Income Statement'!$AR53,'Income Statement Source'!AE:AE)/1000 -> 36.21906 | AD53: =SUM(R53:AC53) -> 36.21906 | AE53: =SUMIF('Income Statement Source'!$C:$C,'1. Income Statement'!$AR53,'Income Statement Source'!AG:AG)/1000 -> 0 | AF53: =SUMIF('Income Statement Source'!$C:$C,'1. Income Statement'!$AR53,'Income Statement Source'!AH:AH)/1000 -> 3.13084 | AG53: =SUMIF('Income Statement Source'!$C:$C,'1. Income Statement'!$AR53,'Income Statement Source'!AI:AI)/1000 -> 2.86244 | AH53: =SUMIF('Income Statement Source'!$C:$C,'1. Income Statement'!$AR53,'Income Statement Source'!AJ:AJ)/1000 -> 2.90484 | AI53: =SUMIF('Income Statement Source'!$C:$C,'1. Income Statement'!$AR53,'Income Statement Source'!AK:AK)/1000 -> 3.01274 | AJ53: =SUMIF('Income Statement Source'!$C:$C,'1. Income Statement'!$AR53,'Income Statement Source'!AL:AL)/1000 -> 3.11238 | AK53: =SUMIF('Income Statement Source'!$C:$C,'1. Income Statement'!$AR53,'Income Statement Source'!AM:AM)/1000 -> 3.02305 | AL53: =SUMIF('Income Statement Source'!$C:$C,'1. Income Statement'!$AR53,'Income Statement Source'!AN:AN)/1000 -> 3.08584 | AM53: =SUMIF('Income Statement Source'!$C:$C,'1. Income Statement'!$AR53,'Income Statement Source'!AO:AO)/1000 -> 3.13288 | AN53: =SUMIF('Income Statement Source'!$C:$C,'1. Income Statement'!$AR53,'Income Statement Source'!AP:AP)/1000 -> 3.22184 | AO53: =SUM(AE53:AN53) -> 27.48685 | AP53: =SUM(AO53,AB53:AC53) -> 63.70591 | AR53: Bonus Expense
B54: =+AR54 -> Payroll Taxes | E54: =SUMIF('Income Statement Source'!$C:$C,'1. Income Statement'!$AR54,'Income Statement Source'!G:G)/1000 -> 3.99779 | F54: =SUMIF('Income Statement Source'!$C:$C,'1. Income Statement'!$AR54,'Income Statement Source'!H:H)/1000 -> 3.985 | G54: =SUMIF('Income Statement Source'!$C:$C,'1. Income Statement'!$AR54,'Income Statement Source'!I:I)/1000 -> 3.98749 | H54: =SUMIF('Income Statement Source'!$C:$C,'1. Income Statement'!$AR54,'Income Statement Source'!J:J)/1000 -> 4.00493 | I54: =SUMIF('Income Statement Source'!$C:$C,'1. Income Statement'!$AR54,'Income Statement Source'!K:K)/1000 -> 9.00664 | J54: =SUMIF('Income Statement Source'!$C:$C,'1. Income Statement'!$AR54,'Income Statement Source'!L:L)/1000 -> 4.05529 | K54: =SUMIF('Income Statement Source'!$C:$C,'1. Income Statement'!$AR54,'Income Statement Source'!M:M)/1000 -> 4.08497 | L54: =SUMIF('Income Statement Source'!$C:$C,'1. Income Statement'!$AR54,'Income Statement Source'!N:N)/1000 -> 4.00071 | M54: =SUMIF('Income Statement Source'!$C:$C,'1. Income Statement'!$AR54,'Income Statement Source'!O:O)/1000 -> 4.073 | N54: =SUMIF('Income Statement Source'!$C:$C,'1. Income Statement'!$AR54,'Income Statement Source'!P:P)/1000 -> 8.92234 | O54: =SUMIF('Income Statement Source'!$C:$C,'1. Income Statement'!$AR54,'Income Statement Source'!Q:Q)/1000 -> 3.90142 | P54: =SUMIF('Income Statement Source'!$C:$C,'1. Income Statement'!$AR54,'Income Statement Source'!R:R)/1000 -> 3.98076 | Q54: =SUM(E54:P54) -> 58.00034 | R54: =SUMIF('Income Statement Source'!$C:$C,'1. Income Statement'!$AR54,'Income Statement Source'!T:T)/1000 -> 4.08378 | S54: =SUMIF('Income Statement Source'!$C:$C,'1. Income Statement'!$AR54,'Income Statement Source'!U:U)/1000 -> 3.9789 | T54: =SUMIF('Income Statement Source'!$C:$C,'1. Income Statement'!$AR54,'Income Statement Source'!V:V)/1000 -> 3.94342 | U54: =SUMIF('Income Statement Source'!$C:$C,'1. Income Statement'!$AR54,'Income Statement Source'!W:W)/1000 -> 4.03866 | V54: =SUMIF('Income Statement Source'!$C:$C,'1. Income Statement'!$AR54,'Income Statement Source'!X:X)/1000 -> 9.08022 | W54: =SUMIF('Income Statement Source'!$C:$C,'1. Income Statement'!$AR54,'Income Statement Source'!Y:Y)/1000 -> 4.05851 | X54: =SUMIF('Income Statement Source'!$C:$C,'1. Income Statement'!$AR54,'Income Statement Source'!Z:Z)/1000 -> 4.08339 | Y54: =SUMIF('Income Statement Source'!$C:$C,'1. Income Statement'!$AR54,'Income Statement Source'!AA:AA)/1000 -> 3.92843 | Z54: =SUMIF('Income Statement Source'!$C:$C,'1. Income Statement'!$AR54,'Income Statement Source'!AB:AB)/1000 -> 4.00324 | AA54: =SUMIF('Income Statement Source'!$C:$C,'1. Income Statement'!$AR54,'Income Statement Source'!AC:AC)/1000 -> 9.09194 | AB54: =SUMIF('Income Statement Source'!$C:$C,'1. Income Statement'!$AR54,'Income Statement Source'!AD:AD)/1000 -> 4.0678 | AC54: =SUMIF('Income Statement Source'!$C:$C,'1. Income Statement'!$AR54,'Income Statement Source'!AE:AE)/1000 -> 3.97952 | AD54: =SUM(R54:AC54) -> 58.33781 | AE54: =SUMIF('Income Statement Source'!$C:$C,'1. Income Statement'!$AR54,'Income Statement Source'!AG:AG)/1000 -> 4.05232 | AF54: =SUMIF('Income Statement Source'!$C:$C,'1. Income Statement'!$AR54,'Income Statement Source'!AH:AH)/1000 -> 3.96692 | AG54: =SUMIF('Income Statement Source'!$C:$C,'1. Income Statement'!$AR54,'Income Statement Source'!AI:AI)/1000 -> 4.07816 | AH54: =SUMIF('Income Statement Source'!$C:$C,'1. Income Statement'!$AR54,'Income Statement Source'!AJ:AJ)/1000 -> 3.93013 | AI54: =SUMIF('Income Statement Source'!$C:$C,'1. Income Statement'!$AR54,'Income Statement Source'!AK:AK)/1000 -> 8.90937 | AJ54: =SUMIF('Income Statement Source'!$C:$C,'1. Income Statement'!$AR54,'Income Statement Source'!AL:AL)/1000 -> 4.0233 | AK54: =SUMIF('Income Statement Source'!$C:$C,'1. Income Statement'!$AR54,'Income Statement Source'!AM:AM)/1000 -> 3.89135 | AL54: =SUMIF('Income Statement Source'!$C:$C,'1. Income Statement'!$AR54,'Income Statement Source'!AN:AN)/1000 -> 4.04492 | AM54: =SUMIF('Income Statement Source'!$C:$C,'1. Income Statement'!$AR54,'Income Statement Source'!AO:AO)/1000 -> 4.07529 | AN54: =SUMIF('Income Statement Source'!$C:$C,'1. Income Statement'!$AR54,'Income Statement Source'!AP:AP)/1000 -> 8.87478 | AO54: =SUM(AE54:AN54) -> 49.84654 | AP54: =SUM(AO54,AB54:AC54) -> 57.89386 | AR54: Payroll Taxes
B55: =+AR55 -> Health Insurance | E55: =SUMIF('Income Statement Source'!$C:$C,'1. Income Statement'!$AR55,'Income Statement Source'!G:G)/1000 -> 4.22185 | F55: =SUMIF('Income Statement Source'!$C:$C,'1. Income Statement'!$AR55,'Income Statement Source'!H:H)/1000 -> 4.15007 | G55: =SUMIF('Income Statement Source'!$C:$C,'1. Income Statement'!$AR55,'Income Statement Source'!I:I)/1000 -> 4.15733 | H55: =SUMIF('Income Statement Source'!$C:$C,'1. Income Statement'!$AR55,'Income Statement Source'!J:J)/1000 -> 4.2306 | I55: =SUMIF('Income Statement Source'!$C:$C,'1. Income Statement'!$AR55,'Income Statement Source'!K:K)/1000 -> 4.23405 | J55: =SUMIF('Income Statement Source'!$C:$C,'1. Income Statement'!$AR55,'Income Statement Source'!L:L)/1000 -> 4.21435 | K55: =SUMIF('Income Statement Source'!$C:$C,'1. Income Statement'!$AR55,'Income Statement Source'!M:M)/1000 -> 4.14128 | L55: =SUMIF('Income Statement Source'!$C:$C,'1. Income Statement'!$AR55,'Income Statement Source'!N:N)/1000 -> 4.15222 | M55: =SUMIF('Income Statement Source'!$C:$C,'1. Income Statement'!$AR55,'Income Statement Source'!O:O)/1000 -> 4.23156 | N55: =SUMIF('Income Statement Source'!$C:$C,'1. Income Statement'!$AR55,'Income Statement Source'!P:P)/1000 -> 4.14227 | O55: =SUMIF('Income Statement Source'!$C:$C,'1. Income Statement'!$AR55,'Income Statement Source'!Q:Q)/1000 -> 4.15923 | P55: =SUMIF('Income Statement Source'!$C:$C,'1. Income Statement'!$AR55,'Income Statement Source'!R:R)/1000 -> 4.1952 | Q55: =SUM(E55:P55) -> 50.23001 | R55: =SUMIF('Income Statement Source'!$C:$C,'1. Income Statement'!$AR55,'Income Statement Source'!T:T)/1000 -> 4.18502 | S55: =SUMIF('Income Statement Source'!$C:$C,'1. Income Statement'!$AR55,'Income Statement Source'!U:U)/1000 -> 4.17865 | T55: =SUMIF('Income Statement Source'!$C:$C,'1. Income Statement'!$AR55,'Income Statement Source'!V:V)/1000 -> 4.26103 | U55: =SUMIF('Income Statement Source'!$C:$C,'1. Income Statement'!$AR55,'Income Statement Source'!W:W)/1000 -> 4.24973 | V55: =SUMIF('Income Statement Source'!$C:$C,'1. Income Statement'!$AR55,'Income Statement Source'!X:X)/1000 -> 4.22299 | W55: =SUMIF('Income Statement Source'!$C:$C,'1. Income Statement'!$AR55,'Income Statement Source'!Y:Y)/1000 -> 4.13982 | X55: =SUMIF('Income Statement Source'!$C:$C,'1. Income Statement'!$AR55,'Income Statement Source'!Z:Z)/1000 -> 4.2327 | Y55: =SUMIF('Income Statement Source'!$C:$C,'1. Income Statement'!$AR55,'Income Statement Source'!AA:AA)/1000 -> 4.21377 | Z55: =SUMIF('Income Statement Source'!$C:$C,'1. Income Statement'!$AR55,'Income Statement Source'!AB:AB)/1000 -> 4.15857 | AA55: =SUMIF('Income Statement Source'!$C:$C,'1. Income Statement'!$AR55,'Income Statement Source'!AC:AC)/1000 -> 4.26157 | AB55: =SUMIF('Income Statement Source'!$C:$C,'1. Income Statement'!$AR55,'Income Statement Source'!AD:AD)/1000 -> 4.25454 | AC55: =SUMIF('Income Statement Source'!$C:$C,'1. Income Statement'!$AR55,'Income Statement Source'!AE:AE)/1000 -> 4.14474 | AD55: =SUM(R55:AC55) -> 50.50313 | AE55: =SUMIF('Income Statement Source'!$C:$C,'1. Income Statement'!$AR55,'Income Statement Source'!AG:AG)/1000 -> 4.19726 | AF55: =SUMIF('Income Statement Source'!$C:$C,'1. Income Statement'!$AR55,'Income Statement Source'!AH:AH)/1000 -> 4.19391 | AG55: =SUMIF('Income Statement Source'!$C:$C,'1. Income Statement'!$AR55,'Income Statement Source'!AI:AI)/1000 -> 4.22361 | AH55: =SUMIF('Income Statement Source'!$C:$C,'1. Income Statement'!$AR55,'Income Statement Source'!AJ:AJ)/1000 -> 4.16603 | AI55: =SUMIF('Income Statement Source'!$C:$C,'1. Income Statement'!$AR55,'Income Statement Source'!AK:AK)/1000 -> 4.26286 | AJ55: =SUMIF('Income Statement Source'!$C:$C,'1. Income Statement'!$AR55,'Income Statement Source'!AL:AL)/1000 -> 4.22169 | AK55: =SUMIF('Income Statement Source'!$C:$C,'1. Income Statement'!$AR55,'Income Statement Source'!AM:AM)/1000 -> 4.25011 | AL55: =SUMIF('Income Statement Source'!$C:$C,'1. Income Statement'!$AR55,'Income Statement Source'!AN:AN)/1000 -> 4.16798 | AM55: =SUMIF('Income Statement Source'!$C:$C,'1. Income Statement'!$AR55,'Income Statement Source'!AO:AO)/1000 -> 4.21398 | AN55: =SUMIF('Income Statement Source'!$C:$C,'1. Income Statement'!$AR55,'Income Statement Source'!AP:AP)/1000 -> 4.14348 | AO55: =SUM(AE55:AN55) -> 42.04091 | AP55: =SUM(AO55,AB55:AC55) -> 50.44019 | AR55: Health Insurance
B56: =+B48 -> Personnel | E56: =SUM(E49:E55) -> 49.97632 | F56: =SUM(F49:F55) -> 50.36516 | G56: =SUM(G49:G55) -> 49.66975 | H56: =SUM(H49:H55) -> 50.40003 | I56: =SUM(I49:I55) -> 76.32234 | J56: =SUM(J49:J55) -> 49.74912 | K56: =SUM(K49:K55) -> 49.99244 | L56: =SUM(L49:L55) -> 50.33846 | ... AP56: =SUM(AP49:AP55) -> 715.21116
E57: =IFERROR(E56/E$19,0) -> 0.26306646 | F57: =IFERROR(F56/F$19,0) -> 0.22159987 | G57: =IFERROR(G56/G$19,0) -> 0.16146698 | H57: =IFERROR(H56/H$19,0) -> 0.19486268 | I57: =IFERROR(I56/I$19,0) -> 0.28082706 | J57: =IFERROR(J56/J$19,0) -> 0.13509418 | K57: =IFERROR(K56/K$19,0) -> 0.16526613 | L57: =IFERROR(L56/L$19,0) -> 0.18158138 | ... AP57: =IFERROR(AP56/AP$19,0) -> 0.16863134
B58: Insurance
B59: =+AR59 -> Workers Compensation Insurance | E59: =SUMIF('Income Statement Source'!$C:$C,'1. Income Statement'!$AR59,'Income Statement Source'!G:G)/1000 -> 5.78158 | F59: =SUMIF('Income Statement Source'!$C:$C,'1. Income Statement'!$AR59,'Income Statement Source'!H:H)/1000 -> 5.92159 | G59: =SUMIF('Income Statement Source'!$C:$C,'1. Income Statement'!$AR59,'Income Statement Source'!I:I)/1000 -> 5.5837 | H59: =SUMIF('Income Statement Source'!$C:$C,'1. Income Statement'!$AR59,'Income Statement Source'!J:J)/1000 -> 5.66555 | I59: =SUMIF('Income Statement Source'!$C:$C,'1. Income Statement'!$AR59,'Income Statement Source'!K:K)/1000 -> 5.75911 | J59: =SUMIF('Income Statement Source'!$C:$C,'1. Income Statement'!$AR59,'Income Statement Source'!L:L)/1000 -> 5.71267 | K59: =SUMIF('Income Statement Source'!$C:$C,'1. Income Statement'!$AR59,'Income Statement Source'!M:M)/1000 -> 5.8305 | L59: =SUMIF('Income Statement Source'!$C:$C,'1. Income Statement'!$AR59,'Income Statement Source'!N:N)/1000 -> 5.79203 | M59: =SUMIF('Income Statement Source'!$C:$C,'1. Income Statement'!$AR59,'Income Statement Source'!O:O)/1000 -> 5.62923 | N59: =SUMIF('Income Statement Source'!$C:$C,'1. Income Statement'!$AR59,'Income Statement Source'!P:P)/1000 -> 5.79103 | O59: =SUMIF('Income Statement Source'!$C:$C,'1. Income Statement'!$AR59,'Income Statement Source'!Q:Q)/1000 -> 5.58193 | P59: =SUMIF('Income Statement Source'!$C:$C,'1. Income Statement'!$AR59,'Income Statement Source'!R:R)/1000 -> 5.98485 | Q59: =SUM(E59:P59) -> 69.03377 | R59: =SUMIF('Income Statement Source'!$C:$C,'1. Income Statement'!$AR59,'Income Statement Source'!T:T)/1000 -> 5.943 | S59: =SUMIF('Income Statement Source'!$C:$C,'1. Income Statement'!$AR59,'Income Statement Source'!U:U)/1000 -> 5.60493 | T59: =SUMIF('Income Statement Source'!$C:$C,'1. Income Statement'!$AR59,'Income Statement Source'!V:V)/1000 -> 5.63333 | U59: =SUMIF('Income Statement Source'!$C:$C,'1. Income Statement'!$AR59,'Income Statement Source'!W:W)/1000 -> 5.65327 | V59: =SUMIF('Income Statement Source'!$C:$C,'1. Income Statement'!$AR59,'Income Statement Source'!X:X)/1000 -> 5.77179 | W59: =SUMIF('Income Statement Source'!$C:$C,'1. Income Statement'!$AR59,'Income Statement Source'!Y:Y)/1000 -> 5.95148 | X59: =SUMIF('Income Statement Source'!$C:$C,'1. Income Statement'!$AR59,'Income Statement Source'!Z:Z)/1000 -> 5.75398 | Y59: =SUMIF('Income Statement Source'!$C:$C,'1. Income Statement'!$AR59,'Income Statement Source'!AA:AA)/1000 -> 5.83722 | Z59: =SUMIF('Income Statement Source'!$C:$C,'1. Income Statement'!$AR59,'Income Statement Source'!AB:AB)/1000 -> 5.9824 | AA59: =SUMIF('Income Statement Source'!$C:$C,'1. Income Statement'!$AR59,'Income Statement Source'!AC:AC)/1000 -> 5.92711 | AB59: =SUMIF('Income Statement Source'!$C:$C,'1. Income Statement'!$AR59,'Income Statement Source'!AD:AD)/1000 -> 5.68657 | AC59: =SUMIF('Income Statement Source'!$C:$C,'1. Income Statement'!$AR59,'Income Statement Source'!AE:AE)/1000 -> 5.9705 | AD59: =SUM(R59:AC59) -> 69.71558 | AE59: =SUMIF('Income Statement Source'!$C:$C,'1. Income Statement'!$AR59,'Income Statement Source'!AG:AG)/1000 -> 5.82174 | AF59: =SUMIF('Income Statement Source'!$C:$C,'1. Income Statement'!$AR59,'Income Statement Source'!AH:AH)/1000 -> 5.99859 | AG59: =SUMIF('Income Statement Source'!$C:$C,'1. Income Statement'!$AR59,'Income Statement Source'!AI:AI)/1000 -> 5.79491 | AH59: =SUMIF('Income Statement Source'!$C:$C,'1. Income Statement'!$AR59,'Income Statement Source'!AJ:AJ)/1000 -> 6.01286 | AI59: =SUMIF('Income Statement Source'!$C:$C,'1. Income Statement'!$AR59,'Income Statement Source'!AK:AK)/1000 -> 5.73282 | AJ59: =SUMIF('Income Statement Source'!$C:$C,'1. Income Statement'!$AR59,'Income Statement Source'!AL:AL)/1000 -> 5.68264 | AK59: =SUMIF('Income Statement Source'!$C:$C,'1. Income Statement'!$AR59,'Income Statement Source'!AM:AM)/1000 -> 5.70897 | AL59: =SUMIF('Income Statement Source'!$C:$C,'1. Income Statement'!$AR59,'Income Statement Source'!AN:AN)/1000 -> 5.88363 | AM59: =SUMIF('Income Statement Source'!$C:$C,'1. Income Statement'!$AR59,'Income Statement Source'!AO:AO)/1000 -> 5.83029 | AN59: =SUMIF('Income Statement Source'!$C:$C,'1. Income Statement'!$AR59,'Income Statement Source'!AP:AP)/1000 -> 5.65601 | AO59: =SUM(AE59:AN59) -> 58.12246 | AP59: =SUM(AO59,AB59:AC59) -> 69.77953 | AR59: Workers Compensation Insurance
B60: =+AR60 -> General Liability Insurance | E60: =SUMIF('Income Statement Source'!$C:$C,'1. Income Statement'!$AR60,'Income Statement Source'!G:G)/1000 -> 8.55713 | F60: =SUMIF('Income Statement Source'!$C:$C,'1. Income Statement'!$AR60,'Income Statement Source'!H:H)/1000 -> 1.41489 | G60: =SUMIF('Income Statement Source'!$C:$C,'1. Income Statement'!$AR60,'Income Statement Source'!I:I)/1000 -> 1.3727 | H60: =SUMIF('Income Statement Source'!$C:$C,'1. Income Statement'!$AR60,'Income Statement Source'!J:J)/1000 -> 1.37306 | I60: =SUMIF('Income Statement Source'!$C:$C,'1. Income Statement'!$AR60,'Income Statement Source'!K:K)/1000 -> 1.42976 | J60: =SUMIF('Income Statement Source'!$C:$C,'1. Income Statement'!$AR60,'Income Statement Source'!L:L)/1000 -> 1.39673 | K60: =SUMIF('Income Statement Source'!$C:$C,'1. Income Statement'!$AR60,'Income Statement Source'!M:M)/1000 -> 1.37497 | L60: =SUMIF('Income Statement Source'!$C:$C,'1. Income Statement'!$AR60,'Income Statement Source'!N:N)/1000 -> 1.3833 | M60: =SUMIF('Income Statement Source'!$C:$C,'1. Income Statement'!$AR60,'Income Statement Source'!O:O)/1000 -> 1.41305 | N60: =SUMIF('Income Statement Source'!$C:$C,'1. Income Statement'!$AR60,'Income Statement Source'!P:P)/1000 -> 1.39861 | O60: =SUMIF('Income Statement Source'!$C:$C,'1. Income Statement'!$AR60,'Income Statement Source'!Q:Q)/1000 -> 0 | P60: =SUMIF('Income Statement Source'!$C:$C,'1. Income Statement'!$AR60,'Income Statement Source'!R:R)/1000 -> 0 | Q60: =SUM(E60:P60) -> 21.1142 | R60: =SUMIF('Income Statement Source'!$C:$C,'1. Income Statement'!$AR60,'Income Statement Source'!T:T)/1000 -> 8.23337 | S60: =SUMIF('Income Statement Source'!$C:$C,'1. Income Statement'!$AR60,'Income Statement Source'!U:U)/1000 -> 1.40981 | T60: =SUMIF('Income Statement Source'!$C:$C,'1. Income Statement'!$AR60,'Income Statement Source'!V:V)/1000 -> 1.4308 | U60: =SUMIF('Income Statement Source'!$C:$C,'1. Income Statement'!$AR60,'Income Statement Source'!W:W)/1000 -> 1.3723 | V60: =SUMIF('Income Statement Source'!$C:$C,'1. Income Statement'!$AR60,'Income Statement Source'!X:X)/1000 -> 1.40105 | W60: =SUMIF('Income Statement Source'!$C:$C,'1. Income Statement'!$AR60,'Income Statement Source'!Y:Y)/1000 -> 1.42222 | X60: =SUMIF('Income Statement Source'!$C:$C,'1. Income Statement'!$AR60,'Income Statement Source'!Z:Z)/1000 -> 1.42405 | Y60: =SUMIF('Income Statement Source'!$C:$C,'1. Income Statement'!$AR60,'Income Statement Source'!AA:AA)/1000 -> 1.40566 | Z60: =SUMIF('Income Statement Source'!$C:$C,'1. Income Statement'!$AR60,'Income Statement Source'!AB:AB)/1000 -> 1.4138 | AA60: =SUMIF('Income Statement Source'!$C:$C,'1. Income Statement'!$AR60,'Income Statement Source'!AC:AC)/1000 -> 1.39536 | AB60: =SUMIF('Income Statement Source'!$C:$C,'1. Income Statement'!$AR60,'Income Statement Source'!AD:AD)/1000 -> 0 | AC60: =SUMIF('Income Statement Source'!$C:$C,'1. Income Statement'!$AR60,'Income Statement Source'!AE:AE)/1000 -> 0 | AD60: =SUM(R60:AC60) -> 20.90842 | AE60: =SUMIF('Income Statement Source'!$C:$C,'1. Income Statement'!$AR60,'Income Statement Source'!AG:AG)/1000 -> 22.4686 | AF60: =SUMIF('Income Statement Source'!$C:$C,'1. Income Statement'!$AR60,'Income Statement Source'!AH:AH)/1000 -> 0 | AG60: =SUMIF('Income Statement Source'!$C:$C,'1. Income Statement'!$AR60,'Income Statement Source'!AI:AI)/1000 -> 0 | AH60: =SUMIF('Income Statement Source'!$C:$C,'1. Income Statement'!$AR60,'Income Statement Source'!AJ:AJ)/1000 -> 0 | AI60: =SUMIF('Income Statement Source'!$C:$C,'1. Income Statement'!$AR60,'Income Statement Source'!AK:AK)/1000 -> 0 | AJ60: =SUMIF('Income Statement Source'!$C:$C,'1. Income Statement'!$AR60,'Income Statement Source'!AL:AL)/1000 -> 0 | AK60: =SUMIF('Income Statement Source'!$C:$C,'1. Income Statement'!$AR60,'Income Statement Source'!AM:AM)/1000 -> 0 | AL60: =SUMIF('Income Statement Source'!$C:$C,'1. Income Statement'!$AR60,'Income Statement Source'!AN:AN)/1000 -> 0 | AM60: =SUMIF('Income Statement Source'!$C:$C,'1. Income Statement'!$AR60,'Income Statement Source'!AO:AO)/1000 -> 0 | AN60: =SUMIF('Income Statement Source'!$C:$C,'1. Income Statement'!$AR60,'Income Statement Source'!AP:AP)/1000 -> 0 | AO60: =SUM(AE60:AN60) -> 22.4686 | AP60: =SUM(AO60,AB60:AC60) -> 22.4686 | AR60: General Liability Insurance
B61: =+AR61 -> Professional Liability Insurance | E61: =SUMIF('Income Statement Source'!$C:$C,'1. Income Statement'!$AR61,'Income Statement Source'!G:G)/1000 -> 0.95218 | F61: =SUMIF('Income Statement Source'!$C:$C,'1. Income Statement'!$AR61,'Income Statement Source'!H:H)/1000 -> 0.94724 | G61: =SUMIF('Income Statement Source'!$C:$C,'1. Income Statement'!$AR61,'Income Statement Source'!I:I)/1000 -> 0.94527 | H61: =SUMIF('Income Statement Source'!$C:$C,'1. Income Statement'!$AR61,'Income Statement Source'!J:J)/1000 -> 0.94324 | I61: =SUMIF('Income Statement Source'!$C:$C,'1. Income Statement'!$AR61,'Income Statement Source'!K:K)/1000 -> 0.95073 | J61: =SUMIF('Income Statement Source'!$C:$C,'1. Income Statement'!$AR61,'Income Statement Source'!L:L)/1000 -> 0.94257 | K61: =SUMIF('Income Statement Source'!$C:$C,'1. Income Statement'!$AR61,'Income Statement Source'!M:M)/1000 -> 0.9486 | L61: =SUMIF('Income Statement Source'!$C:$C,'1. Income Statement'!$AR61,'Income Statement Source'!N:N)/1000 -> 0.95927 | M61: =SUMIF('Income Statement Source'!$C:$C,'1. Income Statement'!$AR61,'Income Statement Source'!O:O)/1000 -> 0.95404 | N61: =SUMIF('Income Statement Source'!$C:$C,'1. Income Statement'!$AR61,'Income Statement Source'!P:P)/1000 -> 0.94229 | O61: =SUMIF('Income Statement Source'!$C:$C,'1. Income Statement'!$AR61,'Income Statement Source'!Q:Q)/1000 -> 0.95093 | P61: =SUMIF('Income Statement Source'!$C:$C,'1. Income Statement'!$AR61,'Income Statement Source'!R:R)/1000 -> 0.95043 | Q61: =SUM(E61:P61) -> 11.38679 | R61: =SUMIF('Income Statement Source'!$C:$C,'1. Income Statement'!$AR61,'Income Statement Source'!T:T)/1000 -> 0.95944 | S61: =SUMIF('Income Statement Source'!$C:$C,'1. Income Statement'!$AR61,'Income Statement Source'!U:U)/1000 -> 0.95577 | T61: =SUMIF('Income Statement Source'!$C:$C,'1. Income Statement'!$AR61,'Income Statement Source'!V:V)/1000 -> 0.94159 | U61: =SUMIF('Income Statement Source'!$C:$C,'1. Income Statement'!$AR61,'Income Statement Source'!W:W)/1000 -> 0.95743 | V61: =SUMIF('Income Statement Source'!$C:$C,'1. Income Statement'!$AR61,'Income Statement Source'!X:X)/1000 -> 0.94841 | W61: =SUMIF('Income Statement Source'!$C:$C,'1. Income Statement'!$AR61,'Income Statement Source'!Y:Y)/1000 -> 0.9541 | X61: =SUMIF('Income Statement Source'!$C:$C,'1. Income Statement'!$AR61,'Income Statement Source'!Z:Z)/1000 -> 0.95586 | Y61: =SUMIF('Income Statement Source'!$C:$C,'1. Income Statement'!$AR61,'Income Statement Source'!AA:AA)/1000 -> 0.95753 | Z61: =SUMIF('Income Statement Source'!$C:$C,'1. Income Statement'!$AR61,'Income Statement Source'!AB:AB)/1000 -> 0.94436 | AA61: =SUMIF('Income Statement Source'!$C:$C,'1. Income Statement'!$AR61,'Income Statement Source'!AC:AC)/1000 -> 0.95811 | AB61: =SUMIF('Income Statement Source'!$C:$C,'1. Income Statement'!$AR61,'Income Statement Source'!AD:AD)/1000 -> 0.95557 | AC61: =SUMIF('Income Statement Source'!$C:$C,'1. Income Statement'!$AR61,'Income Statement Source'!AE:AE)/1000 -> 0.95276 | AD61: =SUM(R61:AC61) -> 11.44093 | AE61: =SUMIF('Income Statement Source'!$C:$C,'1. Income Statement'!$AR61,'Income Statement Source'!AG:AG)/1000 -> 0.95838 | AF61: =SUMIF('Income Statement Source'!$C:$C,'1. Income Statement'!$AR61,'Income Statement Source'!AH:AH)/1000 -> 0.94361 | AG61: =SUMIF('Income Statement Source'!$C:$C,'1. Income Statement'!$AR61,'Income Statement Source'!AI:AI)/1000 -> 0.94551 | AH61: =SUMIF('Income Statement Source'!$C:$C,'1. Income Statement'!$AR61,'Income Statement Source'!AJ:AJ)/1000 -> 0.9503 | AI61: =SUMIF('Income Statement Source'!$C:$C,'1. Income Statement'!$AR61,'Income Statement Source'!AK:AK)/1000 -> 0.94086 | AJ61: =SUMIF('Income Statement Source'!$C:$C,'1. Income Statement'!$AR61,'Income Statement Source'!AL:AL)/1000 -> 0.94656 | AK61: =SUMIF('Income Statement Source'!$C:$C,'1. Income Statement'!$AR61,'Income Statement Source'!AM:AM)/1000 -> 0.95916 | AL61: =SUMIF('Income Statement Source'!$C:$C,'1. Income Statement'!$AR61,'Income Statement Source'!AN:AN)/1000 -> 0.95681 | AM61: =SUMIF('Income Statement Source'!$C:$C,'1. Income Statement'!$AR61,'Income Statement Source'!AO:AO)/1000 -> 0.94325 | AN61: =SUMIF('Income Statement Source'!$C:$C,'1. Income Statement'!$AR61,'Income Statement Source'!AP:AP)/1000 -> 0.9527 | AO61: =SUM(AE61:AN61) -> 9.49714 | AP61: =SUM(AO61,AB61:AC61) -> 11.40547 | AR61: Professional Liability Insurance
B62: =+B58 -> Insurance | E62: =SUM(E59:E61) -> 15.29089 | F62: =SUM(F59:F61) -> 8.28372 | G62: =SUM(G59:G61) -> 7.90167 | H62: =SUM(H59:H61) -> 7.98185 | I62: =SUM(I59:I61) -> 8.1396 | J62: =SUM(J59:J61) -> 8.05197 | K62: =SUM(K59:K61) -> 8.15407 | L62: =SUM(L59:L61) -> 8.1346 | ... AP62: =SUM(AP59:AP61) -> 103.6536
E63: =IFERROR(E62/E$19,0) -> 0.080488527 | F63: =IFERROR(F62/F$19,0) -> 0.036447243 | G63: =IFERROR(G62/G$19,0) -> 0.025686837 | H63: =IFERROR(H62/H$19,0) -> 0.030860392 | I63: =IFERROR(I62/I$19,0) -> 0.029949553 | J63: =IFERROR(J62/J$19,0) -> 0.021865197 | K63: =IFERROR(K62/K$19,0) -> 0.026955907 | L63: =IFERROR(L62/L$19,0) -> 0.029343208 | ... AP63: =IFERROR(AP62/AP$19,0) -> 0.02443928
B64: Facilities
B65: =+AR65 -> Rent - Office | E65: =SUMIF('Income Statement Source'!$C:$C,'1. Income Statement'!$AR65,'Income Statement Source'!G:G)/1000 -> 3.2 | F65: =SUMIF('Income Statement Source'!$C:$C,'1. Income Statement'!$AR65,'Income Statement Source'!H:H)/1000 -> 3.2 | G65: =SUMIF('Income Statement Source'!$C:$C,'1. Income Statement'!$AR65,'Income Statement Source'!I:I)/1000 -> 3.2 | H65: =SUMIF('Income Statement Source'!$C:$C,'1. Income Statement'!$AR65,'Income Statement Source'!J:J)/1000 -> 3.2 | I65: =SUMIF('Income Statement Source'!$C:$C,'1. Income Statement'!$AR65,'Income Statement Source'!K:K)/1000 -> 3.2 | J65: =SUMIF('Income Statement Source'!$C:$C,'1. Income Statement'!$AR65,'Income Statement Source'!L:L)/1000 -> 3.2 | K65: =SUMIF('Income Statement Source'!$C:$C,'1. Income Statement'!$AR65,'Income Statement Source'!M:M)/1000 -> 3.2 | L65: =SUMIF('Income Statement Source'!$C:$C,'1. Income Statement'!$AR65,'Income Statement Source'!N:N)/1000 -> 3.2 | M65: =SUMIF('Income Statement Source'!$C:$C,'1. Income Statement'!$AR65,'Income Statement Source'!O:O)/1000 -> 3.2 | N65: =SUMIF('Income Statement Source'!$C:$C,'1. Income Statement'!$AR65,'Income Statement Source'!P:P)/1000 -> 3.2 | O65: =SUMIF('Income Statement Source'!$C:$C,'1. Income Statement'!$AR65,'Income Statement Source'!Q:Q)/1000 -> 3.2 | P65: =SUMIF('Income Statement Source'!$C:$C,'1. Income Statement'!$AR65,'Income Statement Source'!R:R)/1000 -> 3.2 | Q65: =SUM(E65:P65) -> 38.4 | R65: =SUMIF('Income Statement Source'!$C:$C,'1. Income Statement'!$AR65,'Income Statement Source'!T:T)/1000 -> 3.2 | S65: =SUMIF('Income Statement Source'!$C:$C,'1. Income Statement'!$AR65,'Income Statement Source'!U:U)/1000 -> 3.2 | T65: =SUMIF('Income Statement Source'!$C:$C,'1. Income Statement'!$AR65,'Income Statement Source'!V:V)/1000 -> 3.2 | U65: =SUMIF('Income Statement Source'!$C:$C,'1. Income Statement'!$AR65,'Income Statement Source'!W:W)/1000 -> 3.2 | V65: =SUMIF('Income Statement Source'!$C:$C,'1. Income Statement'!$AR65,'Income Statement Source'!X:X)/1000 -> 3.2 | W65: =SUMIF('Income Statement Source'!$C:$C,'1. Income Statement'!$AR65,'Income Statement Source'!Y:Y)/1000 -> 3.2 | X65: =SUMIF('Income Statement Source'!$C:$C,'1. Income Statement'!$AR65,'Income Statement Source'!Z:Z)/1000 -> 3.2 | Y65: =SUMIF('Income Statement Source'!$C:$C,'1. Income Statement'!$AR65,'Income Statement Source'!AA:AA)/1000 -> 3.2 | Z65: =SUMIF('Income Statement Source'!$C:$C,'1. Income Statement'!$AR65,'Income Statement Source'!AB:AB)/1000 -> 3.2 | AA65: =SUMIF('Income Statement Source'!$C:$C,'1. Income Statement'!$AR65,'Income Statement Source'!AC:AC)/1000 -> 3.2 | AB65: =SUMIF('Income Statement Source'!$C:$C,'1. Income Statement'!$AR65,'Income Statement Source'!AD:AD)/1000 -> 3.2 | AC65: =SUMIF('Income Statement Source'!$C:$C,'1. Income Statement'!$AR65,'Income Statement Source'!AE:AE)/1000 -> 3.2 | AD65: =SUM(R65:AC65) -> 38.4 | AE65: =SUMIF('Income Statement Source'!$C:$C,'1. Income Statement'!$AR65,'Income Statement Source'!AG:AG)/1000 -> 3.2 | AF65: =SUMIF('Income Statement Source'!$C:$C,'1. Income Statement'!$AR65,'Income Statement Source'!AH:AH)/1000 -> 3.2 | AG65: =SUMIF('Income Statement Source'!$C:$C,'1. Income Statement'!$AR65,'Income Statement Source'!AI:AI)/1000 -> 3.2 | AH65: =SUMIF('Income Statement Source'!$C:$C,'1. Income Statement'!$AR65,'Income Statement Source'!AJ:AJ)/1000 -> 3.2 | AI65: =SUMIF('Income Statement Source'!$C:$C,'1. Income Statement'!$AR65,'Income Statement Source'!AK:AK)/1000 -> 3.2 | AJ65: =SUMIF('Income Statement Source'!$C:$C,'1. Income Statement'!$AR65,'Income Statement Source'!AL:AL)/1000 -> 3.2 | AK65: =SUMIF('Income Statement Source'!$C:$C,'1. Income Statement'!$AR65,'Income Statement Source'!AM:AM)/1000 -> 3.2 | AL65: =SUMIF('Income Statement Source'!$C:$C,'1. Income Statement'!$AR65,'Income Statement Source'!AN:AN)/1000 -> 3.2 | AM65: =SUMIF('Income Statement Source'!$C:$C,'1. Income Statement'!$AR65,'Income Statement Source'!AO:AO)/1000 -> 3.2 | AN65: =SUMIF('Income Statement Source'!$C:$C,'1. Income Statement'!$AR65,'Income Statement Source'!AP:AP)/1000 -> 3.2 | AO65: =SUM(AE65:AN65) -> 32 | AP65: =SUM(AO65,AB65:AC65) -> 38.4 | AR65: Rent - Office
B66: =+AR66 -> Rent - Warehouse | E66: =SUMIF('Income Statement Source'!$C:$C,'1. Income Statement'!$AR66,'Income Statement Source'!G:G)/1000 -> 2.8 | F66: =SUMIF('Income Statement Source'!$C:$C,'1. Income Statement'!$AR66,'Income Statement Source'!H:H)/1000 -> 2.8 | G66: =SUMIF('Income Statement Source'!$C:$C,'1. Income Statement'!$AR66,'Income Statement Source'!I:I)/1000 -> 2.8 | H66: =SUMIF('Income Statement Source'!$C:$C,'1. Income Statement'!$AR66,'Income Statement Source'!J:J)/1000 -> 2.8 | I66: =SUMIF('Income Statement Source'!$C:$C,'1. Income Statement'!$AR66,'Income Statement Source'!K:K)/1000 -> 2.8 | J66: =SUMIF('Income Statement Source'!$C:$C,'1. Income Statement'!$AR66,'Income Statement Source'!L:L)/1000 -> 2.8 | K66: =SUMIF('Income Statement Source'!$C:$C,'1. Income Statement'!$AR66,'Income Statement Source'!M:M)/1000 -> 2.8 | L66: =SUMIF('Income Statement Source'!$C:$C,'1. Income Statement'!$AR66,'Income Statement Source'!N:N)/1000 -> 2.8 | M66: =SUMIF('Income Statement Source'!$C:$C,'1. Income Statement'!$AR66,'Income Statement Source'!O:O)/1000 -> 2.8 | N66: =SUMIF('Income Statement Source'!$C:$C,'1. Income Statement'!$AR66,'Income Statement Source'!P:P)/1000 -> 2.8 | O66: =SUMIF('Income Statement Source'!$C:$C,'1. Income Statement'!$AR66,'Income Statement Source'!Q:Q)/1000 -> 2.8 | P66: =SUMIF('Income Statement Source'!$C:$C,'1. Income Statement'!$AR66,'Income Statement Source'!R:R)/1000 -> 2.8 | Q66: =SUM(E66:P66) -> 33.6 | R66: =SUMIF('Income Statement Source'!$C:$C,'1. Income Statement'!$AR66,'Income Statement Source'!T:T)/1000 -> 2.8 | S66: =SUMIF('Income Statement Source'!$C:$C,'1. Income Statement'!$AR66,'Income Statement Source'!U:U)/1000 -> 2.8 | T66: =SUMIF('Income Statement Source'!$C:$C,'1. Income Statement'!$AR66,'Income Statement Source'!V:V)/1000 -> 2.8 | U66: =SUMIF('Income Statement Source'!$C:$C,'1. Income Statement'!$AR66,'Income Statement Source'!W:W)/1000 -> 2.8 | V66: =SUMIF('Income Statement Source'!$C:$C,'1. Income Statement'!$AR66,'Income Statement Source'!X:X)/1000 -> 2.8 | W66: =SUMIF('Income Statement Source'!$C:$C,'1. Income Statement'!$AR66,'Income Statement Source'!Y:Y)/1000 -> 2.8 | X66: =SUMIF('Income Statement Source'!$C:$C,'1. Income Statement'!$AR66,'Income Statement Source'!Z:Z)/1000 -> 2.8 | Y66: =SUMIF('Income Statement Source'!$C:$C,'1. Income Statement'!$AR66,'Income Statement Source'!AA:AA)/1000 -> 2.8 | Z66: =SUMIF('Income Statement Source'!$C:$C,'1. Income Statement'!$AR66,'Income Statement Source'!AB:AB)/1000 -> 2.8 | AA66: =SUMIF('Income Statement Source'!$C:$C,'1. Income Statement'!$AR66,'Income Statement Source'!AC:AC)/1000 -> 2.8 | AB66: =SUMIF('Income Statement Source'!$C:$C,'1. Income Statement'!$AR66,'Income Statement Source'!AD:AD)/1000 -> 2.8 | AC66: =SUMIF('Income Statement Source'!$C:$C,'1. Income Statement'!$AR66,'Income Statement Source'!AE:AE)/1000 -> 2.8 | AD66: =SUM(R66:AC66) -> 33.6 | AE66: =SUMIF('Income Statement Source'!$C:$C,'1. Income Statement'!$AR66,'Income Statement Source'!AG:AG)/1000 -> 2.8 | AF66: =SUMIF('Income Statement Source'!$C:$C,'1. Income Statement'!$AR66,'Income Statement Source'!AH:AH)/1000 -> 2.8 | AG66: =SUMIF('Income Statement Source'!$C:$C,'1. Income Statement'!$AR66,'Income Statement Source'!AI:AI)/1000 -> 2.8 | AH66: =SUMIF('Income Statement Source'!$C:$C,'1. Income Statement'!$AR66,'Income Statement Source'!AJ:AJ)/1000 -> 2.8 | AI66: =SUMIF('Income Statement Source'!$C:$C,'1. Income Statement'!$AR66,'Income Statement Source'!AK:AK)/1000 -> 2.8 | AJ66: =SUMIF('Income Statement Source'!$C:$C,'1. Income Statement'!$AR66,'Income Statement Source'!AL:AL)/1000 -> 2.8 | AK66: =SUMIF('Income Statement Source'!$C:$C,'1. Income Statement'!$AR66,'Income Statement Source'!AM:AM)/1000 -> 2.8 | AL66: =SUMIF('Income Statement Source'!$C:$C,'1. Income Statement'!$AR66,'Income Statement Source'!AN:AN)/1000 -> 2.8 | AM66: =SUMIF('Income Statement Source'!$C:$C,'1. Income Statement'!$AR66,'Income Statement Source'!AO:AO)/1000 -> 2.8 | AN66: =SUMIF('Income Statement Source'!$C:$C,'1. Income Statement'!$AR66,'Income Statement Source'!AP:AP)/1000 -> 2.8 | AO66: =SUM(AE66:AN66) -> 28 | AP66: =SUM(AO66,AB66:AC66) -> 33.6 | AR66: Rent - Warehouse
B67: =+AR67 -> Utilities | E67: =SUMIF('Income Statement Source'!$C:$C,'1. Income Statement'!$AR67,'Income Statement Source'!G:G)/1000 -> 0.87149 | F67: =SUMIF('Income Statement Source'!$C:$C,'1. Income Statement'!$AR67,'Income Statement Source'!H:H)/1000 -> 0.80398 | G67: =SUMIF('Income Statement Source'!$C:$C,'1. Income Statement'!$AR67,'Income Statement Source'!I:I)/1000 -> 0.89926 | H67: =SUMIF('Income Statement Source'!$C:$C,'1. Income Statement'!$AR67,'Income Statement Source'!J:J)/1000 -> 0.88228 | I67: =SUMIF('Income Statement Source'!$C:$C,'1. Income Statement'!$AR67,'Income Statement Source'!K:K)/1000 -> 0.81494 | J67: =SUMIF('Income Statement Source'!$C:$C,'1. Income Statement'!$AR67,'Income Statement Source'!L:L)/1000 -> 0.84106 | K67: =SUMIF('Income Statement Source'!$C:$C,'1. Income Statement'!$AR67,'Income Statement Source'!M:M)/1000 -> 0.87225 | L67: =SUMIF('Income Statement Source'!$C:$C,'1. Income Statement'!$AR67,'Income Statement Source'!N:N)/1000 -> 0.87017 | M67: =SUMIF('Income Statement Source'!$C:$C,'1. Income Statement'!$AR67,'Income Statement Source'!O:O)/1000 -> 0.87802 | N67: =SUMIF('Income Statement Source'!$C:$C,'1. Income Statement'!$AR67,'Income Statement Source'!P:P)/1000 -> 0.78656 | O67: =SUMIF('Income Statement Source'!$C:$C,'1. Income Statement'!$AR67,'Income Statement Source'!Q:Q)/1000 -> 0.90078 | P67: =SUMIF('Income Statement Source'!$C:$C,'1. Income Statement'!$AR67,'Income Statement Source'!R:R)/1000 -> 0.88362 | Q67: =SUM(E67:P67) -> 10.30441 | R67: =SUMIF('Income Statement Source'!$C:$C,'1. Income Statement'!$AR67,'Income Statement Source'!T:T)/1000 -> 0.90994 | S67: =SUMIF('Income Statement Source'!$C:$C,'1. Income Statement'!$AR67,'Income Statement Source'!U:U)/1000 -> 0.79657 | T67: =SUMIF('Income Statement Source'!$C:$C,'1. Income Statement'!$AR67,'Income Statement Source'!V:V)/1000 -> 0.82753 | U67: =SUMIF('Income Statement Source'!$C:$C,'1. Income Statement'!$AR67,'Income Statement Source'!W:W)/1000 -> 0.86438 | V67: =SUMIF('Income Statement Source'!$C:$C,'1. Income Statement'!$AR67,'Income Statement Source'!X:X)/1000 -> 0.87613 | W67: =SUMIF('Income Statement Source'!$C:$C,'1. Income Statement'!$AR67,'Income Statement Source'!Y:Y)/1000 -> 0.86978 | X67: =SUMIF('Income Statement Source'!$C:$C,'1. Income Statement'!$AR67,'Income Statement Source'!Z:Z)/1000 -> 0.80796 | Y67: =SUMIF('Income Statement Source'!$C:$C,'1. Income Statement'!$AR67,'Income Statement Source'!AA:AA)/1000 -> 0.81738 | Z67: =SUMIF('Income Statement Source'!$C:$C,'1. Income Statement'!$AR67,'Income Statement Source'!AB:AB)/1000 -> 0.90972 | AA67: =SUMIF('Income Statement Source'!$C:$C,'1. Income Statement'!$AR67,'Income Statement Source'!AC:AC)/1000 -> 0.91136 | AB67: =SUMIF('Income Statement Source'!$C:$C,'1. Income Statement'!$AR67,'Income Statement Source'!AD:AD)/1000 -> 0.8666 | AC67: =SUMIF('Income Statement Source'!$C:$C,'1. Income Statement'!$AR67,'Income Statement Source'!AE:AE)/1000 -> 0.87632 | AD67: =SUM(R67:AC67) -> 10.33367 | AE67: =SUMIF('Income Statement Source'!$C:$C,'1. Income Statement'!$AR67,'Income Statement Source'!AG:AG)/1000 -> 0.87182 | AF67: =SUMIF('Income Statement Source'!$C:$C,'1. Income Statement'!$AR67,'Income Statement Source'!AH:AH)/1000 -> 0.82803 | AG67: =SUMIF('Income Statement Source'!$C:$C,'1. Income Statement'!$AR67,'Income Statement Source'!AI:AI)/1000 -> 0.80057 | AH67: =SUMIF('Income Statement Source'!$C:$C,'1. Income Statement'!$AR67,'Income Statement Source'!AJ:AJ)/1000 -> 0.86682 | AI67: =SUMIF('Income Statement Source'!$C:$C,'1. Income Statement'!$AR67,'Income Statement Source'!AK:AK)/1000 -> 0.84344 | AJ67: =SUMIF('Income Statement Source'!$C:$C,'1. Income Statement'!$AR67,'Income Statement Source'!AL:AL)/1000 -> 0.89382 | AK67: =SUMIF('Income Statement Source'!$C:$C,'1. Income Statement'!$AR67,'Income Statement Source'!AM:AM)/1000 -> 0.78784 | AL67: =SUMIF('Income Statement Source'!$C:$C,'1. Income Statement'!$AR67,'Income Statement Source'!AN:AN)/1000 -> 0.79258 | AM67: =SUMIF('Income Statement Source'!$C:$C,'1. Income Statement'!$AR67,'Income Statement Source'!AO:AO)/1000 -> 0.79245 | AN67: =SUMIF('Income Statement Source'!$C:$C,'1. Income Statement'!$AR67,'Income Statement Source'!AP:AP)/1000 -> 0.8315 | AO67: =SUM(AE67:AN67) -> 8.30887 | AP67: =SUM(AO67,AB67:AC67) -> 10.05179 | AR67: Utilities
B68: =+AR68 -> Telephone & Internet | E68: =SUMIF('Income Statement Source'!$C:$C,'1. Income Statement'!$AR68,'Income Statement Source'!G:G)/1000 -> 0.67431 | F68: =SUMIF('Income Statement Source'!$C:$C,'1. Income Statement'!$AR68,'Income Statement Source'!H:H)/1000 -> 0.66878 | G68: =SUMIF('Income Statement Source'!$C:$C,'1. Income Statement'!$AR68,'Income Statement Source'!I:I)/1000 -> 0.70048 | H68: =SUMIF('Income Statement Source'!$C:$C,'1. Income Statement'!$AR68,'Income Statement Source'!J:J)/1000 -> 0.68497 | I68: =SUMIF('Income Statement Source'!$C:$C,'1. Income Statement'!$AR68,'Income Statement Source'!K:K)/1000 -> 0.67499 | J68: =SUMIF('Income Statement Source'!$C:$C,'1. Income Statement'!$AR68,'Income Statement Source'!L:L)/1000 -> 0.68781 | K68: =SUMIF('Income Statement Source'!$C:$C,'1. Income Statement'!$AR68,'Income Statement Source'!M:M)/1000 -> 0.68167 | L68: =SUMIF('Income Statement Source'!$C:$C,'1. Income Statement'!$AR68,'Income Statement Source'!N:N)/1000 -> 0.68055 | M68: =SUMIF('Income Statement Source'!$C:$C,'1. Income Statement'!$AR68,'Income Statement Source'!O:O)/1000 -> 0.67645 | N68: =SUMIF('Income Statement Source'!$C:$C,'1. Income Statement'!$AR68,'Income Statement Source'!P:P)/1000 -> 0.67184 | O68: =SUMIF('Income Statement Source'!$C:$C,'1. Income Statement'!$AR68,'Income Statement Source'!Q:Q)/1000 -> 0.65271 | P68: =SUMIF('Income Statement Source'!$C:$C,'1. Income Statement'!$AR68,'Income Statement Source'!R:R)/1000 -> 0.69753 | Q68: =SUM(E68:P68) -> 8.15209 | R68: =SUMIF('Income Statement Source'!$C:$C,'1. Income Statement'!$AR68,'Income Statement Source'!T:T)/1000 -> 0.66247 | S68: =SUMIF('Income Statement Source'!$C:$C,'1. Income Statement'!$AR68,'Income Statement Source'!U:U)/1000 -> 0.67813 | T68: =SUMIF('Income Statement Source'!$C:$C,'1. Income Statement'!$AR68,'Income Statement Source'!V:V)/1000 -> 0.64825 | U68: =SUMIF('Income Statement Source'!$C:$C,'1. Income Statement'!$AR68,'Income Statement Source'!W:W)/1000 -> 0.70486 | V68: =SUMIF('Income Statement Source'!$C:$C,'1. Income Statement'!$AR68,'Income Statement Source'!X:X)/1000 -> 0.67487 | W68: =SUMIF('Income Statement Source'!$C:$C,'1. Income Statement'!$AR68,'Income Statement Source'!Y:Y)/1000 -> 0.65745 | X68: =SUMIF('Income Statement Source'!$C:$C,'1. Income Statement'!$AR68,'Income Statement Source'!Z:Z)/1000 -> 0.70318 | Y68: =SUMIF('Income Statement Source'!$C:$C,'1. Income Statement'!$AR68,'Income Statement Source'!AA:AA)/1000 -> 0.68165 | Z68: =SUMIF('Income Statement Source'!$C:$C,'1. Income Statement'!$AR68,'Income Statement Source'!AB:AB)/1000 -> 0.65045 | AA68: =SUMIF('Income Statement Source'!$C:$C,'1. Income Statement'!$AR68,'Income Statement Source'!AC:AC)/1000 -> 0.67664 | AB68: =SUMIF('Income Statement Source'!$C:$C,'1. Income Statement'!$AR68,'Income Statement Source'!AD:AD)/1000 -> 0.69273 | AC68: =SUMIF('Income Statement Source'!$C:$C,'1. Income Statement'!$AR68,'Income Statement Source'!AE:AE)/1000 -> 0.65095 | AD68: =SUM(R68:AC68) -> 8.08163 | AE68: =SUMIF('Income Statement Source'!$C:$C,'1. Income Statement'!$AR68,'Income Statement Source'!AG:AG)/1000 -> 0.66489 | AF68: =SUMIF('Income Statement Source'!$C:$C,'1. Income Statement'!$AR68,'Income Statement Source'!AH:AH)/1000 -> 0.68981 | AG68: =SUMIF('Income Statement Source'!$C:$C,'1. Income Statement'!$AR68,'Income Statement Source'!AI:AI)/1000 -> 0.663 | AH68: =SUMIF('Income Statement Source'!$C:$C,'1. Income Statement'!$AR68,'Income Statement Source'!AJ:AJ)/1000 -> 0.68425 | AI68: =SUMIF('Income Statement Source'!$C:$C,'1. Income Statement'!$AR68,'Income Statement Source'!AK:AK)/1000 -> 0.66911 | AJ68: =SUMIF('Income Statement Source'!$C:$C,'1. Income Statement'!$AR68,'Income Statement Source'!AL:AL)/1000 -> 0.68477 | AK68: =SUMIF('Income Statement Source'!$C:$C,'1. Income Statement'!$AR68,'Income Statement Source'!AM:AM)/1000 -> 0.68304 | AL68: =SUMIF('Income Statement Source'!$C:$C,'1. Income Statement'!$AR68,'Income Statement Source'!AN:AN)/1000 -> 0.65829 | AM68: =SUMIF('Income Statement Source'!$C:$C,'1. Income Statement'!$AR68,'Income Statement Source'!AO:AO)/1000 -> 0.71003 | AN68: =SUMIF('Income Statement Source'!$C:$C,'1. Income Statement'!$AR68,'Income Statement Source'!AP:AP)/1000 -> 0.70608 | AO68: =SUM(AE68:AN68) -> 6.81327 | AP68: =SUM(AO68,AB68:AC68) -> 8.15695 | AR68: Telephone & Internet
B69: =+AR69 -> Office Supplies | E69: =SUMIF('Income Statement Source'!$C:$C,'1. Income Statement'!$AR69,'Income Statement Source'!G:G)/1000 -> 0.45143 | F69: =SUMIF('Income Statement Source'!$C:$C,'1. Income Statement'!$AR69,'Income Statement Source'!H:H)/1000 -> 0.46719 | G69: =SUMIF('Income Statement Source'!$C:$C,'1. Income Statement'!$AR69,'Income Statement Source'!I:I)/1000 -> 0.40597 | H69: =SUMIF('Income Statement Source'!$C:$C,'1. Income Statement'!$AR69,'Income Statement Source'!J:J)/1000 -> 0.40749 | I69: =SUMIF('Income Statement Source'!$C:$C,'1. Income Statement'!$AR69,'Income Statement Source'!K:K)/1000 -> 0.4195 | J69: =SUMIF('Income Statement Source'!$C:$C,'1. Income Statement'!$AR69,'Income Statement Source'!L:L)/1000 -> 0.37892 | K69: =SUMIF('Income Statement Source'!$C:$C,'1. Income Statement'!$AR69,'Income Statement Source'!M:M)/1000 -> 0.40161 | L69: =SUMIF('Income Statement Source'!$C:$C,'1. Income Statement'!$AR69,'Income Statement Source'!N:N)/1000 -> 0.39388 | M69: =SUMIF('Income Statement Source'!$C:$C,'1. Income Statement'!$AR69,'Income Statement Source'!O:O)/1000 -> 0.45205 | N69: =SUMIF('Income Statement Source'!$C:$C,'1. Income Statement'!$AR69,'Income Statement Source'!P:P)/1000 -> 0.46913 | O69: =SUMIF('Income Statement Source'!$C:$C,'1. Income Statement'!$AR69,'Income Statement Source'!Q:Q)/1000 -> 0.46352 | P69: =SUMIF('Income Statement Source'!$C:$C,'1. Income Statement'!$AR69,'Income Statement Source'!R:R)/1000 -> 0.41954 | Q69: =SUM(E69:P69) -> 5.13023 | R69: =SUMIF('Income Statement Source'!$C:$C,'1. Income Statement'!$AR69,'Income Statement Source'!T:T)/1000 -> 0.37002 | S69: =SUMIF('Income Statement Source'!$C:$C,'1. Income Statement'!$AR69,'Income Statement Source'!U:U)/1000 -> 0.44004 | T69: =SUMIF('Income Statement Source'!$C:$C,'1. Income Statement'!$AR69,'Income Statement Source'!V:V)/1000 -> 0.39277 | U69: =SUMIF('Income Statement Source'!$C:$C,'1. Income Statement'!$AR69,'Income Statement Source'!W:W)/1000 -> 0.44303 | V69: =SUMIF('Income Statement Source'!$C:$C,'1. Income Statement'!$AR69,'Income Statement Source'!X:X)/1000 -> 0.40422 | W69: =SUMIF('Income Statement Source'!$C:$C,'1. Income Statement'!$AR69,'Income Statement Source'!Y:Y)/1000 -> 0.46048 | X69: =SUMIF('Income Statement Source'!$C:$C,'1. Income Statement'!$AR69,'Income Statement Source'!Z:Z)/1000 -> 0.41103 | Y69: =SUMIF('Income Statement Source'!$C:$C,'1. Income Statement'!$AR69,'Income Statement Source'!AA:AA)/1000 -> 0.43433 | Z69: =SUMIF('Income Statement Source'!$C:$C,'1. Income Statement'!$AR69,'Income Statement Source'!AB:AB)/1000 -> 0.42847 | AA69: =SUMIF('Income Statement Source'!$C:$C,'1. Income Statement'!$AR69,'Income Statement Source'!AC:AC)/1000 -> 0.44161 | AB69: =SUMIF('Income Statement Source'!$C:$C,'1. Income Statement'!$AR69,'Income Statement Source'!AD:AD)/1000 -> 0.40844 | AC69: =SUMIF('Income Statement Source'!$C:$C,'1. Income Statement'!$AR69,'Income Statement Source'!AE:AE)/1000 -> 0.39954 | AD69: =SUM(R69:AC69) -> 5.03398 | AE69: =SUMIF('Income Statement Source'!$C:$C,'1. Income Statement'!$AR69,'Income Statement Source'!AG:AG)/1000 -> 0.37792 | AF69: =SUMIF('Income Statement Source'!$C:$C,'1. Income Statement'!$AR69,'Income Statement Source'!AH:AH)/1000 -> 0.38678 | AG69: =SUMIF('Income Statement Source'!$C:$C,'1. Income Statement'!$AR69,'Income Statement Source'!AI:AI)/1000 -> 0.40543 | AH69: =SUMIF('Income Statement Source'!$C:$C,'1. Income Statement'!$AR69,'Income Statement Source'!AJ:AJ)/1000 -> 0.39469 | AI69: =SUMIF('Income Statement Source'!$C:$C,'1. Income Statement'!$AR69,'Income Statement Source'!AK:AK)/1000 -> 0.39346 | AJ69: =SUMIF('Income Statement Source'!$C:$C,'1. Income Statement'!$AR69,'Income Statement Source'!AL:AL)/1000 -> 0.45342 | AK69: =SUMIF('Income Statement Source'!$C:$C,'1. Income Statement'!$AR69,'Income Statement Source'!AM:AM)/1000 -> 0.4155 | AL69: =SUMIF('Income Statement Source'!$C:$C,'1. Income Statement'!$AR69,'Income Statement Source'!AN:AN)/1000 -> 0.40695 | AM69: =SUMIF('Income Statement Source'!$C:$C,'1. Income Statement'!$AR69,'Income Statement Source'!AO:AO)/1000 -> 0.42278 | AN69: =SUMIF('Income Statement Source'!$C:$C,'1. Income Statement'!$AR69,'Income Statement Source'!AP:AP)/1000 -> 0.45257 | AO69: =SUM(AE69:AN69) -> 4.1095 | AP69: =SUM(AO69,AB69:AC69) -> 4.91748 | AR69: Office Supplies
B70: =+B64 -> Facilities | E70: =SUM(E65:E69) -> 7.99723 | F70: =SUM(F65:F69) -> 7.93995 | G70: =SUM(G65:G69) -> 8.00571 | H70: =SUM(H65:H69) -> 7.97474 | I70: =SUM(I65:I69) -> 7.90943 | J70: =SUM(J65:J69) -> 7.90779 | K70: =SUM(K65:K69) -> 7.95553 | L70: =SUM(L65:L69) -> 7.9446 | ... AP70: =SUM(AP65:AP69) -> 95.12622
E71: =IFERROR(E70/E$19,0) -> 0.042095997 | F71: =IFERROR(F70/F$19,0) -> 0.034934702 | G71: =IFERROR(G70/G$19,0) -> 0.026025051 | H71: =IFERROR(H70/H$19,0) -> 0.030832903 | I71: =IFERROR(I70/I$19,0) -> 0.029102646 | J71: =IFERROR(J70/J$19,0) -> 0.021473675 | K71: =IFERROR(K70/K$19,0) -> 0.026299569 | L71: =IFERROR(L70/L$19,0) -> 0.028657838 | ... AP71: =IFERROR(AP70/AP$19,0) -> 0.022428708
B72: Vehicle
B73: =+AR73 -> Vehicle Lease Payments | E73: =SUMIF('Income Statement Source'!$C:$C,'1. Income Statement'!$AR73,'Income Statement Source'!G:G)/1000 -> 2.39045 | F73: =SUMIF('Income Statement Source'!$C:$C,'1. Income Statement'!$AR73,'Income Statement Source'!H:H)/1000 -> 2.37978 | G73: =SUMIF('Income Statement Source'!$C:$C,'1. Income Statement'!$AR73,'Income Statement Source'!I:I)/1000 -> 2.38826 | H73: =SUMIF('Income Statement Source'!$C:$C,'1. Income Statement'!$AR73,'Income Statement Source'!J:J)/1000 -> 2.42227 | I73: =SUMIF('Income Statement Source'!$C:$C,'1. Income Statement'!$AR73,'Income Statement Source'!K:K)/1000 -> 2.4117 | J73: =SUMIF('Income Statement Source'!$C:$C,'1. Income Statement'!$AR73,'Income Statement Source'!L:L)/1000 -> 2.41112 | K73: =SUMIF('Income Statement Source'!$C:$C,'1. Income Statement'!$AR73,'Income Statement Source'!M:M)/1000 -> 2.38956 | L73: =SUMIF('Income Statement Source'!$C:$C,'1. Income Statement'!$AR73,'Income Statement Source'!N:N)/1000 -> 2.3956 | M73: =SUMIF('Income Statement Source'!$C:$C,'1. Income Statement'!$AR73,'Income Statement Source'!O:O)/1000 -> 2.39981 | N73: =SUMIF('Income Statement Source'!$C:$C,'1. Income Statement'!$AR73,'Income Statement Source'!P:P)/1000 -> 2.39135 | O73: =SUMIF('Income Statement Source'!$C:$C,'1. Income Statement'!$AR73,'Income Statement Source'!Q:Q)/1000 -> 2.38446 | P73: =SUMIF('Income Statement Source'!$C:$C,'1. Income Statement'!$AR73,'Income Statement Source'!R:R)/1000 -> 2.39671 | Q73: =SUM(E73:P73) -> 28.76107 | R73: =SUMIF('Income Statement Source'!$C:$C,'1. Income Statement'!$AR73,'Income Statement Source'!T:T)/1000 -> 2.37684 | S73: =SUMIF('Income Statement Source'!$C:$C,'1. Income Statement'!$AR73,'Income Statement Source'!U:U)/1000 -> 2.39436 | T73: =SUMIF('Income Statement Source'!$C:$C,'1. Income Statement'!$AR73,'Income Statement Source'!V:V)/1000 -> 2.41522 | U73: =SUMIF('Income Statement Source'!$C:$C,'1. Income Statement'!$AR73,'Income Statement Source'!W:W)/1000 -> 2.38057 | V73: =SUMIF('Income Statement Source'!$C:$C,'1. Income Statement'!$AR73,'Income Statement Source'!X:X)/1000 -> 2.40756 | W73: =SUMIF('Income Statement Source'!$C:$C,'1. Income Statement'!$AR73,'Income Statement Source'!Y:Y)/1000 -> 2.4051 | X73: =SUMIF('Income Statement Source'!$C:$C,'1. Income Statement'!$AR73,'Income Statement Source'!Z:Z)/1000 -> 2.42166 | Y73: =SUMIF('Income Statement Source'!$C:$C,'1. Income Statement'!$AR73,'Income Statement Source'!AA:AA)/1000 -> 2.39385 | Z73: =SUMIF('Income Statement Source'!$C:$C,'1. Income Statement'!$AR73,'Income Statement Source'!AB:AB)/1000 -> 2.38729 | AA73: =SUMIF('Income Statement Source'!$C:$C,'1. Income Statement'!$AR73,'Income Statement Source'!AC:AC)/1000 -> 2.40311 | AB73: =SUMIF('Income Statement Source'!$C:$C,'1. Income Statement'!$AR73,'Income Statement Source'!AD:AD)/1000 -> 2.38481 | AC73: =SUMIF('Income Statement Source'!$C:$C,'1. Income Statement'!$AR73,'Income Statement Source'!AE:AE)/1000 -> 2.39712 | AD73: =SUM(R73:AC73) -> 28.76749 | AE73: =SUMIF('Income Statement Source'!$C:$C,'1. Income Statement'!$AR73,'Income Statement Source'!AG:AG)/1000 -> 2.39845 | AF73: =SUMIF('Income Statement Source'!$C:$C,'1. Income Statement'!$AR73,'Income Statement Source'!AH:AH)/1000 -> 2.40447 | AG73: =SUMIF('Income Statement Source'!$C:$C,'1. Income Statement'!$AR73,'Income Statement Source'!AI:AI)/1000 -> 2.40628 | AH73: =SUMIF('Income Statement Source'!$C:$C,'1. Income Statement'!$AR73,'Income Statement Source'!AJ:AJ)/1000 -> 2.40911 | AI73: =SUMIF('Income Statement Source'!$C:$C,'1. Income Statement'!$AR73,'Income Statement Source'!AK:AK)/1000 -> 2.39184 | AJ73: =SUMIF('Income Statement Source'!$C:$C,'1. Income Statement'!$AR73,'Income Statement Source'!AL:AL)/1000 -> 2.39853 | AK73: =SUMIF('Income Statement Source'!$C:$C,'1. Income Statement'!$AR73,'Income Statement Source'!AM:AM)/1000 -> 2.40037 | AL73: =SUMIF('Income Statement Source'!$C:$C,'1. Income Statement'!$AR73,'Income Statement Source'!AN:AN)/1000 -> 2.3908 | AM73: =SUMIF('Income Statement Source'!$C:$C,'1. Income Statement'!$AR73,'Income Statement Source'!AO:AO)/1000 -> 2.42271 | AN73: =SUMIF('Income Statement Source'!$C:$C,'1. Income Statement'!$AR73,'Income Statement Source'!AP:AP)/1000 -> 2.39011 | AO73: =SUM(AE73:AN73) -> 24.01267 | AP73: =SUM(AO73,AB73:AC73) -> 28.7946 | AR73: Vehicle Lease Payments
B74: =+AR74 -> Vehicle Insurance | E74: =SUMIF('Income Statement Source'!$C:$C,'1. Income Statement'!$AR74,'Income Statement Source'!G:G)/1000 -> 1.83733 | F74: =SUMIF('Income Statement Source'!$C:$C,'1. Income Statement'!$AR74,'Income Statement Source'!H:H)/1000 -> 1.84865 | G74: =SUMIF('Income Statement Source'!$C:$C,'1. Income Statement'!$AR74,'Income Statement Source'!I:I)/1000 -> 1.8461 | H74: =SUMIF('Income Statement Source'!$C:$C,'1. Income Statement'!$AR74,'Income Statement Source'!J:J)/1000 -> 1.84535 | I74: =SUMIF('Income Statement Source'!$C:$C,'1. Income Statement'!$AR74,'Income Statement Source'!K:K)/1000 -> 1.85083 | J74: =SUMIF('Income Statement Source'!$C:$C,'1. Income Statement'!$AR74,'Income Statement Source'!L:L)/1000 -> 1.82865 | K74: =SUMIF('Income Statement Source'!$C:$C,'1. Income Statement'!$AR74,'Income Statement Source'!M:M)/1000 -> 1.82821 | L74: =SUMIF('Income Statement Source'!$C:$C,'1. Income Statement'!$AR74,'Income Statement Source'!N:N)/1000 -> 1.84477 | M74: =SUMIF('Income Statement Source'!$C:$C,'1. Income Statement'!$AR74,'Income Statement Source'!O:O)/1000 -> 1.84928 | N74: =SUMIF('Income Statement Source'!$C:$C,'1. Income Statement'!$AR74,'Income Statement Source'!P:P)/1000 -> 1.86658 | O74: =SUMIF('Income Statement Source'!$C:$C,'1. Income Statement'!$AR74,'Income Statement Source'!Q:Q)/1000 -> 1.87201 | P74: =SUMIF('Income Statement Source'!$C:$C,'1. Income Statement'!$AR74,'Income Statement Source'!R:R)/1000 -> 1.82305 | Q74: =SUM(E74:P74) -> 22.14081 | R74: =SUMIF('Income Statement Source'!$C:$C,'1. Income Statement'!$AR74,'Income Statement Source'!T:T)/1000 -> 1.8451 | S74: =SUMIF('Income Statement Source'!$C:$C,'1. Income Statement'!$AR74,'Income Statement Source'!U:U)/1000 -> 1.85221 | T74: =SUMIF('Income Statement Source'!$C:$C,'1. Income Statement'!$AR74,'Income Statement Source'!V:V)/1000 -> 1.8251 | U74: =SUMIF('Income Statement Source'!$C:$C,'1. Income Statement'!$AR74,'Income Statement Source'!W:W)/1000 -> 1.87045 | V74: =SUMIF('Income Statement Source'!$C:$C,'1. Income Statement'!$AR74,'Income Statement Source'!X:X)/1000 -> 1.85907 | W74: =SUMIF('Income Statement Source'!$C:$C,'1. Income Statement'!$AR74,'Income Statement Source'!Y:Y)/1000 -> 1.82926 | X74: =SUMIF('Income Statement Source'!$C:$C,'1. Income Statement'!$AR74,'Income Statement Source'!Z:Z)/1000 -> 1.84164 | Y74: =SUMIF('Income Statement Source'!$C:$C,'1. Income Statement'!$AR74,'Income Statement Source'!AA:AA)/1000 -> 1.8611 | Z74: =SUMIF('Income Statement Source'!$C:$C,'1. Income Statement'!$AR74,'Income Statement Source'!AB:AB)/1000 -> 1.85225 | AA74: =SUMIF('Income Statement Source'!$C:$C,'1. Income Statement'!$AR74,'Income Statement Source'!AC:AC)/1000 -> 1.82978 | AB74: =SUMIF('Income Statement Source'!$C:$C,'1. Income Statement'!$AR74,'Income Statement Source'!AD:AD)/1000 -> 1.86952 | AC74: =SUMIF('Income Statement Source'!$C:$C,'1. Income Statement'!$AR74,'Income Statement Source'!AE:AE)/1000 -> 1.84067 | AD74: =SUM(R74:AC74) -> 22.17615 | AE74: =SUMIF('Income Statement Source'!$C:$C,'1. Income Statement'!$AR74,'Income Statement Source'!AG:AG)/1000 -> 1.83466 | AF74: =SUMIF('Income Statement Source'!$C:$C,'1. Income Statement'!$AR74,'Income Statement Source'!AH:AH)/1000 -> 1.87626 | AG74: =SUMIF('Income Statement Source'!$C:$C,'1. Income Statement'!$AR74,'Income Statement Source'!AI:AI)/1000 -> 1.83064 | AH74: =SUMIF('Income Statement Source'!$C:$C,'1. Income Statement'!$AR74,'Income Statement Source'!AJ:AJ)/1000 -> 1.86258 | AI74: =SUMIF('Income Statement Source'!$C:$C,'1. Income Statement'!$AR74,'Income Statement Source'!AK:AK)/1000 -> 1.82388 | AJ74: =SUMIF('Income Statement Source'!$C:$C,'1. Income Statement'!$AR74,'Income Statement Source'!AL:AL)/1000 -> 1.85714 | AK74: =SUMIF('Income Statement Source'!$C:$C,'1. Income Statement'!$AR74,'Income Statement Source'!AM:AM)/1000 -> 1.83087 | AL74: =SUMIF('Income Statement Source'!$C:$C,'1. Income Statement'!$AR74,'Income Statement Source'!AN:AN)/1000 -> 1.83479 | AM74: =SUMIF('Income Statement Source'!$C:$C,'1. Income Statement'!$AR74,'Income Statement Source'!AO:AO)/1000 -> 1.86277 | AN74: =SUMIF('Income Statement Source'!$C:$C,'1. Income Statement'!$AR74,'Income Statement Source'!AP:AP)/1000 -> 1.8737 | AO74: =SUM(AE74:AN74) -> 18.48729 | AP74: =SUM(AO74,AB74:AC74) -> 22.19748 | AR74: Vehicle Insurance
B75: =+AR75 -> Vehicle Maintenance & Repairs | E75: =SUMIF('Income Statement Source'!$C:$C,'1. Income Statement'!$AR75,'Income Statement Source'!G:G)/1000 -> 1.21384 | F75: =SUMIF('Income Statement Source'!$C:$C,'1. Income Statement'!$AR75,'Income Statement Source'!H:H)/1000 -> 1.17275 | G75: =SUMIF('Income Statement Source'!$C:$C,'1. Income Statement'!$AR75,'Income Statement Source'!I:I)/1000 -> 12.22096 | H75: =SUMIF('Income Statement Source'!$C:$C,'1. Income Statement'!$AR75,'Income Statement Source'!J:J)/1000 -> 1.11063 | I75: =SUMIF('Income Statement Source'!$C:$C,'1. Income Statement'!$AR75,'Income Statement Source'!K:K)/1000 -> 1.28072 | J75: =SUMIF('Income Statement Source'!$C:$C,'1. Income Statement'!$AR75,'Income Statement Source'!L:L)/1000 -> 1.19189 | K75: =SUMIF('Income Statement Source'!$C:$C,'1. Income Statement'!$AR75,'Income Statement Source'!M:M)/1000 -> 1.37468 | L75: =SUMIF('Income Statement Source'!$C:$C,'1. Income Statement'!$AR75,'Income Statement Source'!N:N)/1000 -> 1.14992 | M75: =SUMIF('Income Statement Source'!$C:$C,'1. Income Statement'!$AR75,'Income Statement Source'!O:O)/1000 -> 1.21087 | N75: =SUMIF('Income Statement Source'!$C:$C,'1. Income Statement'!$AR75,'Income Statement Source'!P:P)/1000 -> 1.32869 | O75: =SUMIF('Income Statement Source'!$C:$C,'1. Income Statement'!$AR75,'Income Statement Source'!Q:Q)/1000 -> 1.26574 | P75: =SUMIF('Income Statement Source'!$C:$C,'1. Income Statement'!$AR75,'Income Statement Source'!R:R)/1000 -> 1.27057 | Q75: =SUM(E75:P75) -> 25.79126 | R75: =SUMIF('Income Statement Source'!$C:$C,'1. Income Statement'!$AR75,'Income Statement Source'!T:T)/1000 -> 1.12865 | S75: =SUMIF('Income Statement Source'!$C:$C,'1. Income Statement'!$AR75,'Income Statement Source'!U:U)/1000 -> 1.19591 | T75: =SUMIF('Income Statement Source'!$C:$C,'1. Income Statement'!$AR75,'Income Statement Source'!V:V)/1000 -> 1.05366 | U75: =SUMIF('Income Statement Source'!$C:$C,'1. Income Statement'!$AR75,'Income Statement Source'!W:W)/1000 -> 1.27308 | V75: =SUMIF('Income Statement Source'!$C:$C,'1. Income Statement'!$AR75,'Income Statement Source'!X:X)/1000 -> 1.11864 | W75: =SUMIF('Income Statement Source'!$C:$C,'1. Income Statement'!$AR75,'Income Statement Source'!Y:Y)/1000 -> 1.17742 | X75: =SUMIF('Income Statement Source'!$C:$C,'1. Income Statement'!$AR75,'Income Statement Source'!Z:Z)/1000 -> 1.03879 | Y75: =SUMIF('Income Statement Source'!$C:$C,'1. Income Statement'!$AR75,'Income Statement Source'!AA:AA)/1000 -> 12.44096 | Z75: =SUMIF('Income Statement Source'!$C:$C,'1. Income Statement'!$AR75,'Income Statement Source'!AB:AB)/1000 -> 1.31 | AA75: =SUMIF('Income Statement Source'!$C:$C,'1. Income Statement'!$AR75,'Income Statement Source'!AC:AC)/1000 -> 51.07048 | AB75: =SUMIF('Income Statement Source'!$C:$C,'1. Income Statement'!$AR75,'Income Statement Source'!AD:AD)/1000 -> 1.28773 | AC75: =SUMIF('Income Statement Source'!$C:$C,'1. Income Statement'!$AR75,'Income Statement Source'!AE:AE)/1000 -> 1.08956 | AD75: =SUM(R75:AC75) -> 75.18488 | AE75: =SUMIF('Income Statement Source'!$C:$C,'1. Income Statement'!$AR75,'Income Statement Source'!AG:AG)/1000 -> 1.12341 | AF75: =SUMIF('Income Statement Source'!$C:$C,'1. Income Statement'!$AR75,'Income Statement Source'!AH:AH)/1000 -> 1.22651 | AG75: =SUMIF('Income Statement Source'!$C:$C,'1. Income Statement'!$AR75,'Income Statement Source'!AI:AI)/1000 -> 1.35092 | AH75: =SUMIF('Income Statement Source'!$C:$C,'1. Income Statement'!$AR75,'Income Statement Source'!AJ:AJ)/1000 -> 1.25665 | AI75: =SUMIF('Income Statement Source'!$C:$C,'1. Income Statement'!$AR75,'Income Statement Source'!AK:AK)/1000 -> 1.14858 | AJ75: =SUMIF('Income Statement Source'!$C:$C,'1. Income Statement'!$AR75,'Income Statement Source'!AL:AL)/1000 -> 11.70469 | AK75: =SUMIF('Income Statement Source'!$C:$C,'1. Income Statement'!$AR75,'Income Statement Source'!AM:AM)/1000 -> 1.04587 | AL75: =SUMIF('Income Statement Source'!$C:$C,'1. Income Statement'!$AR75,'Income Statement Source'!AN:AN)/1000 -> 1.34318 | AM75: =SUMIF('Income Statement Source'!$C:$C,'1. Income Statement'!$AR75,'Income Statement Source'!AO:AO)/1000 -> 1.20415 | AN75: =SUMIF('Income Statement Source'!$C:$C,'1. Income Statement'!$AR75,'Income Statement Source'!AP:AP)/1000 -> 1.12298 | AO75: =SUM(AE75:AN75) -> 22.52694 | AP75: =SUM(AO75,AB75:AC75) -> 24.90423 | AR75: Vehicle Maintenance & Repairs
B76: =+AR76 -> Fuel - Non-Job Related | E76: =SUMIF('Income Statement Source'!$C:$C,'1. Income Statement'!$AR76,'Income Statement Source'!G:G)/1000 -> 0.92413 | F76: =SUMIF('Income Statement Source'!$C:$C,'1. Income Statement'!$AR76,'Income Statement Source'!H:H)/1000 -> 0.85147 | G76: =SUMIF('Income Statement Source'!$C:$C,'1. Income Statement'!$AR76,'Income Statement Source'!I:I)/1000 -> 0.98949 | H76: =SUMIF('Income Statement Source'!$C:$C,'1. Income Statement'!$AR76,'Income Statement Source'!J:J)/1000 -> 0.97193 | I76: =SUMIF('Income Statement Source'!$C:$C,'1. Income Statement'!$AR76,'Income Statement Source'!K:K)/1000 -> 0.96023 | J76: =SUMIF('Income Statement Source'!$C:$C,'1. Income Statement'!$AR76,'Income Statement Source'!L:L)/1000 -> 0.98939 | K76: =SUMIF('Income Statement Source'!$C:$C,'1. Income Statement'!$AR76,'Income Statement Source'!M:M)/1000 -> 0.97775 | L76: =SUMIF('Income Statement Source'!$C:$C,'1. Income Statement'!$AR76,'Income Statement Source'!N:N)/1000 -> 0.92433 | M76: =SUMIF('Income Statement Source'!$C:$C,'1. Income Statement'!$AR76,'Income Statement Source'!O:O)/1000 -> 0.90942 | N76: =SUMIF('Income Statement Source'!$C:$C,'1. Income Statement'!$AR76,'Income Statement Source'!P:P)/1000 -> 0.9248 | O76: =SUMIF('Income Statement Source'!$C:$C,'1. Income Statement'!$AR76,'Income Statement Source'!Q:Q)/1000 -> 0.91832 | P76: =SUMIF('Income Statement Source'!$C:$C,'1. Income Statement'!$AR76,'Income Statement Source'!R:R)/1000 -> 0.92246 | Q76: =SUM(E76:P76) -> 11.26372 | R76: =SUMIF('Income Statement Source'!$C:$C,'1. Income Statement'!$AR76,'Income Statement Source'!T:T)/1000 -> 0.87728 | S76: =SUMIF('Income Statement Source'!$C:$C,'1. Income Statement'!$AR76,'Income Statement Source'!U:U)/1000 -> 0.87892 | T76: =SUMIF('Income Statement Source'!$C:$C,'1. Income Statement'!$AR76,'Income Statement Source'!V:V)/1000 -> 0.83742 | U76: =SUMIF('Income Statement Source'!$C:$C,'1. Income Statement'!$AR76,'Income Statement Source'!W:W)/1000 -> 0.82381 | V76: =SUMIF('Income Statement Source'!$C:$C,'1. Income Statement'!$AR76,'Income Statement Source'!X:X)/1000 -> 0.89787 | W76: =SUMIF('Income Statement Source'!$C:$C,'1. Income Statement'!$AR76,'Income Statement Source'!Y:Y)/1000 -> 0.91058 | X76: =SUMIF('Income Statement Source'!$C:$C,'1. Income Statement'!$AR76,'Income Statement Source'!Z:Z)/1000 -> 0.84126 | Y76: =SUMIF('Income Statement Source'!$C:$C,'1. Income Statement'!$AR76,'Income Statement Source'!AA:AA)/1000 -> 0.88457 | Z76: =SUMIF('Income Statement Source'!$C:$C,'1. Income Statement'!$AR76,'Income Statement Source'!AB:AB)/1000 -> 0.8949 | AA76: =SUMIF('Income Statement Source'!$C:$C,'1. Income Statement'!$AR76,'Income Statement Source'!AC:AC)/1000 -> 0.90396 | AB76: =SUMIF('Income Statement Source'!$C:$C,'1. Income Statement'!$AR76,'Income Statement Source'!AD:AD)/1000 -> 0.95161 | AC76: =SUMIF('Income Statement Source'!$C:$C,'1. Income Statement'!$AR76,'Income Statement Source'!AE:AE)/1000 -> 0.95352 | AD76: =SUM(R76:AC76) -> 10.6557 | AE76: =SUMIF('Income Statement Source'!$C:$C,'1. Income Statement'!$AR76,'Income Statement Source'!AG:AG)/1000 -> 0.83651 | AF76: =SUMIF('Income Statement Source'!$C:$C,'1. Income Statement'!$AR76,'Income Statement Source'!AH:AH)/1000 -> 0.82992 | AG76: =SUMIF('Income Statement Source'!$C:$C,'1. Income Statement'!$AR76,'Income Statement Source'!AI:AI)/1000 -> 0.98085 | AH76: =SUMIF('Income Statement Source'!$C:$C,'1. Income Statement'!$AR76,'Income Statement Source'!AJ:AJ)/1000 -> 0.91642 | AI76: =SUMIF('Income Statement Source'!$C:$C,'1. Income Statement'!$AR76,'Income Statement Source'!AK:AK)/1000 -> 0.82037 | AJ76: =SUMIF('Income Statement Source'!$C:$C,'1. Income Statement'!$AR76,'Income Statement Source'!AL:AL)/1000 -> 0.91207 | AK76: =SUMIF('Income Statement Source'!$C:$C,'1. Income Statement'!$AR76,'Income Statement Source'!AM:AM)/1000 -> 0.84752 | AL76: =SUMIF('Income Statement Source'!$C:$C,'1. Income Statement'!$AR76,'Income Statement Source'!AN:AN)/1000 -> 0.838 | AM76: =SUMIF('Income Statement Source'!$C:$C,'1. Income Statement'!$AR76,'Income Statement Source'!AO:AO)/1000 -> 0.83267 | AN76: =SUMIF('Income Statement Source'!$C:$C,'1. Income Statement'!$AR76,'Income Statement Source'!AP:AP)/1000 -> 0.87022 | AO76: =SUM(AE76:AN76) -> 8.68455 | AP76: =SUM(AO76,AB76:AC76) -> 10.58968 | AR76: Fuel - Non-Job Related
B77: =+B72 -> Vehicle | E77: =SUM(E73:E76) -> 6.36575 | F77: =SUM(F73:F76) -> 6.25265 | G77: =SUM(G73:G76) -> 17.44481 | H77: =SUM(H73:H76) -> 6.35018 | I77: =SUM(I73:I76) -> 6.50348 | J77: =SUM(J73:J76) -> 6.42105 | K77: =SUM(K73:K76) -> 6.5702 | L77: =SUM(L73:L76) -> 6.31462 | ... AP77: =SUM(AP73:AP76) -> 86.48599
E78: =IFERROR(E77/E$19,0) -> 0.033508176 | F78: =IFERROR(F77/F$19,0) -> 0.027510811 | G78: =IFERROR(G77/G$19,0) -> 0.056709783 | H78: =IFERROR(H77/H$19,0) -> 0.024551833 | I78: =IFERROR(I77/I$19,0) -> 0.023929471 | J78: =IFERROR(J77/J$19,0) -> 0.017436419 | K78: =IFERROR(K77/K$19,0) -> 0.021719914 | L78: =IFERROR(L77/L$19,0) -> 0.022778158 | ... AP78: =IFERROR(AP77/AP$19,0) -> 0.020391528
B79: Professional Fees
B80: =+AR80 -> Accounting & Bookkeeping | E80: =SUMIF('Income Statement Source'!$C:$C,'1. Income Statement'!$AR80,'Income Statement Source'!G:G)/1000 -> 0 | F80: =SUMIF('Income Statement Source'!$C:$C,'1. Income Statement'!$AR80,'Income Statement Source'!H:H)/1000 -> 0 | G80: =SUMIF('Income Statement Source'!$C:$C,'1. Income Statement'!$AR80,'Income Statement Source'!I:I)/1000 -> 0 | H80: =SUMIF('Income Statement Source'!$C:$C,'1. Income Statement'!$AR80,'Income Statement Source'!J:J)/1000 -> 0 | I80: =SUMIF('Income Statement Source'!$C:$C,'1. Income Statement'!$AR80,'Income Statement Source'!K:K)/1000 -> 6.27409 | J80: =SUMIF('Income Statement Source'!$C:$C,'1. Income Statement'!$AR80,'Income Statement Source'!L:L)/1000 -> 0 | K80: =SUMIF('Income Statement Source'!$C:$C,'1. Income Statement'!$AR80,'Income Statement Source'!M:M)/1000 -> 0 | L80: =SUMIF('Income Statement Source'!$C:$C,'1. Income Statement'!$AR80,'Income Statement Source'!N:N)/1000 -> 0 | M80: =SUMIF('Income Statement Source'!$C:$C,'1. Income Statement'!$AR80,'Income Statement Source'!O:O)/1000 -> 0 | N80: =SUMIF('Income Statement Source'!$C:$C,'1. Income Statement'!$AR80,'Income Statement Source'!P:P)/1000 -> 0 | O80: =SUMIF('Income Statement Source'!$C:$C,'1. Income Statement'!$AR80,'Income Statement Source'!Q:Q)/1000 -> 0 | P80: =SUMIF('Income Statement Source'!$C:$C,'1. Income Statement'!$AR80,'Income Statement Source'!R:R)/1000 -> 0 | Q80: =SUM(E80:P80) -> 6.27409 | R80: =SUMIF('Income Statement Source'!$C:$C,'1. Income Statement'!$AR80,'Income Statement Source'!T:T)/1000 -> 0 | S80: =SUMIF('Income Statement Source'!$C:$C,'1. Income Statement'!$AR80,'Income Statement Source'!U:U)/1000 -> 0 | T80: =SUMIF('Income Statement Source'!$C:$C,'1. Income Statement'!$AR80,'Income Statement Source'!V:V)/1000 -> 0 | U80: =SUMIF('Income Statement Source'!$C:$C,'1. Income Statement'!$AR80,'Income Statement Source'!W:W)/1000 -> 0 | V80: =SUMIF('Income Statement Source'!$C:$C,'1. Income Statement'!$AR80,'Income Statement Source'!X:X)/1000 -> 6.46748 | W80: =SUMIF('Income Statement Source'!$C:$C,'1. Income Statement'!$AR80,'Income Statement Source'!Y:Y)/1000 -> 0 | X80: =SUMIF('Income Statement Source'!$C:$C,'1. Income Statement'!$AR80,'Income Statement Source'!Z:Z)/1000 -> 0 | Y80: =SUMIF('Income Statement Source'!$C:$C,'1. Income Statement'!$AR80,'Income Statement Source'!AA:AA)/1000 -> 0 | Z80: =SUMIF('Income Statement Source'!$C:$C,'1. Income Statement'!$AR80,'Income Statement Source'!AB:AB)/1000 -> 0 | AA80: =SUMIF('Income Statement Source'!$C:$C,'1. Income Statement'!$AR80,'Income Statement Source'!AC:AC)/1000 -> 0 | AB80: =SUMIF('Income Statement Source'!$C:$C,'1. Income Statement'!$AR80,'Income Statement Source'!AD:AD)/1000 -> 0 | AC80: =SUMIF('Income Statement Source'!$C:$C,'1. Income Statement'!$AR80,'Income Statement Source'!AE:AE)/1000 -> 0 | AD80: =SUM(R80:AC80) -> 6.46748 | AE80: =SUMIF('Income Statement Source'!$C:$C,'1. Income Statement'!$AR80,'Income Statement Source'!AG:AG)/1000 -> 0 | AF80: =SUMIF('Income Statement Source'!$C:$C,'1. Income Statement'!$AR80,'Income Statement Source'!AH:AH)/1000 -> 0 | AG80: =SUMIF('Income Statement Source'!$C:$C,'1. Income Statement'!$AR80,'Income Statement Source'!AI:AI)/1000 -> 0 | AH80: =SUMIF('Income Statement Source'!$C:$C,'1. Income Statement'!$AR80,'Income Statement Source'!AJ:AJ)/1000 -> 0 | AI80: =SUMIF('Income Statement Source'!$C:$C,'1. Income Statement'!$AR80,'Income Statement Source'!AK:AK)/1000 -> 6.41099 | AJ80: =SUMIF('Income Statement Source'!$C:$C,'1. Income Statement'!$AR80,'Income Statement Source'!AL:AL)/1000 -> 0 | AK80: =SUMIF('Income Statement Source'!$C:$C,'1. Income Statement'!$AR80,'Income Statement Source'!AM:AM)/1000 -> 0 | AL80: =SUMIF('Income Statement Source'!$C:$C,'1. Income Statement'!$AR80,'Income Statement Source'!AN:AN)/1000 -> 0 | AM80: =SUMIF('Income Statement Source'!$C:$C,'1. Income Statement'!$AR80,'Income Statement Source'!AO:AO)/1000 -> 0 | AN80: =SUMIF('Income Statement Source'!$C:$C,'1. Income Statement'!$AR80,'Income Statement Source'!AP:AP)/1000 -> 0 | AO80: =SUM(AE80:AN80) -> 6.41099 | AP80: =SUM(AO80,AB80:AC80) -> 6.41099 | AR80: Accounting & Bookkeeping
B81: =+AR81 -> Legal & Professional Fees | E81: =SUMIF('Income Statement Source'!$C:$C,'1. Income Statement'!$AR81,'Income Statement Source'!G:G)/1000 -> 0.86091 | F81: =SUMIF('Income Statement Source'!$C:$C,'1. Income Statement'!$AR81,'Income Statement Source'!H:H)/1000 -> 0.73604 | G81: =SUMIF('Income Statement Source'!$C:$C,'1. Income Statement'!$AR81,'Income Statement Source'!I:I)/1000 -> 0.85017 | H81: =SUMIF('Income Statement Source'!$C:$C,'1. Income Statement'!$AR81,'Income Statement Source'!J:J)/1000 -> 0.8769 | I81: =SUMIF('Income Statement Source'!$C:$C,'1. Income Statement'!$AR81,'Income Statement Source'!K:K)/1000 -> 0.75289 | J81: =SUMIF('Income Statement Source'!$C:$C,'1. Income Statement'!$AR81,'Income Statement Source'!L:L)/1000 -> 100 | K81: =SUMIF('Income Statement Source'!$C:$C,'1. Income Statement'!$AR81,'Income Statement Source'!M:M)/1000 -> 0.76148 | L81: =SUMIF('Income Statement Source'!$C:$C,'1. Income Statement'!$AR81,'Income Statement Source'!N:N)/1000 -> 0.95118 | M81: =SUMIF('Income Statement Source'!$C:$C,'1. Income Statement'!$AR81,'Income Statement Source'!O:O)/1000 -> 0.77742 | N81: =SUMIF('Income Statement Source'!$C:$C,'1. Income Statement'!$AR81,'Income Statement Source'!P:P)/1000 -> 0.67777 | O81: =SUMIF('Income Statement Source'!$C:$C,'1. Income Statement'!$AR81,'Income Statement Source'!Q:Q)/1000 -> 0.81264 | P81: =SUMIF('Income Statement Source'!$C:$C,'1. Income Statement'!$AR81,'Income Statement Source'!R:R)/1000 -> 0.89518 | Q81: =SUM(E81:P81) -> 108.95258 | R81: =SUMIF('Income Statement Source'!$C:$C,'1. Income Statement'!$AR81,'Income Statement Source'!T:T)/1000 -> 0.75682 | S81: =SUMIF('Income Statement Source'!$C:$C,'1. Income Statement'!$AR81,'Income Statement Source'!U:U)/1000 -> 0.66384 | T81: =SUMIF('Income Statement Source'!$C:$C,'1. Income Statement'!$AR81,'Income Statement Source'!V:V)/1000 -> 0.76411 | U81: =SUMIF('Income Statement Source'!$C:$C,'1. Income Statement'!$AR81,'Income Statement Source'!W:W)/1000 -> 0.79324 | V81: =SUMIF('Income Statement Source'!$C:$C,'1. Income Statement'!$AR81,'Income Statement Source'!X:X)/1000 -> 0.74615 | W81: =SUMIF('Income Statement Source'!$C:$C,'1. Income Statement'!$AR81,'Income Statement Source'!Y:Y)/1000 -> 0.64738 | X81: =SUMIF('Income Statement Source'!$C:$C,'1. Income Statement'!$AR81,'Income Statement Source'!Z:Z)/1000 -> 0.72443 | Y81: =SUMIF('Income Statement Source'!$C:$C,'1. Income Statement'!$AR81,'Income Statement Source'!AA:AA)/1000 -> 0.7582 | Z81: =SUMIF('Income Statement Source'!$C:$C,'1. Income Statement'!$AR81,'Income Statement Source'!AB:AB)/1000 -> 0.86105 | AA81: =SUMIF('Income Statement Source'!$C:$C,'1. Income Statement'!$AR81,'Income Statement Source'!AC:AC)/1000 -> 0.75066 | AB81: =SUMIF('Income Statement Source'!$C:$C,'1. Income Statement'!$AR81,'Income Statement Source'!AD:AD)/1000 -> 0.7257 | AC81: =SUMIF('Income Statement Source'!$C:$C,'1. Income Statement'!$AR81,'Income Statement Source'!AE:AE)/1000 -> 0.8329 | AD81: =SUM(R81:AC81) -> 9.02448 | AE81: =SUMIF('Income Statement Source'!$C:$C,'1. Income Statement'!$AR81,'Income Statement Source'!AG:AG)/1000 -> 0.88825 | AF81: =SUMIF('Income Statement Source'!$C:$C,'1. Income Statement'!$AR81,'Income Statement Source'!AH:AH)/1000 -> 0.65092 | AG81: =SUMIF('Income Statement Source'!$C:$C,'1. Income Statement'!$AR81,'Income Statement Source'!AI:AI)/1000 -> 0.9355 | AH81: =SUMIF('Income Statement Source'!$C:$C,'1. Income Statement'!$AR81,'Income Statement Source'!AJ:AJ)/1000 -> 0.69685 | AI81: =SUMIF('Income Statement Source'!$C:$C,'1. Income Statement'!$AR81,'Income Statement Source'!AK:AK)/1000 -> 0.72776 | AJ81: =SUMIF('Income Statement Source'!$C:$C,'1. Income Statement'!$AR81,'Income Statement Source'!AL:AL)/1000 -> 0.92704 | AK81: =SUMIF('Income Statement Source'!$C:$C,'1. Income Statement'!$AR81,'Income Statement Source'!AM:AM)/1000 -> 0.8127 | AL81: =SUMIF('Income Statement Source'!$C:$C,'1. Income Statement'!$AR81,'Income Statement Source'!AN:AN)/1000 -> 0.8881 | AM81: =SUMIF('Income Statement Source'!$C:$C,'1. Income Statement'!$AR81,'Income Statement Source'!AO:AO)/1000 -> 0.7857 | AN81: =SUMIF('Income Statement Source'!$C:$C,'1. Income Statement'!$AR81,'Income Statement Source'!AP:AP)/1000 -> 0.7588 | AO81: =SUM(AE81:AN81) -> 8.07162 | AP81: =SUM(AO81,AB81:AC81) -> 9.63022 | AR81: Legal & Professional Fees
B82: =+B79 -> Professional Fees | E82: =SUM(E80:E81) -> 0.86091 | F82: =SUM(F80:F81) -> 0.73604 | G82: =SUM(G80:G81) -> 0.85017 | H82: =SUM(H80:H81) -> 0.8769 | I82: =SUM(I80:I81) -> 7.02698 | J82: =SUM(J80:J81) -> 100 | K82: =SUM(K80:K81) -> 0.76148 | L82: =SUM(L80:L81) -> 0.95118 | ... AP82: =SUM(AP80:AP81) -> 16.04121
E83: =IFERROR(E82/E$19,0) -> 0.0045316772 | F83: =IFERROR(F82/F$19,0) -> 0.0032384761 | G83: =IFERROR(G82/G$19,0) -> 0.0027637421 | H83: =IFERROR(H82/H$19,0) -> 0.0033903766 | I83: =IFERROR(I82/I$19,0) -> 0.025855682 | J83: =IFERROR(J82/J$19,0) -> 0.2715509 | K83: =IFERROR(K82/K$19,0) -> 0.0025173176 | L83: =IFERROR(L82/L$19,0) -> 0.0034311057 | ... AP83: =IFERROR(AP82/AP$19,0) -> 0.0037821709
B84: Other
B85: =+AR85 -> Computer & Software | E85: =SUMIF('Income Statement Source'!$C:$C,'1. Income Statement'!$AR85,'Income Statement Source'!G:G)/1000 -> 0.9063 | F85: =SUMIF('Income Statement Source'!$C:$C,'1. Income Statement'!$AR85,'Income Statement Source'!H:H)/1000 -> 0.93315 | G85: =SUMIF('Income Statement Source'!$C:$C,'1. Income Statement'!$AR85,'Income Statement Source'!I:I)/1000 -> 0.91414 | H85: =SUMIF('Income Statement Source'!$C:$C,'1. Income Statement'!$AR85,'Income Statement Source'!J:J)/1000 -> 0.87052 | I85: =SUMIF('Income Statement Source'!$C:$C,'1. Income Statement'!$AR85,'Income Statement Source'!K:K)/1000 -> 0.85879 | J85: =SUMIF('Income Statement Source'!$C:$C,'1. Income Statement'!$AR85,'Income Statement Source'!L:L)/1000 -> 0.89161 | K85: =SUMIF('Income Statement Source'!$C:$C,'1. Income Statement'!$AR85,'Income Statement Source'!M:M)/1000 -> 0.86604 | L85: =SUMIF('Income Statement Source'!$C:$C,'1. Income Statement'!$AR85,'Income Statement Source'!N:N)/1000 -> 0.87714 | M85: =SUMIF('Income Statement Source'!$C:$C,'1. Income Statement'!$AR85,'Income Statement Source'!O:O)/1000 -> 0.94899 | N85: =SUMIF('Income Statement Source'!$C:$C,'1. Income Statement'!$AR85,'Income Statement Source'!P:P)/1000 -> 0.89352 | O85: =SUMIF('Income Statement Source'!$C:$C,'1. Income Statement'!$AR85,'Income Statement Source'!Q:Q)/1000 -> 0.93354 | P85: =SUMIF('Income Statement Source'!$C:$C,'1. Income Statement'!$AR85,'Income Statement Source'!R:R)/1000 -> 0.92283 | Q85: =SUM(E85:P85) -> 10.81657 | R85: =SUMIF('Income Statement Source'!$C:$C,'1. Income Statement'!$AR85,'Income Statement Source'!T:T)/1000 -> 0.91003 | S85: =SUMIF('Income Statement Source'!$C:$C,'1. Income Statement'!$AR85,'Income Statement Source'!U:U)/1000 -> 0.83402 | T85: =SUMIF('Income Statement Source'!$C:$C,'1. Income Statement'!$AR85,'Income Statement Source'!V:V)/1000 -> 0.86178 | U85: =SUMIF('Income Statement Source'!$C:$C,'1. Income Statement'!$AR85,'Income Statement Source'!W:W)/1000 -> 0.8554 | V85: =SUMIF('Income Statement Source'!$C:$C,'1. Income Statement'!$AR85,'Income Statement Source'!X:X)/1000 -> 0.84943 | W85: =SUMIF('Income Statement Source'!$C:$C,'1. Income Statement'!$AR85,'Income Statement Source'!Y:Y)/1000 -> 0.94277 | X85: =SUMIF('Income Statement Source'!$C:$C,'1. Income Statement'!$AR85,'Income Statement Source'!Z:Z)/1000 -> 0.95629 | Y85: =SUMIF('Income Statement Source'!$C:$C,'1. Income Statement'!$AR85,'Income Statement Source'!AA:AA)/1000 -> 0.95155 | Z85: =SUMIF('Income Statement Source'!$C:$C,'1. Income Statement'!$AR85,'Income Statement Source'!AB:AB)/1000 -> 0.87422 | AA85: =SUMIF('Income Statement Source'!$C:$C,'1. Income Statement'!$AR85,'Income Statement Source'!AC:AC)/1000 -> 0.85491 | AB85: =SUMIF('Income Statement Source'!$C:$C,'1. Income Statement'!$AR85,'Income Statement Source'!AD:AD)/1000 -> 0.93612 | AC85: =SUMIF('Income Statement Source'!$C:$C,'1. Income Statement'!$AR85,'Income Statement Source'!AE:AE)/1000 -> 0.857 | AD85: =SUM(R85:AC85) -> 10.68352 | AE85: =SUMIF('Income Statement Source'!$C:$C,'1. Income Statement'!$AR85,'Income Statement Source'!AG:AG)/1000 -> 0.84021 | AF85: =SUMIF('Income Statement Source'!$C:$C,'1. Income Statement'!$AR85,'Income Statement Source'!AH:AH)/1000 -> 0.92209 | AG85: =SUMIF('Income Statement Source'!$C:$C,'1. Income Statement'!$AR85,'Income Statement Source'!AI:AI)/1000 -> 0.95109 | AH85: =SUMIF('Income Statement Source'!$C:$C,'1. Income Statement'!$AR85,'Income Statement Source'!AJ:AJ)/1000 -> 0.85953 | AI85: =SUMIF('Income Statement Source'!$C:$C,'1. Income Statement'!$AR85,'Income Statement Source'!AK:AK)/1000 -> 0.9542 | AJ85: =SUMIF('Income Statement Source'!$C:$C,'1. Income Statement'!$AR85,'Income Statement Source'!AL:AL)/1000 -> 0.83484 | AK85: =SUMIF('Income Statement Source'!$C:$C,'1. Income Statement'!$AR85,'Income Statement Source'!AM:AM)/1000 -> 0.86564 | AL85: =SUMIF('Income Statement Source'!$C:$C,'1. Income Statement'!$AR85,'Income Statement Source'!AN:AN)/1000 -> 0.86397 | AM85: =SUMIF('Income Statement Source'!$C:$C,'1. Income Statement'!$AR85,'Income Statement Source'!AO:AO)/1000 -> 0.87864 | AN85: =SUMIF('Income Statement Source'!$C:$C,'1. Income Statement'!$AR85,'Income Statement Source'!AP:AP)/1000 -> 0.91394 | AO85: =SUM(AE85:AN85) -> 8.88415 | AP85: =SUM(AO85,AB85:AC85) -> 10.67727 | AR85: Computer & Software
B86: =+AR86 -> Licenses & Permits | E86: =SUMIF('Income Statement Source'!$C:$C,'1. Income Statement'!$AR86,'Income Statement Source'!G:G)/1000 -> 0.38182 | F86: =SUMIF('Income Statement Source'!$C:$C,'1. Income Statement'!$AR86,'Income Statement Source'!H:H)/1000 -> 0.33845 | G86: =SUMIF('Income Statement Source'!$C:$C,'1. Income Statement'!$AR86,'Income Statement Source'!I:I)/1000 -> 0.35331 | H86: =SUMIF('Income Statement Source'!$C:$C,'1. Income Statement'!$AR86,'Income Statement Source'!J:J)/1000 -> 0.30821 | I86: =SUMIF('Income Statement Source'!$C:$C,'1. Income Statement'!$AR86,'Income Statement Source'!K:K)/1000 -> 0.32221 | J86: =SUMIF('Income Statement Source'!$C:$C,'1. Income Statement'!$AR86,'Income Statement Source'!L:L)/1000 -> 0.3935 | K86: =SUMIF('Income Statement Source'!$C:$C,'1. Income Statement'!$AR86,'Income Statement Source'!M:M)/1000 -> 0.32785 | L86: =SUMIF('Income Statement Source'!$C:$C,'1. Income Statement'!$AR86,'Income Statement Source'!N:N)/1000 -> 0.3925 | M86: =SUMIF('Income Statement Source'!$C:$C,'1. Income Statement'!$AR86,'Income Statement Source'!O:O)/1000 -> 0.3764 | N86: =SUMIF('Income Statement Source'!$C:$C,'1. Income Statement'!$AR86,'Income Statement Source'!P:P)/1000 -> 0.32902 | O86: =SUMIF('Income Statement Source'!$C:$C,'1. Income Statement'!$AR86,'Income Statement Source'!Q:Q)/1000 -> 0.31828 | P86: =SUMIF('Income Statement Source'!$C:$C,'1. Income Statement'!$AR86,'Income Statement Source'!R:R)/1000 -> 0.39639 | Q86: =SUM(E86:P86) -> 4.23794 | R86: =SUMIF('Income Statement Source'!$C:$C,'1. Income Statement'!$AR86,'Income Statement Source'!T:T)/1000 -> 0.39196 | S86: =SUMIF('Income Statement Source'!$C:$C,'1. Income Statement'!$AR86,'Income Statement Source'!U:U)/1000 -> 0.34997 | T86: =SUMIF('Income Statement Source'!$C:$C,'1. Income Statement'!$AR86,'Income Statement Source'!V:V)/1000 -> 0.40022 | U86: =SUMIF('Income Statement Source'!$C:$C,'1. Income Statement'!$AR86,'Income Statement Source'!W:W)/1000 -> 0.34367 | V86: =SUMIF('Income Statement Source'!$C:$C,'1. Income Statement'!$AR86,'Income Statement Source'!X:X)/1000 -> 0.33327 | W86: =SUMIF('Income Statement Source'!$C:$C,'1. Income Statement'!$AR86,'Income Statement Source'!Y:Y)/1000 -> 0.38302 | X86: =SUMIF('Income Statement Source'!$C:$C,'1. Income Statement'!$AR86,'Income Statement Source'!Z:Z)/1000 -> 0.33744 | Y86: =SUMIF('Income Statement Source'!$C:$C,'1. Income Statement'!$AR86,'Income Statement Source'!AA:AA)/1000 -> 0.3753 | Z86: =SUMIF('Income Statement Source'!$C:$C,'1. Income Statement'!$AR86,'Income Statement Source'!AB:AB)/1000 -> 0.30314 | AA86: =SUMIF('Income Statement Source'!$C:$C,'1. Income Statement'!$AR86,'Income Statement Source'!AC:AC)/1000 -> 0.36714 | AB86: =SUMIF('Income Statement Source'!$C:$C,'1. Income Statement'!$AR86,'Income Statement Source'!AD:AD)/1000 -> 0.38732 | AC86: =SUMIF('Income Statement Source'!$C:$C,'1. Income Statement'!$AR86,'Income Statement Source'!AE:AE)/1000 -> 0.31195 | AD86: =SUM(R86:AC86) -> 4.2844 | AE86: =SUMIF('Income Statement Source'!$C:$C,'1. Income Statement'!$AR86,'Income Statement Source'!AG:AG)/1000 -> 0.38845 | AF86: =SUMIF('Income Statement Source'!$C:$C,'1. Income Statement'!$AR86,'Income Statement Source'!AH:AH)/1000 -> 0.3098 | AG86: =SUMIF('Income Statement Source'!$C:$C,'1. Income Statement'!$AR86,'Income Statement Source'!AI:AI)/1000 -> 0.32974 | AH86: =SUMIF('Income Statement Source'!$C:$C,'1. Income Statement'!$AR86,'Income Statement Source'!AJ:AJ)/1000 -> 0.35299 | AI86: =SUMIF('Income Statement Source'!$C:$C,'1. Income Statement'!$AR86,'Income Statement Source'!AK:AK)/1000 -> 0.32307 | AJ86: =SUMIF('Income Statement Source'!$C:$C,'1. Income Statement'!$AR86,'Income Statement Source'!AL:AL)/1000 -> 0.35146 | AK86: =SUMIF('Income Statement Source'!$C:$C,'1. Income Statement'!$AR86,'Income Statement Source'!AM:AM)/1000 -> 0.37349 | AL86: =SUMIF('Income Statement Source'!$C:$C,'1. Income Statement'!$AR86,'Income Statement Source'!AN:AN)/1000 -> 0.37891 | AM86: =SUMIF('Income Statement Source'!$C:$C,'1. Income Statement'!$AR86,'Income Statement Source'!AO:AO)/1000 -> 0.34784 | AN86: =SUMIF('Income Statement Source'!$C:$C,'1. Income Statement'!$AR86,'Income Statement Source'!AP:AP)/1000 -> 0.33967 | AO86: =SUM(AE86:AN86) -> 3.49542 | AP86: =SUM(AO86,AB86:AC86) -> 4.19469 | AR86: Licenses & Permits
B87: =+AR87 -> Advertising & Marketing | E87: =SUMIF('Income Statement Source'!$C:$C,'1. Income Statement'!$AR87,'Income Statement Source'!G:G)/1000 -> 1.73243 | F87: =SUMIF('Income Statement Source'!$C:$C,'1. Income Statement'!$AR87,'Income Statement Source'!H:H)/1000 -> 2.0247 | G87: =SUMIF('Income Statement Source'!$C:$C,'1. Income Statement'!$AR87,'Income Statement Source'!I:I)/1000 -> 1.85216 | H87: =SUMIF('Income Statement Source'!$C:$C,'1. Income Statement'!$AR87,'Income Statement Source'!J:J)/1000 -> 1.69243 | I87: =SUMIF('Income Statement Source'!$C:$C,'1. Income Statement'!$AR87,'Income Statement Source'!K:K)/1000 -> 1.87918 | J87: =SUMIF('Income Statement Source'!$C:$C,'1. Income Statement'!$AR87,'Income Statement Source'!L:L)/1000 -> 1.71208 | K87: =SUMIF('Income Statement Source'!$C:$C,'1. Income Statement'!$AR87,'Income Statement Source'!M:M)/1000 -> 1.65886 | L87: =SUMIF('Income Statement Source'!$C:$C,'1. Income Statement'!$AR87,'Income Statement Source'!N:N)/1000 -> 1.99721 | M87: =SUMIF('Income Statement Source'!$C:$C,'1. Income Statement'!$AR87,'Income Statement Source'!O:O)/1000 -> 1.56025 | N87: =SUMIF('Income Statement Source'!$C:$C,'1. Income Statement'!$AR87,'Income Statement Source'!P:P)/1000 -> 2.07288 | O87: =SUMIF('Income Statement Source'!$C:$C,'1. Income Statement'!$AR87,'Income Statement Source'!Q:Q)/1000 -> 1.72837 | P87: =SUMIF('Income Statement Source'!$C:$C,'1. Income Statement'!$AR87,'Income Statement Source'!R:R)/1000 -> 1.48987 | Q87: =SUM(E87:P87) -> 21.40042 | R87: =SUMIF('Income Statement Source'!$C:$C,'1. Income Statement'!$AR87,'Income Statement Source'!T:T)/1000 -> 1.98134 | S87: =SUMIF('Income Statement Source'!$C:$C,'1. Income Statement'!$AR87,'Income Statement Source'!U:U)/1000 -> 1.7866 | T87: =SUMIF('Income Statement Source'!$C:$C,'1. Income Statement'!$AR87,'Income Statement Source'!V:V)/1000 -> 1.80292 | U87: =SUMIF('Income Statement Source'!$C:$C,'1. Income Statement'!$AR87,'Income Statement Source'!W:W)/1000 -> 1.73046 | V87: =SUMIF('Income Statement Source'!$C:$C,'1. Income Statement'!$AR87,'Income Statement Source'!X:X)/1000 -> 2.01585 | W87: =SUMIF('Income Statement Source'!$C:$C,'1. Income Statement'!$AR87,'Income Statement Source'!Y:Y)/1000 -> 1.64891 | X87: =SUMIF('Income Statement Source'!$C:$C,'1. Income Statement'!$AR87,'Income Statement Source'!Z:Z)/1000 -> 1.93585 | Y87: =SUMIF('Income Statement Source'!$C:$C,'1. Income Statement'!$AR87,'Income Statement Source'!AA:AA)/1000 -> 1.50279 | Z87: =SUMIF('Income Statement Source'!$C:$C,'1. Income Statement'!$AR87,'Income Statement Source'!AB:AB)/1000 -> 1.52645 | AA87: =SUMIF('Income Statement Source'!$C:$C,'1. Income Statement'!$AR87,'Income Statement Source'!AC:AC)/1000 -> 1.58394 | AB87: =SUMIF('Income Statement Source'!$C:$C,'1. Income Statement'!$AR87,'Income Statement Source'!AD:AD)/1000 -> 1.72615 | AC87: =SUMIF('Income Statement Source'!$C:$C,'1. Income Statement'!$AR87,'Income Statement Source'!AE:AE)/1000 -> 1.82209 | AD87: =SUM(R87:AC87) -> 21.06335 | AE87: =SUMIF('Income Statement Source'!$C:$C,'1. Income Statement'!$AR87,'Income Statement Source'!AG:AG)/1000 -> 1.58904 | AF87: =SUMIF('Income Statement Source'!$C:$C,'1. Income Statement'!$AR87,'Income Statement Source'!AH:AH)/1000 -> 1.84516 | AG87: =SUMIF('Income Statement Source'!$C:$C,'1. Income Statement'!$AR87,'Income Statement Source'!AI:AI)/1000 -> 2.06165 | AH87: =SUMIF('Income Statement Source'!$C:$C,'1. Income Statement'!$AR87,'Income Statement Source'!AJ:AJ)/1000 -> 1.65843 | AI87: =SUMIF('Income Statement Source'!$C:$C,'1. Income Statement'!$AR87,'Income Statement Source'!AK:AK)/1000 -> 1.97575 | AJ87: =SUMIF('Income Statement Source'!$C:$C,'1. Income Statement'!$AR87,'Income Statement Source'!AL:AL)/1000 -> 1.51463 | AK87: =SUMIF('Income Statement Source'!$C:$C,'1. Income Statement'!$AR87,'Income Statement Source'!AM:AM)/1000 -> 1.98973 | AL87: =SUMIF('Income Statement Source'!$C:$C,'1. Income Statement'!$AR87,'Income Statement Source'!AN:AN)/1000 -> 1.97723 | AM87: =SUMIF('Income Statement Source'!$C:$C,'1. Income Statement'!$AR87,'Income Statement Source'!AO:AO)/1000 -> 1.58515 | AN87: =SUMIF('Income Statement Source'!$C:$C,'1. Income Statement'!$AR87,'Income Statement Source'!AP:AP)/1000 -> 1.70563 | AO87: =SUM(AE87:AN87) -> 17.9024 | AP87: =SUM(AO87,AB87:AC87) -> 21.45064 | AR87: Advertising & Marketing
B88: =+AR88 -> Bank Fees & Charges | E88: =SUMIF('Income Statement Source'!$C:$C,'1. Income Statement'!$AR88,'Income Statement Source'!G:G)/1000 -> 0.27583 | F88: =SUMIF('Income Statement Source'!$C:$C,'1. Income Statement'!$AR88,'Income Statement Source'!H:H)/1000 -> 0.30188 | G88: =SUMIF('Income Statement Source'!$C:$C,'1. Income Statement'!$AR88,'Income Statement Source'!I:I)/1000 -> 0.30228 | H88: =SUMIF('Income Statement Source'!$C:$C,'1. Income Statement'!$AR88,'Income Statement Source'!J:J)/1000 -> 0.28605 | I88: =SUMIF('Income Statement Source'!$C:$C,'1. Income Statement'!$AR88,'Income Statement Source'!K:K)/1000 -> 0.26465 | J88: =SUMIF('Income Statement Source'!$C:$C,'1. Income Statement'!$AR88,'Income Statement Source'!L:L)/1000 -> 0.26922 | K88: =SUMIF('Income Statement Source'!$C:$C,'1. Income Statement'!$AR88,'Income Statement Source'!M:M)/1000 -> 0.29402 | L88: =SUMIF('Income Statement Source'!$C:$C,'1. Income Statement'!$AR88,'Income Statement Source'!N:N)/1000 -> 0.28761 | M88: =SUMIF('Income Statement Source'!$C:$C,'1. Income Statement'!$AR88,'Income Statement Source'!O:O)/1000 -> 0.28283 | N88: =SUMIF('Income Statement Source'!$C:$C,'1. Income Statement'!$AR88,'Income Statement Source'!P:P)/1000 -> 0.30582 | O88: =SUMIF('Income Statement Source'!$C:$C,'1. Income Statement'!$AR88,'Income Statement Source'!Q:Q)/1000 -> 0.26872 | P88: =SUMIF('Income Statement Source'!$C:$C,'1. Income Statement'!$AR88,'Income Statement Source'!R:R)/1000 -> 0.28573 | Q88: =SUM(E88:P88) -> 3.42464 | R88: =SUMIF('Income Statement Source'!$C:$C,'1. Income Statement'!$AR88,'Income Statement Source'!T:T)/1000 -> 0.30776 | S88: =SUMIF('Income Statement Source'!$C:$C,'1. Income Statement'!$AR88,'Income Statement Source'!U:U)/1000 -> 0.2566 | T88: =SUMIF('Income Statement Source'!$C:$C,'1. Income Statement'!$AR88,'Income Statement Source'!V:V)/1000 -> 0.27591 | U88: =SUMIF('Income Statement Source'!$C:$C,'1. Income Statement'!$AR88,'Income Statement Source'!W:W)/1000 -> 0.25916 | V88: =SUMIF('Income Statement Source'!$C:$C,'1. Income Statement'!$AR88,'Income Statement Source'!X:X)/1000 -> 0.29778 | W88: =SUMIF('Income Statement Source'!$C:$C,'1. Income Statement'!$AR88,'Income Statement Source'!Y:Y)/1000 -> 0.27502 | X88: =SUMIF('Income Statement Source'!$C:$C,'1. Income Statement'!$AR88,'Income Statement Source'!Z:Z)/1000 -> 0.2724 | Y88: =SUMIF('Income Statement Source'!$C:$C,'1. Income Statement'!$AR88,'Income Statement Source'!AA:AA)/1000 -> 0.27504 | Z88: =SUMIF('Income Statement Source'!$C:$C,'1. Income Statement'!$AR88,'Income Statement Source'!AB:AB)/1000 -> 0.30572 | AA88: =SUMIF('Income Statement Source'!$C:$C,'1. Income Statement'!$AR88,'Income Statement Source'!AC:AC)/1000 -> 0.30121 | AB88: =SUMIF('Income Statement Source'!$C:$C,'1. Income Statement'!$AR88,'Income Statement Source'!AD:AD)/1000 -> 0.30768 | AC88: =SUMIF('Income Statement Source'!$C:$C,'1. Income Statement'!$AR88,'Income Statement Source'!AE:AE)/1000 -> 0.29667 | AD88: =SUM(R88:AC88) -> 3.43095 | AE88: =SUMIF('Income Statement Source'!$C:$C,'1. Income Statement'!$AR88,'Income Statement Source'!AG:AG)/1000 -> 0.30168 | AF88: =SUMIF('Income Statement Source'!$C:$C,'1. Income Statement'!$AR88,'Income Statement Source'!AH:AH)/1000 -> 0.30565 | AG88: =SUMIF('Income Statement Source'!$C:$C,'1. Income Statement'!$AR88,'Income Statement Source'!AI:AI)/1000 -> 0.29719 | AH88: =SUMIF('Income Statement Source'!$C:$C,'1. Income Statement'!$AR88,'Income Statement Source'!AJ:AJ)/1000 -> 0.30152 | AI88: =SUMIF('Income Statement Source'!$C:$C,'1. Income Statement'!$AR88,'Income Statement Source'!AK:AK)/1000 -> 0.26689 | AJ88: =SUMIF('Income Statement Source'!$C:$C,'1. Income Statement'!$AR88,'Income Statement Source'!AL:AL)/1000 -> 0.25225 | AK88: =SUMIF('Income Statement Source'!$C:$C,'1. Income Statement'!$AR88,'Income Statement Source'!AM:AM)/1000 -> 0.25897 | AL88: =SUMIF('Income Statement Source'!$C:$C,'1. Income Statement'!$AR88,'Income Statement Source'!AN:AN)/1000 -> 0.2833 | AM88: =SUMIF('Income Statement Source'!$C:$C,'1. Income Statement'!$AR88,'Income Statement Source'!AO:AO)/1000 -> 0.30147 | AN88: =SUMIF('Income Statement Source'!$C:$C,'1. Income Statement'!$AR88,'Income Statement Source'!AP:AP)/1000 -> 0.26323 | AO88: =SUM(AE88:AN88) -> 2.83215 | AP88: =SUM(AO88,AB88:AC88) -> 3.4365 | AR88: Bank Fees & Charges
B89: =+AR89 -> Meals & Entertainment | E89: =SUMIF('Income Statement Source'!$C:$C,'1. Income Statement'!$AR89,'Income Statement Source'!G:G)/1000 -> 0.5829 | F89: =SUMIF('Income Statement Source'!$C:$C,'1. Income Statement'!$AR89,'Income Statement Source'!H:H)/1000 -> 0.6711 | G89: =SUMIF('Income Statement Source'!$C:$C,'1. Income Statement'!$AR89,'Income Statement Source'!I:I)/1000 -> 0.6982 | H89: =SUMIF('Income Statement Source'!$C:$C,'1. Income Statement'!$AR89,'Income Statement Source'!J:J)/1000 -> 0.67987 | I89: =SUMIF('Income Statement Source'!$C:$C,'1. Income Statement'!$AR89,'Income Statement Source'!K:K)/1000 -> 0.70922 | J89: =SUMIF('Income Statement Source'!$C:$C,'1. Income Statement'!$AR89,'Income Statement Source'!L:L)/1000 -> 0.67916 | K89: =SUMIF('Income Statement Source'!$C:$C,'1. Income Statement'!$AR89,'Income Statement Source'!M:M)/1000 -> 0.69217 | L89: =SUMIF('Income Statement Source'!$C:$C,'1. Income Statement'!$AR89,'Income Statement Source'!N:N)/1000 -> 0.71521 | M89: =SUMIF('Income Statement Source'!$C:$C,'1. Income Statement'!$AR89,'Income Statement Source'!O:O)/1000 -> 0.73026 | N89: =SUMIF('Income Statement Source'!$C:$C,'1. Income Statement'!$AR89,'Income Statement Source'!P:P)/1000 -> 0.70402 | O89: =SUMIF('Income Statement Source'!$C:$C,'1. Income Statement'!$AR89,'Income Statement Source'!Q:Q)/1000 -> 0.63376 | P89: =SUMIF('Income Statement Source'!$C:$C,'1. Income Statement'!$AR89,'Income Statement Source'!R:R)/1000 -> 0.72691 | Q89: =SUM(E89:P89) -> 8.22278 | R89: =SUMIF('Income Statement Source'!$C:$C,'1. Income Statement'!$AR89,'Income Statement Source'!T:T)/1000 -> 0.73623 | S89: =SUMIF('Income Statement Source'!$C:$C,'1. Income Statement'!$AR89,'Income Statement Source'!U:U)/1000 -> 0.62242 | T89: =SUMIF('Income Statement Source'!$C:$C,'1. Income Statement'!$AR89,'Income Statement Source'!V:V)/1000 -> 0.69141 | U89: =SUMIF('Income Statement Source'!$C:$C,'1. Income Statement'!$AR89,'Income Statement Source'!W:W)/1000 -> 0.73296 | V89: =SUMIF('Income Statement Source'!$C:$C,'1. Income Statement'!$AR89,'Income Statement Source'!X:X)/1000 -> 0.55257 | W89: =SUMIF('Income Statement Source'!$C:$C,'1. Income Statement'!$AR89,'Income Statement Source'!Y:Y)/1000 -> 0.62148 | X89: =SUMIF('Income Statement Source'!$C:$C,'1. Income Statement'!$AR89,'Income Statement Source'!Z:Z)/1000 -> 0.74709 | Y89: =SUMIF('Income Statement Source'!$C:$C,'1. Income Statement'!$AR89,'Income Statement Source'!AA:AA)/1000 -> 0.68764 | Z89: =SUMIF('Income Statement Source'!$C:$C,'1. Income Statement'!$AR89,'Income Statement Source'!AB:AB)/1000 -> 0.64415 | AA89: =SUMIF('Income Statement Source'!$C:$C,'1. Income Statement'!$AR89,'Income Statement Source'!AC:AC)/1000 -> 0.59289 | AB89: =SUMIF('Income Statement Source'!$C:$C,'1. Income Statement'!$AR89,'Income Statement Source'!AD:AD)/1000 -> 0.70985 | AC89: =SUMIF('Income Statement Source'!$C:$C,'1. Income Statement'!$AR89,'Income Statement Source'!AE:AE)/1000 -> 0.64311 | AD89: =SUM(R89:AC89) -> 7.9818 | AE89: =SUMIF('Income Statement Source'!$C:$C,'1. Income Statement'!$AR89,'Income Statement Source'!AG:AG)/1000 -> 0.57492 | AF89: =SUMIF('Income Statement Source'!$C:$C,'1. Income Statement'!$AR89,'Income Statement Source'!AH:AH)/1000 -> 0.71436 | AG89: =SUMIF('Income Statement Source'!$C:$C,'1. Income Statement'!$AR89,'Income Statement Source'!AI:AI)/1000 -> 0.72237 | AH89: =SUMIF('Income Statement Source'!$C:$C,'1. Income Statement'!$AR89,'Income Statement Source'!AJ:AJ)/1000 -> 0.68159 | AI89: =SUMIF('Income Statement Source'!$C:$C,'1. Income Statement'!$AR89,'Income Statement Source'!AK:AK)/1000 -> 0.58496 | AJ89: =SUMIF('Income Statement Source'!$C:$C,'1. Income Statement'!$AR89,'Income Statement Source'!AL:AL)/1000 -> 0.62612 | AK89: =SUMIF('Income Statement Source'!$C:$C,'1. Income Statement'!$AR89,'Income Statement Source'!AM:AM)/1000 -> 0.58819 | AL89: =SUMIF('Income Statement Source'!$C:$C,'1. Income Statement'!$AR89,'Income Statement Source'!AN:AN)/1000 -> 0.72182 | AM89: =SUMIF('Income Statement Source'!$C:$C,'1. Income Statement'!$AR89,'Income Statement Source'!AO:AO)/1000 -> 0.56905 | AN89: =SUMIF('Income Statement Source'!$C:$C,'1. Income Statement'!$AR89,'Income Statement Source'!AP:AP)/1000 -> 0.60929 | AO89: =SUM(AE89:AN89) -> 6.39267 | AP89: =SUM(AO89,AB89:AC89) -> 7.74563 | AR89: Meals & Entertainment
B90: =+AR90 -> Training & Education | E90: =SUMIF('Income Statement Source'!$C:$C,'1. Income Statement'!$AR90,'Income Statement Source'!G:G)/1000 -> 0.47972 | F90: =SUMIF('Income Statement Source'!$C:$C,'1. Income Statement'!$AR90,'Income Statement Source'!H:H)/1000 -> 0.36898 | G90: =SUMIF('Income Statement Source'!$C:$C,'1. Income Statement'!$AR90,'Income Statement Source'!I:I)/1000 -> 0.44345 | H90: =SUMIF('Income Statement Source'!$C:$C,'1. Income Statement'!$AR90,'Income Statement Source'!J:J)/1000 -> 0.4196 | I90: =SUMIF('Income Statement Source'!$C:$C,'1. Income Statement'!$AR90,'Income Statement Source'!K:K)/1000 -> 0.41008 | J90: =SUMIF('Income Statement Source'!$C:$C,'1. Income Statement'!$AR90,'Income Statement Source'!L:L)/1000 -> 0.46963 | K90: =SUMIF('Income Statement Source'!$C:$C,'1. Income Statement'!$AR90,'Income Statement Source'!M:M)/1000 -> 0.38048 | L90: =SUMIF('Income Statement Source'!$C:$C,'1. Income Statement'!$AR90,'Income Statement Source'!N:N)/1000 -> 0.36828 | M90: =SUMIF('Income Statement Source'!$C:$C,'1. Income Statement'!$AR90,'Income Statement Source'!O:O)/1000 -> 0.35897 | N90: =SUMIF('Income Statement Source'!$C:$C,'1. Income Statement'!$AR90,'Income Statement Source'!P:P)/1000 -> 0.43487 | O90: =SUMIF('Income Statement Source'!$C:$C,'1. Income Statement'!$AR90,'Income Statement Source'!Q:Q)/1000 -> 0.49741 | P90: =SUMIF('Income Statement Source'!$C:$C,'1. Income Statement'!$AR90,'Income Statement Source'!R:R)/1000 -> 0.48925 | Q90: =SUM(E90:P90) -> 5.12072 | R90: =SUMIF('Income Statement Source'!$C:$C,'1. Income Statement'!$AR90,'Income Statement Source'!T:T)/1000 -> 0.40045 | S90: =SUMIF('Income Statement Source'!$C:$C,'1. Income Statement'!$AR90,'Income Statement Source'!U:U)/1000 -> 0.44831 | T90: =SUMIF('Income Statement Source'!$C:$C,'1. Income Statement'!$AR90,'Income Statement Source'!V:V)/1000 -> 0.40945 | U90: =SUMIF('Income Statement Source'!$C:$C,'1. Income Statement'!$AR90,'Income Statement Source'!W:W)/1000 -> 0.32957 | V90: =SUMIF('Income Statement Source'!$C:$C,'1. Income Statement'!$AR90,'Income Statement Source'!X:X)/1000 -> 0.51224 | W90: =SUMIF('Income Statement Source'!$C:$C,'1. Income Statement'!$AR90,'Income Statement Source'!Y:Y)/1000 -> 0.40301 | X90: =SUMIF('Income Statement Source'!$C:$C,'1. Income Statement'!$AR90,'Income Statement Source'!Z:Z)/1000 -> 0.41002 | Y90: =SUMIF('Income Statement Source'!$C:$C,'1. Income Statement'!$AR90,'Income Statement Source'!AA:AA)/1000 -> 0.46026 | Z90: =SUMIF('Income Statement Source'!$C:$C,'1. Income Statement'!$AR90,'Income Statement Source'!AB:AB)/1000 -> 0.42084 | AA90: =SUMIF('Income Statement Source'!$C:$C,'1. Income Statement'!$AR90,'Income Statement Source'!AC:AC)/1000 -> 0.39106 | AB90: =SUMIF('Income Statement Source'!$C:$C,'1. Income Statement'!$AR90,'Income Statement Source'!AD:AD)/1000 -> 0.43663 | AC90: =SUMIF('Income Statement Source'!$C:$C,'1. Income Statement'!$AR90,'Income Statement Source'!AE:AE)/1000 -> 0.43779 | AD90: =SUM(R90:AC90) -> 5.05963 | AE90: =SUMIF('Income Statement Source'!$C:$C,'1. Income Statement'!$AR90,'Income Statement Source'!AG:AG)/1000 -> 0.47817 | AF90: =SUMIF('Income Statement Source'!$C:$C,'1. Income Statement'!$AR90,'Income Statement Source'!AH:AH)/1000 -> 0.36648 | AG90: =SUMIF('Income Statement Source'!$C:$C,'1. Income Statement'!$AR90,'Income Statement Source'!AI:AI)/1000 -> 0.51645 | AH90: =SUMIF('Income Statement Source'!$C:$C,'1. Income Statement'!$AR90,'Income Statement Source'!AJ:AJ)/1000 -> 0.41801 | AI90: =SUMIF('Income Statement Source'!$C:$C,'1. Income Statement'!$AR90,'Income Statement Source'!AK:AK)/1000 -> 0.40778 | AJ90: =SUMIF('Income Statement Source'!$C:$C,'1. Income Statement'!$AR90,'Income Statement Source'!AL:AL)/1000 -> 0.43768 | AK90: =SUMIF('Income Statement Source'!$C:$C,'1. Income Statement'!$AR90,'Income Statement Source'!AM:AM)/1000 -> 0.50001 | AL90: =SUMIF('Income Statement Source'!$C:$C,'1. Income Statement'!$AR90,'Income Statement Source'!AN:AN)/1000 -> 0.48143 | AM90: =SUMIF('Income Statement Source'!$C:$C,'1. Income Statement'!$AR90,'Income Statement Source'!AO:AO)/1000 -> 0.45516 | AN90: =SUMIF('Income Statement Source'!$C:$C,'1. Income Statement'!$AR90,'Income Statement Source'!AP:AP)/1000 -> 0.44149 | AO90: =SUM(AE90:AN90) -> 4.50266 | AP90: =SUM(AO90,AB90:AC90) -> 5.37708 | AR90: Training & Education
B91: =+AR91 -> Dues & Subscriptions | E91: =SUMIF('Income Statement Source'!$C:$C,'1. Income Statement'!$AR91,'Income Statement Source'!G:G)/1000 -> 0.36696 | F91: =SUMIF('Income Statement Source'!$C:$C,'1. Income Statement'!$AR91,'Income Statement Source'!H:H)/1000 -> 0.37003 | G91: =SUMIF('Income Statement Source'!$C:$C,'1. Income Statement'!$AR91,'Income Statement Source'!I:I)/1000 -> 0.35619 | H91: =SUMIF('Income Statement Source'!$C:$C,'1. Income Statement'!$AR91,'Income Statement Source'!J:J)/1000 -> 0.38764 | I91: =SUMIF('Income Statement Source'!$C:$C,'1. Income Statement'!$AR91,'Income Statement Source'!K:K)/1000 -> 0.38204 | J91: =SUMIF('Income Statement Source'!$C:$C,'1. Income Statement'!$AR91,'Income Statement Source'!L:L)/1000 -> 0.36982 | K91: =SUMIF('Income Statement Source'!$C:$C,'1. Income Statement'!$AR91,'Income Statement Source'!M:M)/1000 -> 0.3609 | L91: =SUMIF('Income Statement Source'!$C:$C,'1. Income Statement'!$AR91,'Income Statement Source'!N:N)/1000 -> 0.3828 | M91: =SUMIF('Income Statement Source'!$C:$C,'1. Income Statement'!$AR91,'Income Statement Source'!O:O)/1000 -> 0.38243 | N91: =SUMIF('Income Statement Source'!$C:$C,'1. Income Statement'!$AR91,'Income Statement Source'!P:P)/1000 -> 0.35483 | O91: =SUMIF('Income Statement Source'!$C:$C,'1. Income Statement'!$AR91,'Income Statement Source'!Q:Q)/1000 -> 0.35192 | P91: =SUMIF('Income Statement Source'!$C:$C,'1. Income Statement'!$AR91,'Income Statement Source'!R:R)/1000 -> 0.38121 | Q91: =SUM(E91:P91) -> 4.44677 | R91: =SUMIF('Income Statement Source'!$C:$C,'1. Income Statement'!$AR91,'Income Statement Source'!T:T)/1000 -> 0.38336 | S91: =SUMIF('Income Statement Source'!$C:$C,'1. Income Statement'!$AR91,'Income Statement Source'!U:U)/1000 -> 0.35246 | T91: =SUMIF('Income Statement Source'!$C:$C,'1. Income Statement'!$AR91,'Income Statement Source'!V:V)/1000 -> 0.36896 | U91: =SUMIF('Income Statement Source'!$C:$C,'1. Income Statement'!$AR91,'Income Statement Source'!W:W)/1000 -> 0.39415 | V91: =SUMIF('Income Statement Source'!$C:$C,'1. Income Statement'!$AR91,'Income Statement Source'!X:X)/1000 -> 0.37864 | W91: =SUMIF('Income Statement Source'!$C:$C,'1. Income Statement'!$AR91,'Income Statement Source'!Y:Y)/1000 -> 0.38452 | X91: =SUMIF('Income Statement Source'!$C:$C,'1. Income Statement'!$AR91,'Income Statement Source'!Z:Z)/1000 -> 0.39625 | Y91: =SUMIF('Income Statement Source'!$C:$C,'1. Income Statement'!$AR91,'Income Statement Source'!AA:AA)/1000 -> 0.35857 | Z91: =SUMIF('Income Statement Source'!$C:$C,'1. Income Statement'!$AR91,'Income Statement Source'!AB:AB)/1000 -> 0.39233 | AA91: =SUMIF('Income Statement Source'!$C:$C,'1. Income Statement'!$AR91,'Income Statement Source'!AC:AC)/1000 -> 0.35162 | AB91: =SUMIF('Income Statement Source'!$C:$C,'1. Income Statement'!$AR91,'Income Statement Source'!AD:AD)/1000 -> 0.3631 | AC91: =SUMIF('Income Statement Source'!$C:$C,'1. Income Statement'!$AR91,'Income Statement Source'!AE:AE)/1000 -> 0.38023 | AD91: =SUM(R91:AC91) -> 4.50419 | AE91: =SUMIF('Income Statement Source'!$C:$C,'1. Income Statement'!$AR91,'Income Statement Source'!AG:AG)/1000 -> 0.35881 | AF91: =SUMIF('Income Statement Source'!$C:$C,'1. Income Statement'!$AR91,'Income Statement Source'!AH:AH)/1000 -> 0.37038 | AG91: =SUMIF('Income Statement Source'!$C:$C,'1. Income Statement'!$AR91,'Income Statement Source'!AI:AI)/1000 -> 0.36746 | AH91: =SUMIF('Income Statement Source'!$C:$C,'1. Income Statement'!$AR91,'Income Statement Source'!AJ:AJ)/1000 -> 0.36084 | AI91: =SUMIF('Income Statement Source'!$C:$C,'1. Income Statement'!$AR91,'Income Statement Source'!AK:AK)/1000 -> 0.36679 | AJ91: =SUMIF('Income Statement Source'!$C:$C,'1. Income Statement'!$AR91,'Income Statement Source'!AL:AL)/1000 -> 0.3848 | AK91: =SUMIF('Income Statement Source'!$C:$C,'1. Income Statement'!$AR91,'Income Statement Source'!AM:AM)/1000 -> 0.40039 | AL91: =SUMIF('Income Statement Source'!$C:$C,'1. Income Statement'!$AR91,'Income Statement Source'!AN:AN)/1000 -> 0.38672 | AM91: =SUMIF('Income Statement Source'!$C:$C,'1. Income Statement'!$AR91,'Income Statement Source'!AO:AO)/1000 -> 0.36336 | AN91: =SUMIF('Income Statement Source'!$C:$C,'1. Income Statement'!$AR91,'Income Statement Source'!AP:AP)/1000 -> 0.38768 | AO91: =SUM(AE91:AN91) -> 3.74723 | AP91: =SUM(AO91,AB91:AC91) -> 4.49056 | AR91: Dues & Subscriptions
